Workbook

Sheet Lists
A1: ClientPriority | B1: RelationshipStatus | C1: LeadSource | D1: ProjectType | E1: FormulaOwnership | F1: YesNo | G1: YesNoPending | H1: Stage | I1: ProjectPriority | J1: WhoNeedsToAct | K1: AssignedTo | L1: GenderPositioning | M1: Concentration | N1: ProductType | O1: FragranceFamily | P1: Season | Q1: Occasion | R1: DayNight | S1: CommercialArtistic | T1: ExpenseCategory | U1: BusinessExpenseType | V1: PaymentMethod | W1: WaitingOn | X1: AgainDecision
A2: Low | B2: Lead | C2: Referral | D2: Personal Perfume | E2: Client Exclusive | F2: Yes | G2: Yes | H2: Brief | I2: Low | J2: Us | K2: =Instructions!$C$8 -> Person A | L2: Feminine | M2: Parfum / Extrait | N2: Fine Fragrance | O2: Floral | P2: Spring | Q2: Everyday | R2: Day | S2: Commercial | T2: Raw Materials | U2: Cost of Goods Sold | V2: Bank Transfer | W2: Us | X2: Yes
A3: Normal | B3: Quoted | C3: Instagram | D3: Brand Collection | E3: Perfumer Retains Rights | F3: No | G3: No | H3: Research | I3: Normal | J3: Client | K3: =Instructions!$C$9 -> Person B | L3: Masculine | M3: Eau de Parfum | N3: Home Fragrance | O3: Oriental / Amber | P3: Summer | Q3: Evening | R3: Night | S3: Artistic | T3: Alcohol/Carrier | U3: Operating Expense | V3: Card | W3: Client | X3: No
A4: High | B4: Signed | C4: Website | D4: Niche Line | E4: Shared | G4: Pending | H4: Concept Development | I4: High | J4: Third Party | K4: Both | L4: Unisex / Shared | M4: Eau de Toilette | N4: Personal Care | O4: Woody | P4: Autumn | Q4: Special Occasion | R4: Both | S4: Balanced | T4: Bottles | U4: Capital Expense | V4: PayPal | W4: Supplier | X4: Maybe
A5: VIP | B5: Active | C5: Google Search | D5: Private Label | E5: Licensed | H5: Formula Development | I5: Urgent | J5: Nobody – Complete | K5: Unassigned | L5: Not Specified | M5: Eau de Cologne | N5: Candle | O5: Fresh | P5: Winter | Q5: Office | T5: Sample Vials | V5: Stripe | W5: Nobody
B6: Completed | C6: Trade Show | D6: Corporate Gift | E6: Not Yet Agreed | H6: Compounding | M6: Fragrance Oil | N6: Diffuser | O6: Chypre | P6: All Year | Q6: Signature Scent | T6: Packaging | V6: Cash
B7: On Hold | C7: Existing Client | D7: Other | H7: Evaluation | N7: Other | O7: Fougere | T7: Labels | V7: Other
B8: Cancelled | C8: Other | H8: Sample Sent | O8: Gourmand | T8: Shipping
H9: Awaiting Feedback | O9: Aquatic | T9: Documentation
H10: Reformulation | O10: Green | T10: SDS
H11: Approved | O11: Citrus | T11: IFRA/Allergen
H12: Documentation | T12: CPSR
H13: Production | T13: Compounding
H14: Complete | T14: External Perfumer
H15: On Hold | T15: Testing
T16: Software
T17: Payment Fees
T18: Other

Sheet Dashboard
A1: PERFUMER STUDIO — Fragrance Development Dashboard
A2: ="Live view — updates automatically as you work. As of "&TEXT(TODAY(),"dddd, dd mmmm yyyy") -> Live view — updates automatically as you work. As of Monday, 17 August 2026
A4: KEY METRICS
B6: ACTIVE CLIENTS | F6: ACTIVE FRAGRANCE PROJECTS | J6: AWAITING CLIENT FEEDBACK | N6: REQUIRING ACTION FROM US | R6: APPROACHING DEADLINE (≤7D)
B7: =COUNTIF(Clients!$V$5:$V$44,"Active") -> 0 | F7: =SUMPRODUCT(('Fragrance Projects'!$A$5:$A$64<>"")*('Fragrance Projects'!$J$5:$J$64<>"Completed")*('Fragrance Projects'!$J$5:$J$64<>"On Hold")) -> 0 | J7: =COUNTIF('Fragrance Projects'!$H$5:$H$64,"Awaiting Feedback") -> 0 | N7: =COUNTIF('Fragrance Projects'!$O$5:$O$64,"Us") -> 0 | R7: =SUM('Fragrance Projects'!$AA$5:$AA$64) -> 0
B11: OVERDUE PROJECTS | F11: TOTAL CONTRACTED REVENUE | J11: REVENUE RECEIVED | N11: OUTSTANDING PAYMENTS | R11: TOTAL PROJECT EXPENSES
B12: =SUM('Fragrance Projects'!$Z$5:$Z$64) -> 0 | F12: =SUM('Project Financials'!$D$5:$D$64) -> 0 | J12: =SUM(Payments!$G$5:$G$64)+SUM(Payments!$K$5:$K$64) -> 0 | N12: =MAX(0,F12-J12) -> 0 | R12: =SUM('Expense Log'!$J$5:$J$154) -> 0
B16: ESTIMATED GROSS PROFIT | F16: AVERAGE PROFIT MARGIN % | J16: AVERAGE REVENUE PER CLIENT | N16: FORMULAS IN DEVELOPMENT | R16: APPROVED FORMULAS
B17: =F12-R12 -> 0 | F17: =IFERROR(AVERAGEIF('Project Financials'!$D$5:$D$64,">0",'Project Financials'!$AC$5:$AC$64),0) -> 0 | J17: =IFERROR(F12/B7,0) -> 0 | N17: =SUMPRODUCT(('Fragrance Projects'!$S$5:$S$64="No")*('Fragrance Projects'!$J$5:$J$64<>"Completed")*('Fragrance Projects'!$J$5:$J$64<>"On Hold")) -> 0 | R17: =COUNTIF('Fragrance Projects'!$T$5:$T$64,"Yes") -> 0
A21: URGENT ATTENTION — Needs You Now
A22: Client | B22: Fragrance | C22: Current Stage | D22: Days Remaining | E22: Next Action | F22: Why It's Flagged | G22: Assigned To
A23: =IFERROR(INDEX('Fragrance Projects'!$C$5:$C$64,SMALL('Fragrance Projects'!$AJ$5:$AJ$64,1)),"") | B23: =IFERROR(INDEX('Fragrance Projects'!$D$5:$D$64,SMALL('Fragrance Projects'!$AJ$5:$AJ$64,1)),"") | C23: =IFERROR(INDEX('Fragrance Projects'!$H$5:$H$64,SMALL('Fragrance Projects'!$AJ$5:$AJ$64,1)),"") | D23: =IFERROR(INDEX('Fragrance Projects'!$G$5:$G$64,SMALL('Fragrance Projects'!$AJ$5:$AJ$64,1)),"") | E23: =IFERROR(INDEX('Fragrance Projects'!$P$5:$P$64,SMALL('Fragrance Projects'!$AJ$5:$AJ$64,1)),"") | F23: =IFERROR(INDEX('Fragrance Projects'!$AH$5:$AH$64,SMALL('Fragrance Projects'!$AJ$5:$AJ$64,1)),"") | G23: =IFERROR(INDEX('Fragrance Projects'!$AK$5:$AK$64,SMALL('Fragrance Projects'!$AJ$5:$AJ$64,1)),"")
A24: =IFERROR(INDEX('Fragrance Projects'!$C$5:$C$64,SMALL('Fragrance Projects'!$AJ$5:$AJ$64,2)),"") | B24: =IFERROR(INDEX('Fragrance Projects'!$D$5:$D$64,SMALL('Fragrance Projects'!$AJ$5:$AJ$64,2)),"") | C24: =IFERROR(INDEX('Fragrance Projects'!$H$5:$H$64,SMALL('Fragrance Projects'!$AJ$5:$AJ$64,2)),"") | D24: =IFERROR(INDEX('Fragrance Projects'!$G$5:$G$64,SMALL('Fragrance Projects'!$AJ$5:$AJ$64,2)),"") | E24: =IFERROR(INDEX('Fragrance Projects'!$P$5:$P$64,SMALL('Fragrance Projects'!$AJ$5:$AJ$64,2)),"") | F24: =IFERROR(INDEX('Fragrance Projects'!$AH$5:$AH$64,SMALL('Fragrance Projects'!$AJ$5:$AJ$64,2)),"") | G24: =IFERROR(INDEX('Fragrance Projects'!$AK$5:$AK$64,SMALL('Fragrance Projects'!$AJ$5:$AJ$64,2)),"")
A25: =IFERROR(INDEX('Fragrance Projects'!$C$5:$C$64,SMALL('Fragrance Projects'!$AJ$5:$AJ$64,3)),"") | B25: =IFERROR(INDEX('Fragrance Projects'!$D$5:$D$64,SMALL('Fragrance Projects'!$AJ$5:$AJ$64,3)),"") | C25: =IFERROR(INDEX('Fragrance Projects'!$H$5:$H$64,SMALL('Fragrance Projects'!$AJ$5:$AJ$64,3)),"") | D25: =IFERROR(INDEX('Fragrance Projects'!$G$5:$G$64,SMALL('Fragrance Projects'!$AJ$5:$AJ$64,3)),"") | E25: =IFERROR(INDEX('Fragrance Projects'!$P$5:$P$64,SMALL('Fragrance Projects'!$AJ$5:$AJ$64,3)),"") | F25: =IFERROR(INDEX('Fragrance Projects'!$AH$5:$AH$64,SMALL('Fragrance Projects'!$AJ$5:$AJ$64,3)),"") | G25: =IFERROR(INDEX('Fragrance Projects'!$AK$5:$AK$64,SMALL('Fragrance Projects'!$AJ$5:$AJ$64,3)),"")
A26: =IFERROR(INDEX('Fragrance Projects'!$C$5:$C$64,SMALL('Fragrance Projects'!$AJ$5:$AJ$64,4)),"") | B26: =IFERROR(INDEX('Fragrance Projects'!$D$5:$D$64,SMALL('Fragrance Projects'!$AJ$5:$AJ$64,4)),"") | C26: =IFERROR(INDEX('Fragrance Projects'!$H$5:$H$64,SMALL('Fragrance Projects'!$AJ$5:$AJ$64,4)),"") | D26: =IFERROR(INDEX('Fragrance Projects'!$G$5:$G$64,SMALL('Fragrance Projects'!$AJ$5:$AJ$64,4)),"") | E26: =IFERROR(INDEX('Fragrance Projects'!$P$5:$P$64,SMALL('Fragrance Projects'!$AJ$5:$AJ$64,4)),"") | F26: =IFERROR(INDEX('Fragrance Projects'!$AH$5:$AH$64,SMALL('Fragrance Projects'!$AJ$5:$AJ$64,4)),"") | G26: =IFERROR(INDEX('Fragrance Projects'!$AK$5:$AK$64,SMALL('Fragrance Projects'!$AJ$5:$AJ$64,4)),"")
A27: =IFERROR(INDEX('Fragrance Projects'!$C$5:$C$64,SMALL('Fragrance Projects'!$AJ$5:$AJ$64,5)),"") | B27: =IFERROR(INDEX('Fragrance Projects'!$D$5:$D$64,SMALL('Fragrance Projects'!$AJ$5:$AJ$64,5)),"") | C27: =IFERROR(INDEX('Fragrance Projects'!$H$5:$H$64,SMALL('Fragrance Projects'!$AJ$5:$AJ$64,5)),"") | D27: =IFERROR(INDEX('Fragrance Projects'!$G$5:$G$64,SMALL('Fragrance Projects'!$AJ$5:$AJ$64,5)),"") | E27: =IFERROR(INDEX('Fragrance Projects'!$P$5:$P$64,SMALL('Fragrance Projects'!$AJ$5:$AJ$64,5)),"") | F27: =IFERROR(INDEX('Fragrance Projects'!$AH$5:$AH$64,SMALL('Fragrance Projects'!$AJ$5:$AJ$64,5)),"") | G27: =IFERROR(INDEX('Fragrance Projects'!$AK$5:$AK$64,SMALL('Fragrance Projects'!$AJ$5:$AJ$64,5)),"")
A28: =IFERROR(INDEX('Fragrance Projects'!$C$5:$C$64,SMALL('Fragrance Projects'!$AJ$5:$AJ$64,6)),"") | B28: =IFERROR(INDEX('Fragrance Projects'!$D$5:$D$64,SMALL('Fragrance Projects'!$AJ$5:$AJ$64,6)),"") | C28: =IFERROR(INDEX('Fragrance Projects'!$H$5:$H$64,SMALL('Fragrance Projects'!$AJ$5:$AJ$64,6)),"") | D28: =IFERROR(INDEX('Fragrance Projects'!$G$5:$G$64,SMALL('Fragrance Projects'!$AJ$5:$AJ$64,6)),"") | E28: =IFERROR(INDEX('Fragrance Projects'!$P$5:$P$64,SMALL('Fragrance Projects'!$AJ$5:$AJ$64,6)),"") | F28: =IFERROR(INDEX('Fragrance Projects'!$AH$5:$AH$64,SMALL('Fragrance Projects'!$AJ$5:$AJ$64,6)),"") | G28: =IFERROR(INDEX('Fragrance Projects'!$AK$5:$AK$64,SMALL('Fragrance Projects'!$AJ$5:$AJ$64,6)),"")
A29: =IFERROR(INDEX('Fragrance Projects'!$C$5:$C$64,SMALL('Fragrance Projects'!$AJ$5:$AJ$64,7)),"") | B29: =IFERROR(INDEX('Fragrance Projects'!$D$5:$D$64,SMALL('Fragrance Projects'!$AJ$5:$AJ$64,7)),"") | C29: =IFERROR(INDEX('Fragrance Projects'!$H$5:$H$64,SMALL('Fragrance Projects'!$AJ$5:$AJ$64,7)),"") | D29: =IFERROR(INDEX('Fragrance Projects'!$G$5:$G$64,SMALL('Fragrance Projects'!$AJ$5:$AJ$64,7)),"") | E29: =IFERROR(INDEX('Fragrance Projects'!$P$5:$P$64,SMALL('Fragrance Projects'!$AJ$5:$AJ$64,7)),"") | F29: =IFERROR(INDEX('Fragrance Projects'!$AH$5:$AH$64,SMALL('Fragrance Projects'!$AJ$5:$AJ$64,7)),"") | G29: =IFERROR(INDEX('Fragrance Projects'!$AK$5:$AK$64,SMALL('Fragrance Projects'!$AJ$5:$AJ$64,7)),"")
A30: =IFERROR(INDEX('Fragrance Projects'!$C$5:$C$64,SMALL('Fragrance Projects'!$AJ$5:$AJ$64,8)),"") | B30: =IFERROR(INDEX('Fragrance Projects'!$D$5:$D$64,SMALL('Fragrance Projects'!$AJ$5:$AJ$64,8)),"") | C30: =IFERROR(INDEX('Fragrance Projects'!$H$5:$H$64,SMALL('Fragrance Projects'!$AJ$5:$AJ$64,8)),"") | D30: =IFERROR(INDEX('Fragrance Projects'!$G$5:$G$64,SMALL('Fragrance Projects'!$AJ$5:$AJ$64,8)),"") | E30: =IFERROR(INDEX('Fragrance Projects'!$P$5:$P$64,SMALL('Fragrance Projects'!$AJ$5:$AJ$64,8)),"") | F30: =IFERROR(INDEX('Fragrance Projects'!$AH$5:$AH$64,SMALL('Fragrance Projects'!$AJ$5:$AJ$64,8)),"") | G30: =IFERROR(INDEX('Fragrance Projects'!$AK$5:$AK$64,SMALL('Fragrance Projects'!$AJ$5:$AJ$64,8)),"")
A31: =IFERROR(INDEX('Fragrance Projects'!$C$5:$C$64,SMALL('Fragrance Projects'!$AJ$5:$AJ$64,9)),"") | B31: =IFERROR(INDEX('Fragrance Projects'!$D$5:$D$64,SMALL('Fragrance Projects'!$AJ$5:$AJ$64,9)),"") | C31: =IFERROR(INDEX('Fragrance Projects'!$H$5:$H$64,SMALL('Fragrance Projects'!$AJ$5:$AJ$64,9)),"") | D31: =IFERROR(INDEX('Fragrance Projects'!$G$5:$G$64,SMALL('Fragrance Projects'!$AJ$5:$AJ$64,9)),"") | E31: =IFERROR(INDEX('Fragrance Projects'!$P$5:$P$64,SMALL('Fragrance Projects'!$AJ$5:$AJ$64,9)),"") | F31: =IFERROR(INDEX('Fragrance Projects'!$AH$5:$AH$64,SMALL('Fragrance Projects'!$AJ$5:$AJ$64,9)),"") | G31: =IFERROR(INDEX('Fragrance Projects'!$AK$5:$AK$64,SMALL('Fragrance Projects'!$AJ$5:$AJ$64,9)),"")
A32: =IFERROR(INDEX('Fragrance Projects'!$C$5:$C$64,SMALL('Fragrance Projects'!$AJ$5:$AJ$64,10)),"") | B32: =IFERROR(INDEX('Fragrance Projects'!$D$5:$D$64,SMALL('Fragrance Projects'!$AJ$5:$AJ$64,10)),"") | C32: =IFERROR(INDEX('Fragrance Projects'!$H$5:$H$64,SMALL('Fragrance Projects'!$AJ$5:$AJ$64,10)),"") | D32: =IFERROR(INDEX('Fragrance Projects'!$G$5:$G$64,SMALL('Fragrance Projects'!$AJ$5:$AJ$64,10)),"") | E32: =IFERROR(INDEX('Fragrance Projects'!$P$5:$P$64,SMALL('Fragrance Projects'!$AJ$5:$AJ$64,10)),"") | F32: =IFERROR(INDEX('Fragrance Projects'!$AH$5:$AH$64,SMALL('Fragrance Projects'!$AJ$5:$AJ$64,10)),"") | G32: =IFERROR(INDEX('Fragrance Projects'!$AK$5:$AK$64,SMALL('Fragrance Projects'!$AJ$5:$AJ$64,10)),"")
A34: UPCOMING DEADLINES — Next 8 In Line
A35: Client | B35: Fragrance | C35: Deadline | D35: Days Remaining | E35: Current Stage | F35: Next Action
A36: =IFERROR(INDEX('Fragrance Projects'!$C$5:$C$64,MOD(SMALL('Fragrance Projects'!$AI$5:$AI$64,1),1000)),"") | B36: =IFERROR(INDEX('Fragrance Projects'!$D$5:$D$64,MOD(SMALL('Fragrance Projects'!$AI$5:$AI$64,1),1000)),"") | C36: =IFERROR(INDEX('Fragrance Projects'!$F$5:$F$64,MOD(SMALL('Fragrance Projects'!$AI$5:$AI$64,1),1000)),"") | D36: =IFERROR(INDEX('Fragrance Projects'!$G$5:$G$64,MOD(SMALL('Fragrance Projects'!$AI$5:$AI$64,1),1000)),"") | E36: =IFERROR(INDEX('Fragrance Projects'!$H$5:$H$64,MOD(SMALL('Fragrance Projects'!$AI$5:$AI$64,1),1000)),"") | F36: =IFERROR(INDEX('Fragrance Projects'!$P$5:$P$64,MOD(SMALL('Fragrance Projects'!$AI$5:$AI$64,1),1000)),"")
A37: =IFERROR(INDEX('Fragrance Projects'!$C$5:$C$64,MOD(SMALL('Fragrance Projects'!$AI$5:$AI$64,2),1000)),"") | B37: =IFERROR(INDEX('Fragrance Projects'!$D$5:$D$64,MOD(SMALL('Fragrance Projects'!$AI$5:$AI$64,2),1000)),"") | C37: =IFERROR(INDEX('Fragrance Projects'!$F$5:$F$64,MOD(SMALL('Fragrance Projects'!$AI$5:$AI$64,2),1000)),"") | D37: =IFERROR(INDEX('Fragrance Projects'!$G$5:$G$64,MOD(SMALL('Fragrance Projects'!$AI$5:$AI$64,2),1000)),"") | E37: =IFERROR(INDEX('Fragrance Projects'!$H$5:$H$64,MOD(SMALL('Fragrance Projects'!$AI$5:$AI$64,2),1000)),"") | F37: =IFERROR(INDEX('Fragrance Projects'!$P$5:$P$64,MOD(SMALL('Fragrance Projects'!$AI$5:$AI$64,2),1000)),"")
A38: =IFERROR(INDEX('Fragrance Projects'!$C$5:$C$64,MOD(SMALL('Fragrance Projects'!$AI$5:$AI$64,3),1000)),"") | B38: =IFERROR(INDEX('Fragrance Projects'!$D$5:$D$64,MOD(SMALL('Fragrance Projects'!$AI$5:$AI$64,3),1000)),"") | C38: =IFERROR(INDEX('Fragrance Projects'!$F$5:$F$64,MOD(SMALL('Fragrance Projects'!$AI$5:$AI$64,3),1000)),"") | D38: =IFERROR(INDEX('Fragrance Projects'!$G$5:$G$64,MOD(SMALL('Fragrance Projects'!$AI$5:$AI$64,3),1000)),"") | E38: =IFERROR(INDEX('Fragrance Projects'!$H$5:$H$64,MOD(SMALL('Fragrance Projects'!$AI$5:$AI$64,3),1000)),"") | F38: =IFERROR(INDEX('Fragrance Projects'!$P$5:$P$64,MOD(SMALL('Fragrance Projects'!$AI$5:$AI$64,3),1000)),"")
A39: =IFERROR(INDEX('Fragrance Projects'!$C$5:$C$64,MOD(SMALL('Fragrance Projects'!$AI$5:$AI$64,4),1000)),"") | B39: =IFERROR(INDEX('Fragrance Projects'!$D$5:$D$64,MOD(SMALL('Fragrance Projects'!$AI$5:$AI$64,4),1000)),"") | C39: =IFERROR(INDEX('Fragrance Projects'!$F$5:$F$64,MOD(SMALL('Fragrance Projects'!$AI$5:$AI$64,4),1000)),"") | D39: =IFERROR(INDEX('Fragrance Projects'!$G$5:$G$64,MOD(SMALL('Fragrance Projects'!$AI$5:$AI$64,4),1000)),"") | E39: =IFERROR(INDEX('Fragrance Projects'!$H$5:$H$64,MOD(SMALL('Fragrance Projects'!$AI$5:$AI$64,4),1000)),"") | F39: =IFERROR(INDEX('Fragrance Projects'!$P$5:$P$64,MOD(SMALL('Fragrance Projects'!$AI$5:$AI$64,4),1000)),"")
A40: =IFERROR(INDEX('Fragrance Projects'!$C$5:$C$64,MOD(SMALL('Fragrance Projects'!$AI$5:$AI$64,5),1000)),"") | B40: =IFERROR(INDEX('Fragrance Projects'!$D$5:$D$64,MOD(SMALL('Fragrance Projects'!$AI$5:$AI$64,5),1000)),"") | C40: =IFERROR(INDEX('Fragrance Projects'!$F$5:$F$64,MOD(SMALL('Fragrance Projects'!$AI$5:$AI$64,5),1000)),"") | D40: =IFERROR(INDEX('Fragrance Projects'!$G$5:$G$64,MOD(SMALL('Fragrance Projects'!$AI$5:$AI$64,5),1000)),"") | E40: =IFERROR(INDEX('Fragrance Projects'!$H$5:$H$64,MOD(SMALL('Fragrance Projects'!$AI$5:$AI$64,5),1000)),"") | F40: =IFERROR(INDEX('Fragrance Projects'!$P$5:$P$64,MOD(SMALL('Fragrance Projects'!$AI$5:$AI$64,5),1000)),"")
A41: =IFERROR(INDEX('Fragrance Projects'!$C$5:$C$64,MOD(SMALL('Fragrance Projects'!$AI$5:$AI$64,6),1000)),"") | B41: =IFERROR(INDEX('Fragrance Projects'!$D$5:$D$64,MOD(SMALL('Fragrance Projects'!$AI$5:$AI$64,6),1000)),"") | C41: =IFERROR(INDEX('Fragrance Projects'!$F$5:$F$64,MOD(SMALL('Fragrance Projects'!$AI$5:$AI$64,6),1000)),"") | D41: =IFERROR(INDEX('Fragrance Projects'!$G$5:$G$64,MOD(SMALL('Fragrance Projects'!$AI$5:$AI$64,6),1000)),"") | E41: =IFERROR(INDEX('Fragrance Projects'!$H$5:$H$64,MOD(SMALL('Fragrance Projects'!$AI$5:$AI$64,6),1000)),"") | F41: =IFERROR(INDEX('Fragrance Projects'!$P$5:$P$64,MOD(SMALL('Fragrance Projects'!$AI$5:$AI$64,6),1000)),"")
A42: =IFERROR(INDEX('Fragrance Projects'!$C$5:$C$64,MOD(SMALL('Fragrance Projects'!$AI$5:$AI$64,7),1000)),"") | B42: =IFERROR(INDEX('Fragrance Projects'!$D$5:$D$64,MOD(SMALL('Fragrance Projects'!$AI$5:$AI$64,7),1000)),"") | C42: =IFERROR(INDEX('Fragrance Projects'!$F$5:$F$64,MOD(SMALL('Fragrance Projects'!$AI$5:$AI$64,7),1000)),"") | D42: =IFERROR(INDEX('Fragrance Projects'!$G$5:$G$64,MOD(SMALL('Fragrance Projects'!$AI$5:$AI$64,7),1000)),"") | E42: =IFERROR(INDEX('Fragrance Projects'!$H$5:$H$64,MOD(SMALL('Fragrance Projects'!$AI$5:$AI$64,7),1000)),"") | F42: =IFERROR(INDEX('Fragrance Projects'!$P$5:$P$64,MOD(SMALL('Fragrance Projects'!$AI$5:$AI$64,7),1000)),"")
A43: =IFERROR(INDEX('Fragrance Projects'!$C$5:$C$64,MOD(SMALL('Fragrance Projects'!$AI$5:$AI$64,8),1000)),"") | B43: =IFERROR(INDEX('Fragrance Projects'!$D$5:$D$64,MOD(SMALL('Fragrance Projects'!$AI$5:$AI$64,8),1000)),"") | C43: =IFERROR(INDEX('Fragrance Projects'!$F$5:$F$64,MOD(SMALL('Fragrance Projects'!$AI$5:$AI$64,8),1000)),"") | D43: =IFERROR(INDEX('Fragrance Projects'!$G$5:$G$64,MOD(SMALL('Fragrance Projects'!$AI$5:$AI$64,8),1000)),"") | E43: =IFERROR(INDEX('Fragrance Projects'!$H$5:$H$64,MOD(SMALL('Fragrance Projects'!$AI$5:$AI$64,8),1000)),"") | F43: =IFERROR(INDEX('Fragrance Projects'!$P$5:$P$64,MOD(SMALL('Fragrance Projects'!$AI$5:$AI$64,8),1000)),"")
A45: CHARTS
A46: Chart data (calculated automatically — do not edit)
A47: Month | B47: Revenue Received | C47: Expenses | D47: Profit | F47: Stage | G47: Projects | I47: Client | J47: Active Projects
A48: =TEXT(DATE(YEAR(EDATE(TODAY(),-7)),MONTH(EDATE(TODAY(),-7)),1),"mmm yy") -> Jan 26 | B48: =SUMIFS(Payments!$G$5:$G$64,Payments!$H$5:$H$64,">="&DATE(YEAR(EDATE(TODAY(),-7)),MONTH(EDATE(TODAY(),-7)),1),Payments!$H$5:$H$64,"<="&EDATE(DATE(YEAR(EDATE(TODAY(),-7)),MONTH(EDATE(TODAY(),-7)),1),1)-1)+SUMIFS(Payments!$K$5:$K$64,Payments!$J$5:$J$64,">="&DATE(YEAR(EDATE(TODAY(),-7)),MONTH(EDATE(TODAY(),-7)),1),Payments!$J$5:$J$64,"<="&EDATE(DATE(YEAR(EDATE(TODAY(),-7)),MONTH(EDATE(TODAY(),-7)),1),1)-1) -> 0 | C48: =SUMIFS('Expense Log'!$J$5:$J$154,'Expense Log'!$A$5:$A$154,">="&DATE(YEAR(EDATE(TODAY(),-7)),MONTH(EDATE(TODAY(),-7)),1),'Expense Log'!$A$5:$A$154,"<="&EDATE(DATE(YEAR(EDATE(TODAY(),-7)),MONTH(EDATE(TODAY(),-7)),1),1)-1) -> 0 | D48: =B48-C48 -> 0 | F48: Brief | G48: =COUNTIF('Fragrance Projects'!$H$5:$H$64,"Brief") -> 0 | I48: =IFERROR(INDEX(Clients!$B$5:$B$44,1),"") -> 0 | J48: =IF($I48="","",SUMPRODUCT(('Fragrance Projects'!$C$5:$C$64=$I48)*('Fragrance Projects'!$J$5:$J$64<>"Completed")*('Fragrance Projects'!$J$5:$J$64<>"On Hold")))
A49: =TEXT(DATE(YEAR(EDATE(TODAY(),-6)),MONTH(EDATE(TODAY(),-6)),1),"mmm yy") -> Feb 26 | B49: =SUMIFS(Payments!$G$5:$G$64,Payments!$H$5:$H$64,">="&DATE(YEAR(EDATE(TODAY(),-6)),MONTH(EDATE(TODAY(),-6)),1),Payments!$H$5:$H$64,"<="&EDATE(DATE(YEAR(EDATE(TODAY(),-6)),MONTH(EDATE(TODAY(),-6)),1),1)-1)+SUMIFS(Payments!$K$5:$K$64,Payments!$J$5:$J$64,">="&DATE(YEAR(EDATE(TODAY(),-6)),MONTH(EDATE(TODAY(),-6)),1),Payments!$J$5:$J$64,"<="&EDATE(DATE(YEAR(EDATE(TODAY(),-6)),MONTH(EDATE(TODAY(),-6)),1),1)-1) -> 0 | C49: =SUMIFS('Expense Log'!$J$5:$J$154,'Expense Log'!$A$5:$A$154,">="&DATE(YEAR(EDATE(TODAY(),-6)),MONTH(EDATE(TODAY(),-6)),1),'Expense Log'!$A$5:$A$154,"<="&EDATE(DATE(YEAR(EDATE(TODAY(),-6)),MONTH(EDATE(TODAY(),-6)),1),1)-1) -> 0 | D49: =B49-C49 -> 0 | F49: Research | G49: =COUNTIF('Fragrance Projects'!$H$5:$H$64,"Research") -> 0 | I49: =IFERROR(INDEX(Clients!$B$5:$B$44,2),"") -> 0 | J49: =IF($I49="","",SUMPRODUCT(('Fragrance Projects'!$C$5:$C$64=$I49)*('Fragrance Projects'!$J$5:$J$64<>"Completed")*('Fragrance Projects'!$J$5:$J$64<>"On Hold")))
A50: =TEXT(DATE(YEAR(EDATE(TODAY(),-5)),MONTH(EDATE(TODAY(),-5)),1),"mmm yy") -> Mar 26 | B50: =SUMIFS(Payments!$G$5:$G$64,Payments!$H$5:$H$64,">="&DATE(YEAR(EDATE(TODAY(),-5)),MONTH(EDATE(TODAY(),-5)),1),Payments!$H$5:$H$64,"<="&EDATE(DATE(YEAR(EDATE(TODAY(),-5)),MONTH(EDATE(TODAY(),-5)),1),1)-1)+SUMIFS(Payments!$K$5:$K$64,Payments!$J$5:$J$64,">="&DATE(YEAR(EDATE(TODAY(),-5)),MONTH(EDATE(TODAY(),-5)),1),Payments!$J$5:$J$64,"<="&EDATE(DATE(YEAR(EDATE(TODAY(),-5)),MONTH(EDATE(TODAY(),-5)),1),1)-1) -> 0 | C50: =SUMIFS('Expense Log'!$J$5:$J$154,'Expense Log'!$A$5:$A$154,">="&DATE(YEAR(EDATE(TODAY(),-5)),MONTH(EDATE(TODAY(),-5)),1),'Expense Log'!$A$5:$A$154,"<="&EDATE(DATE(YEAR(EDATE(TODAY(),-5)),MONTH(EDATE(TODAY(),-5)),1),1)-1) -> 0 | D50: =B50-C50 -> 0 | F50: Concept Development | G50: =COUNTIF('Fragrance Projects'!$H$5:$H$64,"Concept Development") -> 0 | I50: =IFERROR(INDEX(Clients!$B$5:$B$44,3),"") -> 0 | J50: =IF($I50="","",SUMPRODUCT(('Fragrance Projects'!$C$5:$C$64=$I50)*('Fragrance Projects'!$J$5:$J$64<>"Completed")*('Fragrance Projects'!$J$5:$J$64<>"On Hold")))
A51: =TEXT(DATE(YEAR(EDATE(TODAY(),-4)),MONTH(EDATE(TODAY(),-4)),1),"mmm yy") -> Apr 26 | B51: =SUMIFS(Payments!$G$5:$G$64,Payments!$H$5:$H$64,">="&DATE(YEAR(EDATE(TODAY(),-4)),MONTH(EDATE(TODAY(),-4)),1),Payments!$H$5:$H$64,"<="&EDATE(DATE(YEAR(EDATE(TODAY(),-4)),MONTH(EDATE(TODAY(),-4)),1),1)-1)+SUMIFS(Payments!$K$5:$K$64,Payments!$J$5:$J$64,">="&DATE(YEAR(EDATE(TODAY(),-4)),MONTH(EDATE(TODAY(),-4)),1),Payments!$J$5:$J$64,"<="&EDATE(DATE(YEAR(EDATE(TODAY(),-4)),MONTH(EDATE(TODAY(),-4)),1),1)-1) -> 0 | C51: =SUMIFS('Expense Log'!$J$5:$J$154,'Expense Log'!$A$5:$A$154,">="&DATE(YEAR(EDATE(TODAY(),-4)),MONTH(EDATE(TODAY(),-4)),1),'Expense Log'!$A$5:$A$154,"<="&EDATE(DATE(YEAR(EDATE(TODAY(),-4)),MONTH(EDATE(TODAY(),-4)),1),1)-1) -> 0 | D51: =B51-C51 -> 0 | F51: Formula Development | G51: =COUNTIF('Fragrance Projects'!$H$5:$H$64,"Formula Development") -> 0 | I51: =IFERROR(INDEX(Clients!$B$5:$B$44,4),"") -> 0 | J51: =IF($I51="","",SUMPRODUCT(('Fragrance Projects'!$C$5:$C$64=$I51)*('Fragrance Projects'!$J$5:$J$64<>"Completed")*('Fragrance Projects'!$J$5:$J$64<>"On Hold")))
A52: =TEXT(DATE(YEAR(EDATE(TODAY(),-3)),MONTH(EDATE(TODAY(),-3)),1),"mmm yy") -> May 26 | B52: =SUMIFS(Payments!$G$5:$G$64,Payments!$H$5:$H$64,">="&DATE(YEAR(EDATE(TODAY(),-3)),MONTH(EDATE(TODAY(),-3)),1),Payments!$H$5:$H$64,"<="&EDATE(DATE(YEAR(EDATE(TODAY(),-3)),MONTH(EDATE(TODAY(),-3)),1),1)-1)+SUMIFS(Payments!$K$5:$K$64,Payments!$J$5:$J$64,">="&DATE(YEAR(EDATE(TODAY(),-3)),MONTH(EDATE(TODAY(),-3)),1),Payments!$J$5:$J$64,"<="&EDATE(DATE(YEAR(EDATE(TODAY(),-3)),MONTH(EDATE(TODAY(),-3)),1),1)-1) -> 0 | C52: =SUMIFS('Expense Log'!$J$5:$J$154,'Expense Log'!$A$5:$A$154,">="&DATE(YEAR(EDATE(TODAY(),-3)),MONTH(EDATE(TODAY(),-3)),1),'Expense Log'!$A$5:$A$154,"<="&EDATE(DATE(YEAR(EDATE(TODAY(),-3)),MONTH(EDATE(TODAY(),-3)),1),1)-1) -> 0 | D52: =B52-C52 -> 0 | F52: Compounding | G52: =COUNTIF('Fragrance Projects'!$H$5:$H$64,"Compounding") -> 0 | I52: =IFERROR(INDEX(Clients!$B$5:$B$44,5),"") -> 0 | J52: =IF($I52="","",SUMPRODUCT(('Fragrance Projects'!$C$5:$C$64=$I52)*('Fragrance Projects'!$J$5:$J$64<>"Completed")*('Fragrance Projects'!$J$5:$J$64<>"On Hold")))
A53: =TEXT(DATE(YEAR(EDATE(TODAY(),-2)),MONTH(EDATE(TODAY(),-2)),1),"mmm yy") -> Jun 26 | B53: =SUMIFS(Payments!$G$5:$G$64,Payments!$H$5:$H$64,">="&DATE(YEAR(EDATE(TODAY(),-2)),MONTH(EDATE(TODAY(),-2)),1),Payments!$H$5:$H$64,"<="&EDATE(DATE(YEAR(EDATE(TODAY(),-2)),MONTH(EDATE(TODAY(),-2)),1),1)-1)+SUMIFS(Payments!$K$5:$K$64,Payments!$J$5:$J$64,">="&DATE(YEAR(EDATE(TODAY(),-2)),MONTH(EDATE(TODAY(),-2)),1),Payments!$J$5:$J$64,"<="&EDATE(DATE(YEAR(EDATE(TODAY(),-2)),MONTH(EDATE(TODAY(),-2)),1),1)-1) -> 0 | C53: =SUMIFS('Expense Log'!$J$5:$J$154,'Expense Log'!$A$5:$A$154,">="&DATE(YEAR(EDATE(TODAY(),-2)),MONTH(EDATE(TODAY(),-2)),1),'Expense Log'!$A$5:$A$154,"<="&EDATE(DATE(YEAR(EDATE(TODAY(),-2)),MONTH(EDATE(TODAY(),-2)),1),1)-1) -> 0 | D53: =B53-C53 -> 0 | F53: Evaluation | G53: =COUNTIF('Fragrance Projects'!$H$5:$H$64,"Evaluation") -> 0 | I53: =IFERROR(INDEX(Clients!$B$5:$B$44,6),"") -> 0 | J53: =IF($I53="","",SUMPRODUCT(('Fragrance Projects'!$C$5:$C$64=$I53)*('Fragrance Projects'!$J$5:$J$64<>"Completed")*('Fragrance Projects'!$J$5:$J$64<>"On Hold")))
A54: =TEXT(DATE(YEAR(EDATE(TODAY(),-1)),MONTH(EDATE(TODAY(),-1)),1),"mmm yy") -> Jul 26 | B54: =SUMIFS(Payments!$G$5:$G$64,Payments!$H$5:$H$64,">="&DATE(YEAR(EDATE(TODAY(),-1)),MONTH(EDATE(TODAY(),-1)),1),Payments!$H$5:$H$64,"<="&EDATE(DATE(YEAR(EDATE(TODAY(),-1)),MONTH(EDATE(TODAY(),-1)),1),1)-1)+SUMIFS(Payments!$K$5:$K$64,Payments!$J$5:$J$64,">="&DATE(YEAR(EDATE(TODAY(),-1)),MONTH(EDATE(TODAY(),-1)),1),Payments!$J$5:$J$64,"<="&EDATE(DATE(YEAR(EDATE(TODAY(),-1)),MONTH(EDATE(TODAY(),-1)),1),1)-1) -> 0 | C54: =SUMIFS('Expense Log'!$J$5:$J$154,'Expense Log'!$A$5:$A$154,">="&DATE(YEAR(EDATE(TODAY(),-1)),MONTH(EDATE(TODAY(),-1)),1),'Expense Log'!$A$5:$A$154,"<="&EDATE(DATE(YEAR(EDATE(TODAY(),-1)),MONTH(EDATE(TODAY(),-1)),1),1)-1) -> 0 | D54: =B54-C54 -> 0 | F54: Sample Sent | G54: =COUNTIF('Fragrance Projects'!$H$5:$H$64,"Sample Sent") -> 0 | I54: =IFERROR(INDEX(Clients!$B$5:$B$44,7),"") -> 0 | J54: =IF($I54="","",SUMPRODUCT(('Fragrance Projects'!$C$5:$C$64=$I54)*('Fragrance Projects'!$J$5:$J$64<>"Completed")*('Fragrance Projects'!$J$5:$J$64<>"On Hold")))
A55: =TEXT(DATE(YEAR(EDATE(TODAY(),0)),MONTH(EDATE(TODAY(),0)),1),"mmm yy") -> Aug 26 | B55: =SUMIFS(Payments!$G$5:$G$64,Payments!$H$5:$H$64,">="&DATE(YEAR(EDATE(TODAY(),0)),MONTH(EDATE(TODAY(),0)),1),Payments!$H$5:$H$64,"<="&EDATE(DATE(YEAR(EDATE(TODAY(),0)),MONTH(EDATE(TODAY(),0)),1),1)-1)+SUMIFS(Payments!$K$5:$K$64,Payments!$J$5:$J$64,">="&DATE(YEAR(EDATE(TODAY(),0)),MONTH(EDATE(TODAY(),0)),1),Payments!$J$5:$J$64,"<="&EDATE(DATE(YEAR(EDATE(TODAY(),0)),MONTH(EDATE(TODAY(),0)),1),1)-1) -> 0 | C55: =SUMIFS('Expense Log'!$J$5:$J$154,'Expense Log'!$A$5:$A$154,">="&DATE(YEAR(EDATE(TODAY(),0)),MONTH(EDATE(TODAY(),0)),1),'Expense Log'!$A$5:$A$154,"<="&EDATE(DATE(YEAR(EDATE(TODAY(),0)),MONTH(EDATE(TODAY(),0)),1),1)-1) -> 0 | D55: =B55-C55 -> 0 | F55: Awaiting Feedback | G55: =COUNTIF('Fragrance Projects'!$H$5:$H$64,"Awaiting Feedback") -> 0 | I55: =IFERROR(INDEX(Clients!$B$5:$B$44,8),"") -> 0 | J55: =IF($I55="","",SUMPRODUCT(('Fragrance Projects'!$C$5:$C$64=$I55)*('Fragrance Projects'!$J$5:$J$64<>"Completed")*('Fragrance Projects'!$J$5:$J$64<>"On Hold")))
A56: Note: revenue-by-month approximates timing using deposit date and balance due date. | F56: Reformulation | G56: =COUNTIF('Fragrance Projects'!$H$5:$H$64,"Reformulation") -> 0 | I56: =IFERROR(INDEX(Clients!$B$5:$B$44,9),"") -> 0 | J56: =IF($I56="","",SUMPRODUCT(('Fragrance Projects'!$C$5:$C$64=$I56)*('Fragrance Projects'!$J$5:$J$64<>"Completed")*('Fragrance Projects'!$J$5:$J$64<>"On Hold")))
F57: Approved | G57: =COUNTIF('Fragrance Projects'!$H$5:$H$64,"Approved") -> 0 | I57: =IFERROR(INDEX(Clients!$B$5:$B$44,10),"") -> 0 | J57: =IF($I57="","",SUMPRODUCT(('Fragrance Projects'!$C$5:$C$64=$I57)*('Fragrance Projects'!$J$5:$J$64<>"Completed")*('Fragrance Projects'!$J$5:$J$64<>"On Hold")))
F58: Documentation | G58: =COUNTIF('Fragrance Projects'!$H$5:$H$64,"Documentation") -> 0
F59: Production | G59: =COUNTIF('Fragrance Projects'!$H$5:$H$64,"Production") -> 0
F60: Complete | G60: =COUNTIF('Fragrance Projects'!$H$5:$H$64,"Complete") -> 0
F61: On Hold | G61: =COUNTIF('Fragrance Projects'!$H$5:$H$64,"On Hold") -> 0

Sheet Clients
A1: CLIENTS — Master Client Database
A2: One row per client / brand. New clients: add a row and choose the next Client ID (e.g. C007).
B3: INPUT — type or choose here | F3: CALCULATED — formula, do not edit | J3: AUTO-LOOKUP — pulled from another sheet
A4: Client ID | B4: Client / Brand Name | C4: Contact Name | D4: Email | E4: Phone | F4: Country | G4: Date Enquired | H4: Date Signed | I4: Lead Source | J4: Project Type | K4: No. of Fragrances | L4: Package Purchased | M4: Agreed Price | N4: Deposit Required | O4: Deposit Paid | P4: Remaining Balance | Q4: Payment Status | R4: Contract Signed? | S4: NDA? | T4: Formula Ownership | U4: Client Priority | V4: Relationship Status | W4: Notes
P5: =IF($M5="","",$M5-$O5) | Q5: =IF($A5="","",_xlfn.IFS($M5=0,"Not Invoiced",$O5=0,"Awaiting Deposit",$P5<=0,"Paid",TRUE(),"Part Paid"))
P6: =IF($M6="","",$M6-$O6) | Q6: =IF($A6="","",_xlfn.IFS($M6=0,"Not Invoiced",$O6=0,"Awaiting Deposit",$P6<=0,"Paid",TRUE(),"Part Paid"))
P7: =IF($M7="","",$M7-$O7) | Q7: =IF($A7="","",_xlfn.IFS($M7=0,"Not Invoiced",$O7=0,"Awaiting Deposit",$P7<=0,"Paid",TRUE(),"Part Paid"))
P8: =IF($M8="","",$M8-$O8) | Q8: =IF($A8="","",_xlfn.IFS($M8=0,"Not Invoiced",$O8=0,"Awaiting Deposit",$P8<=0,"Paid",TRUE(),"Part Paid"))
P9: =IF($M9="","",$M9-$O9) | Q9: =IF($A9="","",_xlfn.IFS($M9=0,"Not Invoiced",$O9=0,"Awaiting Deposit",$P9<=0,"Paid",TRUE(),"Part Paid"))
P10: =IF($M10="","",$M10-$O10) | Q10: =IF($A10="","",_xlfn.IFS($M10=0,"Not Invoiced",$O10=0,"Awaiting Deposit",$P10<=0,"Paid",TRUE(),"Part Paid"))
P11: =IF($M11="","",$M11-$O11) | Q11: =IF($A11="","",_xlfn.IFS($M11=0,"Not Invoiced",$O11=0,"Awaiting Deposit",$P11<=0,"Paid",TRUE(),"Part Paid"))
P12: =IF($M12="","",$M12-$O12) | Q12: =IF($A12="","",_xlfn.IFS($M12=0,"Not Invoiced",$O12=0,"Awaiting Deposit",$P12<=0,"Paid",TRUE(),"Part Paid"))
P13: =IF($M13="","",$M13-$O13) | Q13: =IF($A13="","",_xlfn.IFS($M13=0,"Not Invoiced",$O13=0,"Awaiting Deposit",$P13<=0,"Paid",TRUE(),"Part Paid"))
P14: =IF($M14="","",$M14-$O14) | Q14: =IF($A14="","",_xlfn.IFS($M14=0,"Not Invoiced",$O14=0,"Awaiting Deposit",$P14<=0,"Paid",TRUE(),"Part Paid"))
P15: =IF($M15="","",$M15-$O15) | Q15: =IF($A15="","",_xlfn.IFS($M15=0,"Not Invoiced",$O15=0,"Awaiting Deposit",$P15<=0,"Paid",TRUE(),"Part Paid"))
P16: =IF($M16="","",$M16-$O16) | Q16: =IF($A16="","",_xlfn.IFS($M16=0,"Not Invoiced",$O16=0,"Awaiting Deposit",$P16<=0,"Paid",TRUE(),"Part Paid"))
... P44: =IF($M44="","",$M44-$O44) | Q44: =IF($A44="","",_xlfn.IFS($M44=0,"Not Invoiced",$O44=0,"Awaiting Deposit",$P44<=0,"Paid",TRUE(),"Part Paid"))

Sheet Fragrance Projects
A1: FRAGRANCE PROJECTS — Development Tracker
A2: One row per fragrance. Overall Status, iteration count and staleness flags are calculated automatically.
B3: INPUT — type or choose here | F3: CALCULATED — formula, do not edit | J3: AUTO-LOOKUP — pulled from another sheet
A4: Project ID | B4: Client ID | C4: Client Name | D4: Fragrance Name / Working Name | E4: Project Start Date | F4: Target Completion Date | G4: Days Remaining | H4: Current Stage | I4: Priority | J4: Overall Status | K4: Current Iteration | L4: Included Iterations | M4: Remaining Iterations | N4: Last Action Date | O4: Who Currently Needs to Act? | P4: Next Action | Q4: Next Action Due | R4: Days Since Last Activity | S4: Formula Complete? | T4: Formula Approved? | U4: Documentation Complete? | V4: Production/Compounding Required? | W4: Final Delivery Complete? | X4: Notes | Y4: Spacer | Z4: Overdue Flag | AA4: Due Soon Flag | AB4: Waiting On Us Flag | AC4: Client Feedback Overdue Flag | AD4: Iteration Limit Flag | AE4: Low Margin Flag | AF4: Unpaid Flag | AG4: Urgent Flag | AH4: Urgent Reason | AI4: Deadline Rank | AJ4: Urgent Row Offset | AK4: Assigned To
C5: =IFERROR(INDEX(Clients!$B$5:$B$44,MATCH($B5,Clients!$A$5:$A$44,0)),"") | G5: =IF($A5="","",$F5-TODAY()) | J5: =IF($A5="","",_xlfn.IFS(OR($W5="Yes",$H5="Complete"),"Completed",$H5="On Hold","On Hold",$G5<0,"Overdue",$O5="Client","Waiting on Client",$G5<=7,"At Risk",TRUE(),"On Track")) | K5: =IF($A5="","",IFERROR(_xlfn.MAXIFS('Iteration Tracker'!$D$5:$D$124,'Iteration Tracker'!$A$5:$A$124,$A5),0)) | M5: =IF($A5="","",$L5-$K5) | R5: =IF($A5="","",IF($N5="","",TODAY()-$N5)) | Z5: =IF($A5="",0,IF(AND($G5<0,$J5<>"Completed",$J5<>"On Hold"),1,0)) -> 0 | AA5: =IF($A5="",0,IF(AND($G5>=0,$G5<=7,$J5<>"Completed",$J5<>"On Hold"),1,0)) -> 0 | AB5: =IF($A5="",0,IF(AND($O5="Us",$J5<>"Completed"),1,0)) -> 0 | AC5: =IF($A5="",0,IF(AND($H5="Awaiting Feedback",$R5<>"",$R5>7),1,0)) -> 0 | AD5: =IF($A5="",0,IF(AND($M5<>"",$M5<=1,$J5<>"Completed"),1,0)) -> 0 | AE5: =IFERROR(IF(AND($A5<>"",INDEX('Project Financials'!$AC$5:$AC$64,MATCH($A5,'Project Financials'!$A$5:$A$64,0))<0.2,INDEX('Project Financials'!$D$5:$D$64,MATCH($A5,'Project Financials'!$A$5:$A$64,0))>0),1,0),0) -> 0 | AF5: =IFERROR(IF(OR(INDEX(Payments!$N$5:$N$64,MATCH($A5,Payments!$B$5:$B$64,0))="Overdue",INDEX(Payments!$N$5:$N$64,MATCH($A5,Payments!$B$5:$B$64,0))="Awaiting Deposit"),1,0),0) -> 0 | AG5: =IF($A5="",0,IF(SUM(Z5:AF5)>0,1,0)) -> 0 | AH5: =IF($AG5=0,"",LEFT((IF($Z5=1,"Overdue; ",""))&(IF($AA5=1,"Deadline ≤ 7 days; ",""))&(IF($AB5=1,"Action needed from us; ",""))&(IF($AC5=1,"Client feedback overdue; ",""))&(IF($AD5=1,"At iteration limit; ",""))&(IF($AE5=1,"Low margin; ",""))&(IF($AF5=1,"Unpaid invoice; ","")),LEN((IF($Z5=1,"Overdue; ",""))&(IF($AA5=1,"Deadline ≤ 7 days; ",""))&(IF($AB5=1,"Action needed from us; ",""))&(IF($AC5=1,"Client feedback overdue; ",""))&(IF($AD5=1,"At iteration limit; ",""))&(IF($AE5=1,"Low margin; ",""))&(IF($AF5=1,"Unpaid invoice; ","")))-2)) | AI5: =IF(AND($A5<>"",$J5<>"Completed",$J5<>"On Hold"),$F5*1000+(ROW()-ROW($A$5)+1),"") | AJ5: =IF($AG5=1,ROW()-ROW($A$5)+1,"")
C6: =IFERROR(INDEX(Clients!$B$5:$B$44,MATCH($B6,Clients!$A$5:$A$44,0)),"") | G6: =IF($A6="","",$F6-TODAY()) | J6: =IF($A6="","",_xlfn.IFS(OR($W6="Yes",$H6="Complete"),"Completed",$H6="On Hold","On Hold",$G6<0,"Overdue",$O6="Client","Waiting on Client",$G6<=7,"At Risk",TRUE(),"On Track")) | K6: =IF($A6="","",IFERROR(_xlfn.MAXIFS('Iteration Tracker'!$D$5:$D$124,'Iteration Tracker'!$A$5:$A$124,$A6),0)) | M6: =IF($A6="","",$L6-$K6) | R6: =IF($A6="","",IF($N6="","",TODAY()-$N6)) | Z6: =IF($A6="",0,IF(AND($G6<0,$J6<>"Completed",$J6<>"On Hold"),1,0)) -> 0 | AA6: =IF($A6="",0,IF(AND($G6>=0,$G6<=7,$J6<>"Completed",$J6<>"On Hold"),1,0)) -> 0 | AB6: =IF($A6="",0,IF(AND($O6="Us",$J6<>"Completed"),1,0)) -> 0 | AC6: =IF($A6="",0,IF(AND($H6="Awaiting Feedback",$R6<>"",$R6>7),1,0)) -> 0 | AD6: =IF($A6="",0,IF(AND($M6<>"",$M6<=1,$J6<>"Completed"),1,0)) -> 0 | AE6: =IFERROR(IF(AND($A6<>"",INDEX('Project Financials'!$AC$5:$AC$64,MATCH($A6,'Project Financials'!$A$5:$A$64,0))<0.2,INDEX('Project Financials'!$D$5:$D$64,MATCH($A6,'Project Financials'!$A$5:$A$64,0))>0),1,0),0) -> 0 | AF6: =IFERROR(IF(OR(INDEX(Payments!$N$5:$N$64,MATCH($A6,Payments!$B$5:$B$64,0))="Overdue",INDEX(Payments!$N$5:$N$64,MATCH($A6,Payments!$B$5:$B$64,0))="Awaiting Deposit"),1,0),0) -> 0 | AG6: =IF($A6="",0,IF(SUM(Z6:AF6)>0,1,0)) -> 0 | AH6: =IF($AG6=0,"",LEFT((IF($Z6=1,"Overdue; ",""))&(IF($AA6=1,"Deadline ≤ 7 days; ",""))&(IF($AB6=1,"Action needed from us; ",""))&(IF($AC6=1,"Client feedback overdue; ",""))&(IF($AD6=1,"At iteration limit; ",""))&(IF($AE6=1,"Low margin; ",""))&(IF($AF6=1,"Unpaid invoice; ","")),LEN((IF($Z6=1,"Overdue; ",""))&(IF($AA6=1,"Deadline ≤ 7 days; ",""))&(IF($AB6=1,"Action needed from us; ",""))&(IF($AC6=1,"Client feedback overdue; ",""))&(IF($AD6=1,"At iteration limit; ",""))&(IF($AE6=1,"Low margin; ",""))&(IF($AF6=1,"Unpaid invoice; ","")))-2)) | AI6: =IF(AND($A6<>"",$J6<>"Completed",$J6<>"On Hold"),$F6*1000+(ROW()-ROW($A$5)+1),"") | AJ6: =IF($AG6=1,ROW()-ROW($A$5)+1,"")
C7: =IFERROR(INDEX(Clients!$B$5:$B$44,MATCH($B7,Clients!$A$5:$A$44,0)),"") | G7: =IF($A7="","",$F7-TODAY()) | J7: =IF($A7="","",_xlfn.IFS(OR($W7="Yes",$H7="Complete"),"Completed",$H7="On Hold","On Hold",$G7<0,"Overdue",$O7="Client","Waiting on Client",$G7<=7,"At Risk",TRUE(),"On Track")) | K7: =IF($A7="","",IFERROR(_xlfn.MAXIFS('Iteration Tracker'!$D$5:$D$124,'Iteration Tracker'!$A$5:$A$124,$A7),0)) | M7: =IF($A7="","",$L7-$K7) | R7: =IF($A7="","",IF($N7="","",TODAY()-$N7)) | Z7: =IF($A7="",0,IF(AND($G7<0,$J7<>"Completed",$J7<>"On Hold"),1,0)) -> 0 | AA7: =IF($A7="",0,IF(AND($G7>=0,$G7<=7,$J7<>"Completed",$J7<>"On Hold"),1,0)) -> 0 | AB7: =IF($A7="",0,IF(AND($O7="Us",$J7<>"Completed"),1,0)) -> 0 | AC7: =IF($A7="",0,IF(AND($H7="Awaiting Feedback",$R7<>"",$R7>7),1,0)) -> 0 | AD7: =IF($A7="",0,IF(AND($M7<>"",$M7<=1,$J7<>"Completed"),1,0)) -> 0 | AE7: =IFERROR(IF(AND($A7<>"",INDEX('Project Financials'!$AC$5:$AC$64,MATCH($A7,'Project Financials'!$A$5:$A$64,0))<0.2,INDEX('Project Financials'!$D$5:$D$64,MATCH($A7,'Project Financials'!$A$5:$A$64,0))>0),1,0),0) -> 0 | AF7: =IFERROR(IF(OR(INDEX(Payments!$N$5:$N$64,MATCH($A7,Payments!$B$5:$B$64,0))="Overdue",INDEX(Payments!$N$5:$N$64,MATCH($A7,Payments!$B$5:$B$64,0))="Awaiting Deposit"),1,0),0) -> 0 | AG7: =IF($A7="",0,IF(SUM(Z7:AF7)>0,1,0)) -> 0 | AH7: =IF($AG7=0,"",LEFT((IF($Z7=1,"Overdue; ",""))&(IF($AA7=1,"Deadline ≤ 7 days; ",""))&(IF($AB7=1,"Action needed from us; ",""))&(IF($AC7=1,"Client feedback overdue; ",""))&(IF($AD7=1,"At iteration limit; ",""))&(IF($AE7=1,"Low margin; ",""))&(IF($AF7=1,"Unpaid invoice; ","")),LEN((IF($Z7=1,"Overdue; ",""))&(IF($AA7=1,"Deadline ≤ 7 days; ",""))&(IF($AB7=1,"Action needed from us; ",""))&(IF($AC7=1,"Client feedback overdue; ",""))&(IF($AD7=1,"At iteration limit; ",""))&(IF($AE7=1,"Low margin; ",""))&(IF($AF7=1,"Unpaid invoice; ","")))-2)) | AI7: =IF(AND($A7<>"",$J7<>"Completed",$J7<>"On Hold"),$F7*1000+(ROW()-ROW($A$5)+1),"") | AJ7: =IF($AG7=1,ROW()-ROW($A$5)+1,"")
C8: =IFERROR(INDEX(Clients!$B$5:$B$44,MATCH($B8,Clients!$A$5:$A$44,0)),"") | G8: =IF($A8="","",$F8-TODAY()) | J8: =IF($A8="","",_xlfn.IFS(OR($W8="Yes",$H8="Complete"),"Completed",$H8="On Hold","On Hold",$G8<0,"Overdue",$O8="Client","Waiting on Client",$G8<=7,"At Risk",TRUE(),"On Track")) | K8: =IF($A8="","",IFERROR(_xlfn.MAXIFS('Iteration Tracker'!$D$5:$D$124,'Iteration Tracker'!$A$5:$A$124,$A8),0)) | M8: =IF($A8="","",$L8-$K8) | R8: =IF($A8="","",IF($N8="","",TODAY()-$N8)) | Z8: =IF($A8="",0,IF(AND($G8<0,$J8<>"Completed",$J8<>"On Hold"),1,0)) -> 0 | AA8: =IF($A8="",0,IF(AND($G8>=0,$G8<=7,$J8<>"Completed",$J8<>"On Hold"),1,0)) -> 0 | AB8: =IF($A8="",0,IF(AND($O8="Us",$J8<>"Completed"),1,0)) -> 0 | AC8: =IF($A8="",0,IF(AND($H8="Awaiting Feedback",$R8<>"",$R8>7),1,0)) -> 0 | AD8: =IF($A8="",0,IF(AND($M8<>"",$M8<=1,$J8<>"Completed"),1,0)) -> 0 | AE8: =IFERROR(IF(AND($A8<>"",INDEX('Project Financials'!$AC$5:$AC$64,MATCH($A8,'Project Financials'!$A$5:$A$64,0))<0.2,INDEX('Project Financials'!$D$5:$D$64,MATCH($A8,'Project Financials'!$A$5:$A$64,0))>0),1,0),0) -> 0 | AF8: =IFERROR(IF(OR(INDEX(Payments!$N$5:$N$64,MATCH($A8,Payments!$B$5:$B$64,0))="Overdue",INDEX(Payments!$N$5:$N$64,MATCH($A8,Payments!$B$5:$B$64,0))="Awaiting Deposit"),1,0),0) -> 0 | AG8: =IF($A8="",0,IF(SUM(Z8:AF8)>0,1,0)) -> 0 | AH8: =IF($AG8=0,"",LEFT((IF($Z8=1,"Overdue; ",""))&(IF($AA8=1,"Deadline ≤ 7 days; ",""))&(IF($AB8=1,"Action needed from us; ",""))&(IF($AC8=1,"Client feedback overdue; ",""))&(IF($AD8=1,"At iteration limit; ",""))&(IF($AE8=1,"Low margin; ",""))&(IF($AF8=1,"Unpaid invoice; ","")),LEN((IF($Z8=1,"Overdue; ",""))&(IF($AA8=1,"Deadline ≤ 7 days; ",""))&(IF($AB8=1,"Action needed from us; ",""))&(IF($AC8=1,"Client feedback overdue; ",""))&(IF($AD8=1,"At iteration limit; ",""))&(IF($AE8=1,"Low margin; ",""))&(IF($AF8=1,"Unpaid invoice; ","")))-2)) | AI8: =IF(AND($A8<>"",$J8<>"Completed",$J8<>"On Hold"),$F8*1000+(ROW()-ROW($A$5)+1),"") | AJ8: =IF($AG8=1,ROW()-ROW($A$5)+1,"")
C9: =IFERROR(INDEX(Clients!$B$5:$B$44,MATCH($B9,Clients!$A$5:$A$44,0)),"") | G9: =IF($A9="","",$F9-TODAY()) | J9: =IF($A9="","",_xlfn.IFS(OR($W9="Yes",$H9="Complete"),"Completed",$H9="On Hold","On Hold",$G9<0,"Overdue",$O9="Client","Waiting on Client",$G9<=7,"At Risk",TRUE(),"On Track")) | K9: =IF($A9="","",IFERROR(_xlfn.MAXIFS('Iteration Tracker'!$D$5:$D$124,'Iteration Tracker'!$A$5:$A$124,$A9),0)) | M9: =IF($A9="","",$L9-$K9) | R9: =IF($A9="","",IF($N9="","",TODAY()-$N9)) | Z9: =IF($A9="",0,IF(AND($G9<0,$J9<>"Completed",$J9<>"On Hold"),1,0)) -> 0 | AA9: =IF($A9="",0,IF(AND($G9>=0,$G9<=7,$J9<>"Completed",$J9<>"On Hold"),1,0)) -> 0 | AB9: =IF($A9="",0,IF(AND($O9="Us",$J9<>"Completed"),1,0)) -> 0 | AC9: =IF($A9="",0,IF(AND($H9="Awaiting Feedback",$R9<>"",$R9>7),1,0)) -> 0 | AD9: =IF($A9="",0,IF(AND($M9<>"",$M9<=1,$J9<>"Completed"),1,0)) -> 0 | AE9: =IFERROR(IF(AND($A9<>"",INDEX('Project Financials'!$AC$5:$AC$64,MATCH($A9,'Project Financials'!$A$5:$A$64,0))<0.2,INDEX('Project Financials'!$D$5:$D$64,MATCH($A9,'Project Financials'!$A$5:$A$64,0))>0),1,0),0) -> 0 | AF9: =IFERROR(IF(OR(INDEX(Payments!$N$5:$N$64,MATCH($A9,Payments!$B$5:$B$64,0))="Overdue",INDEX(Payments!$N$5:$N$64,MATCH($A9,Payments!$B$5:$B$64,0))="Awaiting Deposit"),1,0),0) -> 0 | AG9: =IF($A9="",0,IF(SUM(Z9:AF9)>0,1,0)) -> 0 | AH9: =IF($AG9=0,"",LEFT((IF($Z9=1,"Overdue; ",""))&(IF($AA9=1,"Deadline ≤ 7 days; ",""))&(IF($AB9=1,"Action needed from us; ",""))&(IF($AC9=1,"Client feedback overdue; ",""))&(IF($AD9=1,"At iteration limit; ",""))&(IF($AE9=1,"Low margin; ",""))&(IF($AF9=1,"Unpaid invoice; ","")),LEN((IF($Z9=1,"Overdue; ",""))&(IF($AA9=1,"Deadline ≤ 7 days; ",""))&(IF($AB9=1,"Action needed from us; ",""))&(IF($AC9=1,"Client feedback overdue; ",""))&(IF($AD9=1,"At iteration limit; ",""))&(IF($AE9=1,"Low margin; ",""))&(IF($AF9=1,"Unpaid invoice; ","")))-2)) | AI9: =IF(AND($A9<>"",$J9<>"Completed",$J9<>"On Hold"),$F9*1000+(ROW()-ROW($A$5)+1),"") | AJ9: =IF($AG9=1,ROW()-ROW($A$5)+1,"")
C10: =IFERROR(INDEX(Clients!$B$5:$B$44,MATCH($B10,Clients!$A$5:$A$44,0)),"") | G10: =IF($A10="","",$F10-TODAY()) | J10: =IF($A10="","",_xlfn.IFS(OR($W10="Yes",$H10="Complete"),"Completed",$H10="On Hold","On Hold",$G10<0,"Overdue",$O10="Client","Waiting on Client",$G10<=7,"At Risk",TRUE(),"On Track")) | K10: =IF($A10="","",IFERROR(_xlfn.MAXIFS('Iteration Tracker'!$D$5:$D$124,'Iteration Tracker'!$A$5:$A$124,$A10),0)) | M10: =IF($A10="","",$L10-$K10) | R10: =IF($A10="","",IF($N10="","",TODAY()-$N10)) | Z10: =IF($A10="",0,IF(AND($G10<0,$J10<>"Completed",$J10<>"On Hold"),1,0)) -> 0 | AA10: =IF($A10="",0,IF(AND($G10>=0,$G10<=7,$J10<>"Completed",$J10<>"On Hold"),1,0)) -> 0 | AB10: =IF($A10="",0,IF(AND($O10="Us",$J10<>"Completed"),1,0)) -> 0 | AC10: =IF($A10="",0,IF(AND($H10="Awaiting Feedback",$R10<>"",$R10>7),1,0)) -> 0 | AD10: =IF($A10="",0,IF(AND($M10<>"",$M10<=1,$J10<>"Completed"),1,0)) -> 0 | AE10: =IFERROR(IF(AND($A10<>"",INDEX('Project Financials'!$AC$5:$AC$64,MATCH($A10,'Project Financials'!$A$5:$A$64,0))<0.2,INDEX('Project Financials'!$D$5:$D$64,MATCH($A10,'Project Financials'!$A$5:$A$64,0))>0),1,0),0) -> 0 | AF10: =IFERROR(IF(OR(INDEX(Payments!$N$5:$N$64,MATCH($A10,Payments!$B$5:$B$64,0))="Overdue",INDEX(Payments!$N$5:$N$64,MATCH($A10,Payments!$B$5:$B$64,0))="Awaiting Deposit"),1,0),0) -> 0 | AG10: =IF($A10="",0,IF(SUM(Z10:AF10)>0,1,0)) -> 0 | AH10: =IF($AG10=0,"",LEFT((IF($Z10=1,"Overdue; ",""))&(IF($AA10=1,"Deadline ≤ 7 days; ",""))&(IF($AB10=1,"Action needed from us; ",""))&(IF($AC10=1,"Client feedback overdue; ",""))&(IF($AD10=1,"At iteration limit; ",""))&(IF($AE10=1,"Low margin; ",""))&(IF($AF10=1,"Unpaid invoice; ","")),LEN((IF($Z10=1,"Overdue; ",""))&(IF($AA10=1,"Deadline ≤ 7 days; ",""))&(IF($AB10=1,"Action needed from us; ",""))&(IF($AC10=1,"Client feedback overdue; ",""))&(IF($AD10=1,"At iteration limit; ",""))&(IF($AE10=1,"Low margin; ",""))&(IF($AF10=1,"Unpaid invoice; ","")))-2)) | AI10: =IF(AND($A10<>"",$J10<>"Completed",$J10<>"On Hold"),$F10*1000+(ROW()-ROW($A$5)+1),"") | AJ10: =IF($AG10=1,ROW()-ROW($A$5)+1,"")
C11: =IFERROR(INDEX(Clients!$B$5:$B$44,MATCH($B11,Clients!$A$5:$A$44,0)),"") | G11: =IF($A11="","",$F11-TODAY()) | J11: =IF($A11="","",_xlfn.IFS(OR($W11="Yes",$H11="Complete"),"Completed",$H11="On Hold","On Hold",$G11<0,"Overdue",$O11="Client","Waiting on Client",$G11<=7,"At Risk",TRUE(),"On Track")) | K11: =IF($A11="","",IFERROR(_xlfn.MAXIFS('Iteration Tracker'!$D$5:$D$124,'Iteration Tracker'!$A$5:$A$124,$A11),0)) | M11: =IF($A11="","",$L11-$K11) | R11: =IF($A11="","",IF($N11="","",TODAY()-$N11)) | Z11: =IF($A11="",0,IF(AND($G11<0,$J11<>"Completed",$J11<>"On Hold"),1,0)) -> 0 | AA11: =IF($A11="",0,IF(AND($G11>=0,$G11<=7,$J11<>"Completed",$J11<>"On Hold"),1,0)) -> 0 | AB11: =IF($A11="",0,IF(AND($O11="Us",$J11<>"Completed"),1,0)) -> 0 | AC11: =IF($A11="",0,IF(AND($H11="Awaiting Feedback",$R11<>"",$R11>7),1,0)) -> 0 | AD11: =IF($A11="",0,IF(AND($M11<>"",$M11<=1,$J11<>"Completed"),1,0)) -> 0 | AE11: =IFERROR(IF(AND($A11<>"",INDEX('Project Financials'!$AC$5:$AC$64,MATCH($A11,'Project Financials'!$A$5:$A$64,0))<0.2,INDEX('Project Financials'!$D$5:$D$64,MATCH($A11,'Project Financials'!$A$5:$A$64,0))>0),1,0),0) -> 0 | AF11: =IFERROR(IF(OR(INDEX(Payments!$N$5:$N$64,MATCH($A11,Payments!$B$5:$B$64,0))="Overdue",INDEX(Payments!$N$5:$N$64,MATCH($A11,Payments!$B$5:$B$64,0))="Awaiting Deposit"),1,0),0) -> 0 | AG11: =IF($A11="",0,IF(SUM(Z11:AF11)>0,1,0)) -> 0 | AH11: =IF($AG11=0,"",LEFT((IF($Z11=1,"Overdue; ",""))&(IF($AA11=1,"Deadline ≤ 7 days; ",""))&(IF($AB11=1,"Action needed from us; ",""))&(IF($AC11=1,"Client feedback overdue; ",""))&(IF($AD11=1,"At iteration limit; ",""))&(IF($AE11=1,"Low margin; ",""))&(IF($AF11=1,"Unpaid invoice; ","")),LEN((IF($Z11=1,"Overdue; ",""))&(IF($AA11=1,"Deadline ≤ 7 days; ",""))&(IF($AB11=1,"Action needed from us; ",""))&(IF($AC11=1,"Client feedback overdue; ",""))&(IF($AD11=1,"At iteration limit; ",""))&(IF($AE11=1,"Low margin; ",""))&(IF($AF11=1,"Unpaid invoice; ","")))-2)) | AI11: =IF(AND($A11<>"",$J11<>"Completed",$J11<>"On Hold"),$F11*1000+(ROW()-ROW($A$5)+1),"") | AJ11: =IF($AG11=1,ROW()-ROW($A$5)+1,"")
C12: =IFERROR(INDEX(Clients!$B$5:$B$44,MATCH($B12,Clients!$A$5:$A$44,0)),"") | G12: =IF($A12="","",$F12-TODAY()) | J12: =IF($A12="","",_xlfn.IFS(OR($W12="Yes",$H12="Complete"),"Completed",$H12="On Hold","On Hold",$G12<0,"Overdue",$O12="Client","Waiting on Client",$G12<=7,"At Risk",TRUE(),"On Track")) | K12: =IF($A12="","",IFERROR(_xlfn.MAXIFS('Iteration Tracker'!$D$5:$D$124,'Iteration Tracker'!$A$5:$A$124,$A12),0)) | M12: =IF($A12="","",$L12-$K12) | R12: =IF($A12="","",IF($N12="","",TODAY()-$N12)) | Z12: =IF($A12="",0,IF(AND($G12<0,$J12<>"Completed",$J12<>"On Hold"),1,0)) -> 0 | AA12: =IF($A12="",0,IF(AND($G12>=0,$G12<=7,$J12<>"Completed",$J12<>"On Hold"),1,0)) -> 0 | AB12: =IF($A12="",0,IF(AND($O12="Us",$J12<>"Completed"),1,0)) -> 0 | AC12: =IF($A12="",0,IF(AND($H12="Awaiting Feedback",$R12<>"",$R12>7),1,0)) -> 0 | AD12: =IF($A12="",0,IF(AND($M12<>"",$M12<=1,$J12<>"Completed"),1,0)) -> 0 | AE12: =IFERROR(IF(AND($A12<>"",INDEX('Project Financials'!$AC$5:$AC$64,MATCH($A12,'Project Financials'!$A$5:$A$64,0))<0.2,INDEX('Project Financials'!$D$5:$D$64,MATCH($A12,'Project Financials'!$A$5:$A$64,0))>0),1,0),0) -> 0 | AF12: =IFERROR(IF(OR(INDEX(Payments!$N$5:$N$64,MATCH($A12,Payments!$B$5:$B$64,0))="Overdue",INDEX(Payments!$N$5:$N$64,MATCH($A12,Payments!$B$5:$B$64,0))="Awaiting Deposit"),1,0),0) -> 0 | AG12: =IF($A12="",0,IF(SUM(Z12:AF12)>0,1,0)) -> 0 | AH12: =IF($AG12=0,"",LEFT((IF($Z12=1,"Overdue; ",""))&(IF($AA12=1,"Deadline ≤ 7 days; ",""))&(IF($AB12=1,"Action needed from us; ",""))&(IF($AC12=1,"Client feedback overdue; ",""))&(IF($AD12=1,"At iteration limit; ",""))&(IF($AE12=1,"Low margin; ",""))&(IF($AF12=1,"Unpaid invoice; ","")),LEN((IF($Z12=1,"Overdue; ",""))&(IF($AA12=1,"Deadline ≤ 7 days; ",""))&(IF($AB12=1,"Action needed from us; ",""))&(IF($AC12=1,"Client feedback overdue; ",""))&(IF($AD12=1,"At iteration limit; ",""))&(IF($AE12=1,"Low margin; ",""))&(IF($AF12=1,"Unpaid invoice; ","")))-2)) | AI12: =IF(AND($A12<>"",$J12<>"Completed",$J12<>"On Hold"),$F12*1000+(ROW()-ROW($A$5)+1),"") | AJ12: =IF($AG12=1,ROW()-ROW($A$5)+1,"")
C13: =IFERROR(INDEX(Clients!$B$5:$B$44,MATCH($B13,Clients!$A$5:$A$44,0)),"") | G13: =IF($A13="","",$F13-TODAY()) | J13: =IF($A13="","",_xlfn.IFS(OR($W13="Yes",$H13="Complete"),"Completed",$H13="On Hold","On Hold",$G13<0,"Overdue",$O13="Client","Waiting on Client",$G13<=7,"At Risk",TRUE(),"On Track")) | K13: =IF($A13="","",IFERROR(_xlfn.MAXIFS('Iteration Tracker'!$D$5:$D$124,'Iteration Tracker'!$A$5:$A$124,$A13),0)) | M13: =IF($A13="","",$L13-$K13) | R13: =IF($A13="","",IF($N13="","",TODAY()-$N13)) | Z13: =IF($A13="",0,IF(AND($G13<0,$J13<>"Completed",$J13<>"On Hold"),1,0)) -> 0 | AA13: =IF($A13="",0,IF(AND($G13>=0,$G13<=7,$J13<>"Completed",$J13<>"On Hold"),1,0)) -> 0 | AB13: =IF($A13="",0,IF(AND($O13="Us",$J13<>"Completed"),1,0)) -> 0 | AC13: =IF($A13="",0,IF(AND($H13="Awaiting Feedback",$R13<>"",$R13>7),1,0)) -> 0 | AD13: =IF($A13="",0,IF(AND($M13<>"",$M13<=1,$J13<>"Completed"),1,0)) -> 0 | AE13: =IFERROR(IF(AND($A13<>"",INDEX('Project Financials'!$AC$5:$AC$64,MATCH($A13,'Project Financials'!$A$5:$A$64,0))<0.2,INDEX('Project Financials'!$D$5:$D$64,MATCH($A13,'Project Financials'!$A$5:$A$64,0))>0),1,0),0) -> 0 | AF13: =IFERROR(IF(OR(INDEX(Payments!$N$5:$N$64,MATCH($A13,Payments!$B$5:$B$64,0))="Overdue",INDEX(Payments!$N$5:$N$64,MATCH($A13,Payments!$B$5:$B$64,0))="Awaiting Deposit"),1,0),0) -> 0 | AG13: =IF($A13="",0,IF(SUM(Z13:AF13)>0,1,0)) -> 0 | AH13: =IF($AG13=0,"",LEFT((IF($Z13=1,"Overdue; ",""))&(IF($AA13=1,"Deadline ≤ 7 days; ",""))&(IF($AB13=1,"Action needed from us; ",""))&(IF($AC13=1,"Client feedback overdue; ",""))&(IF($AD13=1,"At iteration limit; ",""))&(IF($AE13=1,"Low margin; ",""))&(IF($AF13=1,"Unpaid invoice; ","")),LEN((IF($Z13=1,"Overdue; ",""))&(IF($AA13=1,"Deadline ≤ 7 days; ",""))&(IF($AB13=1,"Action needed from us; ",""))&(IF($AC13=1,"Client feedback overdue; ",""))&(IF($AD13=1,"At iteration limit; ",""))&(IF($AE13=1,"Low margin; ",""))&(IF($AF13=1,"Unpaid invoice; ","")))-2)) | AI13: =IF(AND($A13<>"",$J13<>"Completed",$J13<>"On Hold"),$F13*1000+(ROW()-ROW($A$5)+1),"") | AJ13: =IF($AG13=1,ROW()-ROW($A$5)+1,"")
C14: =IFERROR(INDEX(Clients!$B$5:$B$44,MATCH($B14,Clients!$A$5:$A$44,0)),"") | G14: =IF($A14="","",$F14-TODAY()) | J14: =IF($A14="","",_xlfn.IFS(OR($W14="Yes",$H14="Complete"),"Completed",$H14="On Hold","On Hold",$G14<0,"Overdue",$O14="Client","Waiting on Client",$G14<=7,"At Risk",TRUE(),"On Track")) | K14: =IF($A14="","",IFERROR(_xlfn.MAXIFS('Iteration Tracker'!$D$5:$D$124,'Iteration Tracker'!$A$5:$A$124,$A14),0)) | M14: =IF($A14="","",$L14-$K14) | R14: =IF($A14="","",IF($N14="","",TODAY()-$N14)) | Z14: =IF($A14="",0,IF(AND($G14<0,$J14<>"Completed",$J14<>"On Hold"),1,0)) -> 0 | AA14: =IF($A14="",0,IF(AND($G14>=0,$G14<=7,$J14<>"Completed",$J14<>"On Hold"),1,0)) -> 0 | AB14: =IF($A14="",0,IF(AND($O14="Us",$J14<>"Completed"),1,0)) -> 0 | AC14: =IF($A14="",0,IF(AND($H14="Awaiting Feedback",$R14<>"",$R14>7),1,0)) -> 0 | AD14: =IF($A14="",0,IF(AND($M14<>"",$M14<=1,$J14<>"Completed"),1,0)) -> 0 | AE14: =IFERROR(IF(AND($A14<>"",INDEX('Project Financials'!$AC$5:$AC$64,MATCH($A14,'Project Financials'!$A$5:$A$64,0))<0.2,INDEX('Project Financials'!$D$5:$D$64,MATCH($A14,'Project Financials'!$A$5:$A$64,0))>0),1,0),0) -> 0 | AF14: =IFERROR(IF(OR(INDEX(Payments!$N$5:$N$64,MATCH($A14,Payments!$B$5:$B$64,0))="Overdue",INDEX(Payments!$N$5:$N$64,MATCH($A14,Payments!$B$5:$B$64,0))="Awaiting Deposit"),1,0),0) -> 0 | AG14: =IF($A14="",0,IF(SUM(Z14:AF14)>0,1,0)) -> 0 | AH14: =IF($AG14=0,"",LEFT((IF($Z14=1,"Overdue; ",""))&(IF($AA14=1,"Deadline ≤ 7 days; ",""))&(IF($AB14=1,"Action needed from us; ",""))&(IF($AC14=1,"Client feedback overdue; ",""))&(IF($AD14=1,"At iteration limit; ",""))&(IF($AE14=1,"Low margin; ",""))&(IF($AF14=1,"Unpaid invoice; ","")),LEN((IF($Z14=1,"Overdue; ",""))&(IF($AA14=1,"Deadline ≤ 7 days; ",""))&(IF($AB14=1,"Action needed from us; ",""))&(IF($AC14=1,"Client feedback overdue; ",""))&(IF($AD14=1,"At iteration limit; ",""))&(IF($AE14=1,"Low margin; ",""))&(IF($AF14=1,"Unpaid invoice; ","")))-2)) | AI14: =IF(AND($A14<>"",$J14<>"Completed",$J14<>"On Hold"),$F14*1000+(ROW()-ROW($A$5)+1),"") | AJ14: =IF($AG14=1,ROW()-ROW($A$5)+1,"")
C15: =IFERROR(INDEX(Clients!$B$5:$B$44,MATCH($B15,Clients!$A$5:$A$44,0)),"") | G15: =IF($A15="","",$F15-TODAY()) | J15: =IF($A15="","",_xlfn.IFS(OR($W15="Yes",$H15="Complete"),"Completed",$H15="On Hold","On Hold",$G15<0,"Overdue",$O15="Client","Waiting on Client",$G15<=7,"At Risk",TRUE(),"On Track")) | K15: =IF($A15="","",IFERROR(_xlfn.MAXIFS('Iteration Tracker'!$D$5:$D$124,'Iteration Tracker'!$A$5:$A$124,$A15),0)) | M15: =IF($A15="","",$L15-$K15) | R15: =IF($A15="","",IF($N15="","",TODAY()-$N15)) | Z15: =IF($A15="",0,IF(AND($G15<0,$J15<>"Completed",$J15<>"On Hold"),1,0)) -> 0 | AA15: =IF($A15="",0,IF(AND($G15>=0,$G15<=7,$J15<>"Completed",$J15<>"On Hold"),1,0)) -> 0 | AB15: =IF($A15="",0,IF(AND($O15="Us",$J15<>"Completed"),1,0)) -> 0 | AC15: =IF($A15="",0,IF(AND($H15="Awaiting Feedback",$R15<>"",$R15>7),1,0)) -> 0 | AD15: =IF($A15="",0,IF(AND($M15<>"",$M15<=1,$J15<>"Completed"),1,0)) -> 0 | AE15: =IFERROR(IF(AND($A15<>"",INDEX('Project Financials'!$AC$5:$AC$64,MATCH($A15,'Project Financials'!$A$5:$A$64,0))<0.2,INDEX('Project Financials'!$D$5:$D$64,MATCH($A15,'Project Financials'!$A$5:$A$64,0))>0),1,0),0) -> 0 | AF15: =IFERROR(IF(OR(INDEX(Payments!$N$5:$N$64,MATCH($A15,Payments!$B$5:$B$64,0))="Overdue",INDEX(Payments!$N$5:$N$64,MATCH($A15,Payments!$B$5:$B$64,0))="Awaiting Deposit"),1,0),0) -> 0 | AG15: =IF($A15="",0,IF(SUM(Z15:AF15)>0,1,0)) -> 0 | AH15: =IF($AG15=0,"",LEFT((IF($Z15=1,"Overdue; ",""))&(IF($AA15=1,"Deadline ≤ 7 days; ",""))&(IF($AB15=1,"Action needed from us; ",""))&(IF($AC15=1,"Client feedback overdue; ",""))&(IF($AD15=1,"At iteration limit; ",""))&(IF($AE15=1,"Low margin; ",""))&(IF($AF15=1,"Unpaid invoice; ","")),LEN((IF($Z15=1,"Overdue; ",""))&(IF($AA15=1,"Deadline ≤ 7 days; ",""))&(IF($AB15=1,"Action needed from us; ",""))&(IF($AC15=1,"Client feedback overdue; ",""))&(IF($AD15=1,"At iteration limit; ",""))&(IF($AE15=1,"Low margin; ",""))&(IF($AF15=1,"Unpaid invoice; ","")))-2)) | AI15: =IF(AND($A15<>"",$J15<>"Completed",$J15<>"On Hold"),$F15*1000+(ROW()-ROW($A$5)+1),"") | AJ15: =IF($AG15=1,ROW()-ROW($A$5)+1,"")
C16: =IFERROR(INDEX(Clients!$B$5:$B$44,MATCH($B16,Clients!$A$5:$A$44,0)),"") | G16: =IF($A16="","",$F16-TODAY()) | J16: =IF($A16="","",_xlfn.IFS(OR($W16="Yes",$H16="Complete"),"Completed",$H16="On Hold","On Hold",$G16<0,"Overdue",$O16="Client","Waiting on Client",$G16<=7,"At Risk",TRUE(),"On Track")) | K16: =IF($A16="","",IFERROR(_xlfn.MAXIFS('Iteration Tracker'!$D$5:$D$124,'Iteration Tracker'!$A$5:$A$124,$A16),0)) | M16: =IF($A16="","",$L16-$K16) | R16: =IF($A16="","",IF($N16="","",TODAY()-$N16)) | Z16: =IF($A16="",0,IF(AND($G16<0,$J16<>"Completed",$J16<>"On Hold"),1,0)) -> 0 | AA16: =IF($A16="",0,IF(AND($G16>=0,$G16<=7,$J16<>"Completed",$J16<>"On Hold"),1,0)) -> 0 | AB16: =IF($A16="",0,IF(AND($O16="Us",$J16<>"Completed"),1,0)) -> 0 | AC16: =IF($A16="",0,IF(AND($H16="Awaiting Feedback",$R16<>"",$R16>7),1,0)) -> 0 | AD16: =IF($A16="",0,IF(AND($M16<>"",$M16<=1,$J16<>"Completed"),1,0)) -> 0 | AE16: =IFERROR(IF(AND($A16<>"",INDEX('Project Financials'!$AC$5:$AC$64,MATCH($A16,'Project Financials'!$A$5:$A$64,0))<0.2,INDEX('Project Financials'!$D$5:$D$64,MATCH($A16,'Project Financials'!$A$5:$A$64,0))>0),1,0),0) -> 0 | AF16: =IFERROR(IF(OR(INDEX(Payments!$N$5:$N$64,MATCH($A16,Payments!$B$5:$B$64,0))="Overdue",INDEX(Payments!$N$5:$N$64,MATCH($A16,Payments!$B$5:$B$64,0))="Awaiting Deposit"),1,0),0) -> 0 | AG16: =IF($A16="",0,IF(SUM(Z16:AF16)>0,1,0)) -> 0 | AH16: =IF($AG16=0,"",LEFT((IF($Z16=1,"Overdue; ",""))&(IF($AA16=1,"Deadline ≤ 7 days; ",""))&(IF($AB16=1,"Action needed from us; ",""))&(IF($AC16=1,"Client feedback overdue; ",""))&(IF($AD16=1,"At iteration limit; ",""))&(IF($AE16=1,"Low margin; ",""))&(IF($AF16=1,"Unpaid invoice; ","")),LEN((IF($Z16=1,"Overdue; ",""))&(IF($AA16=1,"Deadline ≤ 7 days; ",""))&(IF($AB16=1,"Action needed from us; ",""))&(IF($AC16=1,"Client feedback overdue; ",""))&(IF($AD16=1,"At iteration limit; ",""))&(IF($AE16=1,"Low margin; ",""))&(IF($AF16=1,"Unpaid invoice; ","")))-2)) | AI16: =IF(AND($A16<>"",$J16<>"Completed",$J16<>"On Hold"),$F16*1000+(ROW()-ROW($A$5)+1),"") | AJ16: =IF($AG16=1,ROW()-ROW($A$5)+1,"")
... C64: =IFERROR(INDEX(Clients!$B$5:$B$44,MATCH($B64,Clients!$A$5:$A$44,0)),"") | G64: =IF($A64="","",$F64-TODAY()) | J64: =IF($A64="","",_xlfn.IFS(OR($W64="Yes",$H64="Complete"),"Completed",$H64="On Hold","On Hold",$G64<0,"Overdue",$O64="Client","Waiting on Client",$G64<=7,"At Risk",TRUE(),"On Track")) | K64: =IF($A64="","",IFERROR(_xlfn.MAXIFS('Iteration Tracker'!$D$5:$D$124,'Iteration Tracker'!$A$5:$A$124,$A64),0)) | M64: =IF($A64="","",$L64-$K64) | R64: =IF($A64="","",IF($N64="","",TODAY()-$N64)) | Z64: =IF($A64="",0,IF(AND($G64<0,$J64<>"Completed",$J64<>"On Hold"),1,0)) -> 0 | AA64: =IF($A64="",0,IF(AND($G64>=0,$G64<=7,$J64<>"Completed",$J64<>"On Hold"),1,0)) -> 0 | AB64: =IF($A64="",0,IF(AND($O64="Us",$J64<>"Completed"),1,0)) -> 0 | AC64: =IF($A64="",0,IF(AND($H64="Awaiting Feedback",$R64<>"",$R64>7),1,0)) -> 0 | AD64: =IF($A64="",0,IF(AND($M64<>"",$M64<=1,$J64<>"Completed"),1,0)) -> 0 | AE64: =IFERROR(IF(AND($A64<>"",INDEX('Project Financials'!$AC$5:$AC$64,MATCH($A64,'Project Financials'!$A$5:$A$64,0))<0.2,INDEX('Project Financials'!$D$5:$D$64,MATCH($A64,'Project Financials'!$A$5:$A$64,0))>0),1,0),0) -> 0 | AF64: =IFERROR(IF(OR(INDEX(Payments!$N$5:$N$64,MATCH($A64,Payments!$B$5:$B$64,0))="Overdue",INDEX(Payments!$N$5:$N$64,MATCH($A64,Payments!$B$5:$B$64,0))="Awaiting Deposit"),1,0),0) -> 0 | AG64: =IF($A64="",0,IF(SUM(Z64:AF64)>0,1,0)) -> 0 | AH64: =IF($AG64=0,"",LEFT((IF($Z64=1,"Overdue; ",""))&(IF($AA64=1,"Deadline ≤ 7 days; ",""))&(IF($AB64=1,"Action needed from us; ",""))&(IF($AC64=1,"Client feedback overdue; ",""))&(IF($AD64=1,"At iteration limit; ",""))&(IF($AE64=1,"Low margin; ",""))&(IF($AF64=1,"Unpaid invoice; ","")),LEN((IF($Z64=1,"Overdue; ",""))&(IF($AA64=1,"Deadline ≤ 7 days; ",""))&(IF($AB64=1,"Action needed from us; ",""))&(IF($AC64=1,"Client feedback overdue; ",""))&(IF($AD64=1,"At iteration limit; ",""))&(IF($AE64=1,"Low margin; ",""))&(IF($AF64=1,"Unpaid invoice; ","")))-2)) | AI64: =IF(AND($A64<>"",$J64<>"Completed",$J64<>"On Hold"),$F64*1000+(ROW()-ROW($A$5)+1),"") | AJ64: =IF($AG64=1,ROW()-ROW($A$5)+1,"")

Sheet Client Brief
A1: CLIENT BRIEF — Creative Brief Database
A2: Client Direction • Olfactive Direction • My Creative Interpretation. One row per fragrance, linked by Project ID.
B3: INPUT — type or choose here | F3: CALCULATED — formula, do not edit | J3: AUTO-LOOKUP — pulled from another sheet
A4: Project ID | B4: Client | C4: Fragrance | D4: Target Customer | E4: Gender Positioning | F4: Target Age | G4: Intended Market | H4: Desired Retail Price | I4: Desired Concentration | J4: Bottle Size | K4: Product Type | L4: Client Description | M4: Overall Feeling | N4: Desired Opening | O4: Desired Heart | P4: Desired Drydown | Q4: Top Notes Requested | R4: Heart Notes Requested | S4: Base Notes Requested | T4: Preferred Fragrance Families | U4: Reference Perfumes | V4: Materials/Notes They Like | W4: Materials/Notes They Dislike | X4: Must Include | Y4: Must Avoid | Z4: Desired Strength | AA4: Desired Projection | AB4: Desired Longevity | AC4: Season | AD4: Occasion | AE4: Day/Night | AF4: Commercial vs Artistic | AG4: What I Think The Client Actually Wants | AH4: Proposed DNA | AI4: Recommended Top Direction | AJ4: Recommended Heart Direction | AK4: Recommended Base Direction | AL4: Suggested Materials | AM4: Suggested Accords | AN4: Potential Reference Structures | AO4: Creative Twist | AP4: Potential Problems With Brief | AQ4: Questions To Ask Client | AR4: Development Strategy
B5: =IF($A5="","",IFERROR(INDEX('Fragrance Projects'!$C$5:$C$64,MATCH($A5,'Fragrance Projects'!$A$5:$A$64,0)),"")) | C5: =IF($A5="","",IFERROR(INDEX('Fragrance Projects'!$D$5:$D$64,MATCH($A5,'Fragrance Projects'!$A$5:$A$64,0)),""))
B6: =IF($A6="","",IFERROR(INDEX('Fragrance Projects'!$C$5:$C$64,MATCH($A6,'Fragrance Projects'!$A$5:$A$64,0)),"")) | C6: =IF($A6="","",IFERROR(INDEX('Fragrance Projects'!$D$5:$D$64,MATCH($A6,'Fragrance Projects'!$A$5:$A$64,0)),""))
B7: =IF($A7="","",IFERROR(INDEX('Fragrance Projects'!$C$5:$C$64,MATCH($A7,'Fragrance Projects'!$A$5:$A$64,0)),"")) | C7: =IF($A7="","",IFERROR(INDEX('Fragrance Projects'!$D$5:$D$64,MATCH($A7,'Fragrance Projects'!$A$5:$A$64,0)),""))
B8: =IF($A8="","",IFERROR(INDEX('Fragrance Projects'!$C$5:$C$64,MATCH($A8,'Fragrance Projects'!$A$5:$A$64,0)),"")) | C8: =IF($A8="","",IFERROR(INDEX('Fragrance Projects'!$D$5:$D$64,MATCH($A8,'Fragrance Projects'!$A$5:$A$64,0)),""))
B9: =IF($A9="","",IFERROR(INDEX('Fragrance Projects'!$C$5:$C$64,MATCH($A9,'Fragrance Projects'!$A$5:$A$64,0)),"")) | C9: =IF($A9="","",IFERROR(INDEX('Fragrance Projects'!$D$5:$D$64,MATCH($A9,'Fragrance Projects'!$A$5:$A$64,0)),""))
B10: =IF($A10="","",IFERROR(INDEX('Fragrance Projects'!$C$5:$C$64,MATCH($A10,'Fragrance Projects'!$A$5:$A$64,0)),"")) | C10: =IF($A10="","",IFERROR(INDEX('Fragrance Projects'!$D$5:$D$64,MATCH($A10,'Fragrance Projects'!$A$5:$A$64,0)),""))
B11: =IF($A11="","",IFERROR(INDEX('Fragrance Projects'!$C$5:$C$64,MATCH($A11,'Fragrance Projects'!$A$5:$A$64,0)),"")) | C11: =IF($A11="","",IFERROR(INDEX('Fragrance Projects'!$D$5:$D$64,MATCH($A11,'Fragrance Projects'!$A$5:$A$64,0)),""))
B12: =IF($A12="","",IFERROR(INDEX('Fragrance Projects'!$C$5:$C$64,MATCH($A12,'Fragrance Projects'!$A$5:$A$64,0)),"")) | C12: =IF($A12="","",IFERROR(INDEX('Fragrance Projects'!$D$5:$D$64,MATCH($A12,'Fragrance Projects'!$A$5:$A$64,0)),""))
B13: =IF($A13="","",IFERROR(INDEX('Fragrance Projects'!$C$5:$C$64,MATCH($A13,'Fragrance Projects'!$A$5:$A$64,0)),"")) | C13: =IF($A13="","",IFERROR(INDEX('Fragrance Projects'!$D$5:$D$64,MATCH($A13,'Fragrance Projects'!$A$5:$A$64,0)),""))
B14: =IF($A14="","",IFERROR(INDEX('Fragrance Projects'!$C$5:$C$64,MATCH($A14,'Fragrance Projects'!$A$5:$A$64,0)),"")) | C14: =IF($A14="","",IFERROR(INDEX('Fragrance Projects'!$D$5:$D$64,MATCH($A14,'Fragrance Projects'!$A$5:$A$64,0)),""))
B15: =IF($A15="","",IFERROR(INDEX('Fragrance Projects'!$C$5:$C$64,MATCH($A15,'Fragrance Projects'!$A$5:$A$64,0)),"")) | C15: =IF($A15="","",IFERROR(INDEX('Fragrance Projects'!$D$5:$D$64,MATCH($A15,'Fragrance Projects'!$A$5:$A$64,0)),""))
B16: =IF($A16="","",IFERROR(INDEX('Fragrance Projects'!$C$5:$C$64,MATCH($A16,'Fragrance Projects'!$A$5:$A$64,0)),"")) | C16: =IF($A16="","",IFERROR(INDEX('Fragrance Projects'!$D$5:$D$64,MATCH($A16,'Fragrance Projects'!$A$5:$A$64,0)),""))
... B64: =IF($A64="","",IFERROR(INDEX('Fragrance Projects'!$C$5:$C$64,MATCH($A64,'Fragrance Projects'!$A$5:$A$64,0)),"")) | C64: =IF($A64="","",IFERROR(INDEX('Fragrance Projects'!$D$5:$D$64,MATCH($A64,'Fragrance Projects'!$A$5:$A$64,0)),""))

Sheet Iteration Tracker
A1: ITERATION TRACKER — Every Formula Version
A2: One row per iteration/version. Total Iteration Cost and per-project cost totals are calculated automatically.
B3: INPUT — type or choose here | F3: CALCULATED — formula, do not edit | J3: AUTO-LOOKUP — pulled from another sheet
A4: Project ID | B4: Client | C4: Fragrance | D4: Iteration No. | E4: Formula Version | F4: Date Created | G4: Date Compounded | H4: Date Evaluated | I4: Sample Sent Date | J4: Sample Received Date | K4: Feedback Received Date | L4: Client Rating /10 | M4: My Rating /10 | N4: Client Feedback | O4: My Evaluation | P4: Changes Required | Q4: Changes Made | R4: Next Version Required? | S4: Approved? | T4: Time Spent (hrs) | U4: Material Cost | V4: Shipping Cost | W4: Other Cost | X4: Total Iteration Cost
B5: =IF($A5="","",IFERROR(INDEX('Fragrance Projects'!$C$5:$C$64,MATCH($A5,'Fragrance Projects'!$A$5:$A$64,0)),"")) | C5: =IF($A5="","",IFERROR(INDEX('Fragrance Projects'!$D$5:$D$64,MATCH($A5,'Fragrance Projects'!$A$5:$A$64,0)),"")) | X5: =IF($A5="","",SUM($U5:$W5))
B6: =IF($A6="","",IFERROR(INDEX('Fragrance Projects'!$C$5:$C$64,MATCH($A6,'Fragrance Projects'!$A$5:$A$64,0)),"")) | C6: =IF($A6="","",IFERROR(INDEX('Fragrance Projects'!$D$5:$D$64,MATCH($A6,'Fragrance Projects'!$A$5:$A$64,0)),"")) | X6: =IF($A6="","",SUM($U6:$W6))
B7: =IF($A7="","",IFERROR(INDEX('Fragrance Projects'!$C$5:$C$64,MATCH($A7,'Fragrance Projects'!$A$5:$A$64,0)),"")) | C7: =IF($A7="","",IFERROR(INDEX('Fragrance Projects'!$D$5:$D$64,MATCH($A7,'Fragrance Projects'!$A$5:$A$64,0)),"")) | X7: =IF($A7="","",SUM($U7:$W7))
B8: =IF($A8="","",IFERROR(INDEX('Fragrance Projects'!$C$5:$C$64,MATCH($A8,'Fragrance Projects'!$A$5:$A$64,0)),"")) | C8: =IF($A8="","",IFERROR(INDEX('Fragrance Projects'!$D$5:$D$64,MATCH($A8,'Fragrance Projects'!$A$5:$A$64,0)),"")) | X8: =IF($A8="","",SUM($U8:$W8))
B9: =IF($A9="","",IFERROR(INDEX('Fragrance Projects'!$C$5:$C$64,MATCH($A9,'Fragrance Projects'!$A$5:$A$64,0)),"")) | C9: =IF($A9="","",IFERROR(INDEX('Fragrance Projects'!$D$5:$D$64,MATCH($A9,'Fragrance Projects'!$A$5:$A$64,0)),"")) | X9: =IF($A9="","",SUM($U9:$W9))
B10: =IF($A10="","",IFERROR(INDEX('Fragrance Projects'!$C$5:$C$64,MATCH($A10,'Fragrance Projects'!$A$5:$A$64,0)),"")) | C10: =IF($A10="","",IFERROR(INDEX('Fragrance Projects'!$D$5:$D$64,MATCH($A10,'Fragrance Projects'!$A$5:$A$64,0)),"")) | X10: =IF($A10="","",SUM($U10:$W10))
B11: =IF($A11="","",IFERROR(INDEX('Fragrance Projects'!$C$5:$C$64,MATCH($A11,'Fragrance Projects'!$A$5:$A$64,0)),"")) | C11: =IF($A11="","",IFERROR(INDEX('Fragrance Projects'!$D$5:$D$64,MATCH($A11,'Fragrance Projects'!$A$5:$A$64,0)),"")) | X11: =IF($A11="","",SUM($U11:$W11))
B12: =IF($A12="","",IFERROR(INDEX('Fragrance Projects'!$C$5:$C$64,MATCH($A12,'Fragrance Projects'!$A$5:$A$64,0)),"")) | C12: =IF($A12="","",IFERROR(INDEX('Fragrance Projects'!$D$5:$D$64,MATCH($A12,'Fragrance Projects'!$A$5:$A$64,0)),"")) | X12: =IF($A12="","",SUM($U12:$W12))
B13: =IF($A13="","",IFERROR(INDEX('Fragrance Projects'!$C$5:$C$64,MATCH($A13,'Fragrance Projects'!$A$5:$A$64,0)),"")) | C13: =IF($A13="","",IFERROR(INDEX('Fragrance Projects'!$D$5:$D$64,MATCH($A13,'Fragrance Projects'!$A$5:$A$64,0)),"")) | X13: =IF($A13="","",SUM($U13:$W13))
B14: =IF($A14="","",IFERROR(INDEX('Fragrance Projects'!$C$5:$C$64,MATCH($A14,'Fragrance Projects'!$A$5:$A$64,0)),"")) | C14: =IF($A14="","",IFERROR(INDEX('Fragrance Projects'!$D$5:$D$64,MATCH($A14,'Fragrance Projects'!$A$5:$A$64,0)),"")) | X14: =IF($A14="","",SUM($U14:$W14))
B15: =IF($A15="","",IFERROR(INDEX('Fragrance Projects'!$C$5:$C$64,MATCH($A15,'Fragrance Projects'!$A$5:$A$64,0)),"")) | C15: =IF($A15="","",IFERROR(INDEX('Fragrance Projects'!$D$5:$D$64,MATCH($A15,'Fragrance Projects'!$A$5:$A$64,0)),"")) | X15: =IF($A15="","",SUM($U15:$W15))
B16: =IF($A16="","",IFERROR(INDEX('Fragrance Projects'!$C$5:$C$64,MATCH($A16,'Fragrance Projects'!$A$5:$A$64,0)),"")) | C16: =IF($A16="","",IFERROR(INDEX('Fragrance Projects'!$D$5:$D$64,MATCH($A16,'Fragrance Projects'!$A$5:$A$64,0)),"")) | X16: =IF($A16="","",SUM($U16:$W16))
... B124: =IF($A124="","",IFERROR(INDEX('Fragrance Projects'!$C$5:$C$64,MATCH($A124,'Fragrance Projects'!$A$5:$A$64,0)),"")) | C124: =IF($A124="","",IFERROR(INDEX('Fragrance Projects'!$D$5:$D$64,MATCH($A124,'Fragrance Projects'!$A$5:$A$64,0)),"")) | X124: =IF($A124="","",SUM($U124:$W124))

Sheet Project Financials
A1: PROJECT FINANCIALS — Profitability Calculator
A2: Expense columns pull automatically from the Expense Log by Project ID and category. Only Agreed Revenue and Hourly Rate are typed in.
B3: INPUT — type or choose here | F3: CALCULATED — formula, do not edit | J3: AUTO-LOOKUP — pulled from another sheet
A4: Project ID | B4: Client | C4: Fragrance | D4: Agreed Revenue | E4: Deposit Received | F4: Remaining Revenue | G4: Materials | H4: Alcohol/Carrier | I4: Sample Bottles | J4: Packaging | K4: Labels | L4: Shipping | M4: Documentation | N4: SDS Costs | O4: IFRA/Allergen Costs | P4: CPSR/Safety Assessment | Q4: External Compounding | R4: Outsourcing | S4: Payment Processing Fees | T4: Other Expenses | U4: Total Direct Expenses | V4: Hours Worked | W4: Hourly Value of My Time | X4: Labour Cost | Y4: True Project Cost | Z4: Gross Profit Before Labour | AA4: Profit After Labour | AB4: Gross Margin % | AC4: True Margin % | AD4: Effective Hourly Earnings
B5: =IF($A5="","",IFERROR(INDEX('Fragrance Projects'!$C$5:$C$64,MATCH($A5,'Fragrance Projects'!$A$5:$A$64,0)),"")) | C5: =IF($A5="","",IFERROR(INDEX('Fragrance Projects'!$D$5:$D$64,MATCH($A5,'Fragrance Projects'!$A$5:$A$64,0)),"")) | E5: =IF($A5="","",IFERROR(INDEX(Payments!$G$5:$G$64,MATCH($A5,Payments!$B$5:$B$64,0)),0)+IFERROR(INDEX(Payments!$K$5:$K$64,MATCH($A5,Payments!$B$5:$B$64,0)),0)) | F5: =IF($A5="","",$D5-$E5) | G5: =IF($A5="","",SUMIFS('Expense Log'!$J$5:$J$154,'Expense Log'!$B$5:$B$154,$A5,'Expense Log'!$E$5:$E$154,"Raw Materials")) | H5: =IF($A5="","",SUMIFS('Expense Log'!$J$5:$J$154,'Expense Log'!$B$5:$B$154,$A5,'Expense Log'!$E$5:$E$154,"Alcohol/Carrier")) | I5: =IF($A5="","",SUMIFS('Expense Log'!$J$5:$J$154,'Expense Log'!$B$5:$B$154,$A5,'Expense Log'!$E$5:$E$154,"Bottles")+SUMIFS('Expense Log'!$J$5:$J$154,'Expense Log'!$B$5:$B$154,$A5,'Expense Log'!$E$5:$E$154,"Sample Vials")) | J5: =IF($A5="","",SUMIFS('Expense Log'!$J$5:$J$154,'Expense Log'!$B$5:$B$154,$A5,'Expense Log'!$E$5:$E$154,"Packaging")) | K5: =IF($A5="","",SUMIFS('Expense Log'!$J$5:$J$154,'Expense Log'!$B$5:$B$154,$A5,'Expense Log'!$E$5:$E$154,"Labels")) | L5: =IF($A5="","",SUMIFS('Expense Log'!$J$5:$J$154,'Expense Log'!$B$5:$B$154,$A5,'Expense Log'!$E$5:$E$154,"Shipping")) | M5: =IF($A5="","",SUMIFS('Expense Log'!$J$5:$J$154,'Expense Log'!$B$5:$B$154,$A5,'Expense Log'!$E$5:$E$154,"Documentation")) | N5: =IF($A5="","",SUMIFS('Expense Log'!$J$5:$J$154,'Expense Log'!$B$5:$B$154,$A5,'Expense Log'!$E$5:$E$154,"SDS")) | O5: =IF($A5="","",SUMIFS('Expense Log'!$J$5:$J$154,'Expense Log'!$B$5:$B$154,$A5,'Expense Log'!$E$5:$E$154,"IFRA/Allergen")) | P5: =IF($A5="","",SUMIFS('Expense Log'!$J$5:$J$154,'Expense Log'!$B$5:$B$154,$A5,'Expense Log'!$E$5:$E$154,"CPSR")) | Q5: =IF($A5="","",SUMIFS('Expense Log'!$J$5:$J$154,'Expense Log'!$B$5:$B$154,$A5,'Expense Log'!$E$5:$E$154,"Compounding")) | R5: =IF($A5="","",SUMIFS('Expense Log'!$J$5:$J$154,'Expense Log'!$B$5:$B$154,$A5,'Expense Log'!$E$5:$E$154,"External Perfumer")) | S5: =IF($A5="","",SUMIFS('Expense Log'!$J$5:$J$154,'Expense Log'!$B$5:$B$154,$A5,'Expense Log'!$E$5:$E$154,"Payment Fees")) | T5: =IF($A5="","",SUMIFS('Expense Log'!$J$5:$J$154,'Expense Log'!$B$5:$B$154,$A5,'Expense Log'!$E$5:$E$154,"Testing")+SUMIFS('Expense Log'!$J$5:$J$154,'Expense Log'!$B$5:$B$154,$A5,'Expense Log'!$E$5:$E$154,"Software")+SUMIFS('Expense Log'!$J$5:$J$154,'Expense Log'!$B$5:$B$154,$A5,'Expense Log'!$E$5:$E$154,"Other")) | U5: =IF($A5="","",SUM($G5:$T5)) | V5: =IF($A5="","",SUMIFS('Iteration Tracker'!$T$5:$T$124,'Iteration Tracker'!$A$5:$A$124,$A5)) | X5: =IF($A5="","",$V5*$W5) | Y5: =IF($A5="","",$U5+$X5) | Z5: =IF($A5="","",$D5-$U5) | AA5: =IF($A5="","",$D5-$Y5) | AB5: =IF(OR($A5="",$D5=0),"",$Z5/$D5) | AC5: =IF(OR($A5="",$D5=0),"",$AA5/$D5) | AD5: =IFERROR(IF($A5="","",$Z5/$V5),"")
B6: =IF($A6="","",IFERROR(INDEX('Fragrance Projects'!$C$5:$C$64,MATCH($A6,'Fragrance Projects'!$A$5:$A$64,0)),"")) | C6: =IF($A6="","",IFERROR(INDEX('Fragrance Projects'!$D$5:$D$64,MATCH($A6,'Fragrance Projects'!$A$5:$A$64,0)),"")) | E6: =IF($A6="","",IFERROR(INDEX(Payments!$G$5:$G$64,MATCH($A6,Payments!$B$5:$B$64,0)),0)+IFERROR(INDEX(Payments!$K$5:$K$64,MATCH($A6,Payments!$B$5:$B$64,0)),0)) | F6: =IF($A6="","",$D6-$E6) | G6: =IF($A6="","",SUMIFS('Expense Log'!$J$5:$J$154,'Expense Log'!$B$5:$B$154,$A6,'Expense Log'!$E$5:$E$154,"Raw Materials")) | H6: =IF($A6="","",SUMIFS('Expense Log'!$J$5:$J$154,'Expense Log'!$B$5:$B$154,$A6,'Expense Log'!$E$5:$E$154,"Alcohol/Carrier")) | I6: =IF($A6="","",SUMIFS('Expense Log'!$J$5:$J$154,'Expense Log'!$B$5:$B$154,$A6,'Expense Log'!$E$5:$E$154,"Bottles")+SUMIFS('Expense Log'!$J$5:$J$154,'Expense Log'!$B$5:$B$154,$A6,'Expense Log'!$E$5:$E$154,"Sample Vials")) | J6: =IF($A6="","",SUMIFS('Expense Log'!$J$5:$J$154,'Expense Log'!$B$5:$B$154,$A6,'Expense Log'!$E$5:$E$154,"Packaging")) | K6: =IF($A6="","",SUMIFS('Expense Log'!$J$5:$J$154,'Expense Log'!$B$5:$B$154,$A6,'Expense Log'!$E$5:$E$154,"Labels")) | L6: =IF($A6="","",SUMIFS('Expense Log'!$J$5:$J$154,'Expense Log'!$B$5:$B$154,$A6,'Expense Log'!$E$5:$E$154,"Shipping")) | M6: =IF($A6="","",SUMIFS('Expense Log'!$J$5:$J$154,'Expense Log'!$B$5:$B$154,$A6,'Expense Log'!$E$5:$E$154,"Documentation")) | N6: =IF($A6="","",SUMIFS('Expense Log'!$J$5:$J$154,'Expense Log'!$B$5:$B$154,$A6,'Expense Log'!$E$5:$E$154,"SDS")) | O6: =IF($A6="","",SUMIFS('Expense Log'!$J$5:$J$154,'Expense Log'!$B$5:$B$154,$A6,'Expense Log'!$E$5:$E$154,"IFRA/Allergen")) | P6: =IF($A6="","",SUMIFS('Expense Log'!$J$5:$J$154,'Expense Log'!$B$5:$B$154,$A6,'Expense Log'!$E$5:$E$154,"CPSR")) | Q6: =IF($A6="","",SUMIFS('Expense Log'!$J$5:$J$154,'Expense Log'!$B$5:$B$154,$A6,'Expense Log'!$E$5:$E$154,"Compounding")) | R6: =IF($A6="","",SUMIFS('Expense Log'!$J$5:$J$154,'Expense Log'!$B$5:$B$154,$A6,'Expense Log'!$E$5:$E$154,"External Perfumer")) | S6: =IF($A6="","",SUMIFS('Expense Log'!$J$5:$J$154,'Expense Log'!$B$5:$B$154,$A6,'Expense Log'!$E$5:$E$154,"Payment Fees")) | T6: =IF($A6="","",SUMIFS('Expense Log'!$J$5:$J$154,'Expense Log'!$B$5:$B$154,$A6,'Expense Log'!$E$5:$E$154,"Testing")+SUMIFS('Expense Log'!$J$5:$J$154,'Expense Log'!$B$5:$B$154,$A6,'Expense Log'!$E$5:$E$154,"Software")+SUMIFS('Expense Log'!$J$5:$J$154,'Expense Log'!$B$5:$B$154,$A6,'Expense Log'!$E$5:$E$154,"Other")) | U6: =IF($A6="","",SUM($G6:$T6)) | V6: =IF($A6="","",SUMIFS('Iteration Tracker'!$T$5:$T$124,'Iteration Tracker'!$A$5:$A$124,$A6)) | X6: =IF($A6="","",$V6*$W6) | Y6: =IF($A6="","",$U6+$X6) | Z6: =IF($A6="","",$D6-$U6) | AA6: =IF($A6="","",$D6-$Y6) | AB6: =IF(OR($A6="",$D6=0),"",$Z6/$D6) | AC6: =IF(OR($A6="",$D6=0),"",$AA6/$D6) | AD6: =IFERROR(IF($A6="","",$Z6/$V6),"")
B7: =IF($A7="","",IFERROR(INDEX('Fragrance Projects'!$C$5:$C$64,MATCH($A7,'Fragrance Projects'!$A$5:$A$64,0)),"")) | C7: =IF($A7="","",IFERROR(INDEX('Fragrance Projects'!$D$5:$D$64,MATCH($A7,'Fragrance Projects'!$A$5:$A$64,0)),"")) | E7: =IF($A7="","",IFERROR(INDEX(Payments!$G$5:$G$64,MATCH($A7,Payments!$B$5:$B$64,0)),0)+IFERROR(INDEX(Payments!$K$5:$K$64,MATCH($A7,Payments!$B$5:$B$64,0)),0)) | F7: =IF($A7="","",$D7-$E7) | G7: =IF($A7="","",SUMIFS('Expense Log'!$J$5:$J$154,'Expense Log'!$B$5:$B$154,$A7,'Expense Log'!$E$5:$E$154,"Raw Materials")) | H7: =IF($A7="","",SUMIFS('Expense Log'!$J$5:$J$154,'Expense Log'!$B$5:$B$154,$A7,'Expense Log'!$E$5:$E$154,"Alcohol/Carrier")) | I7: =IF($A7="","",SUMIFS('Expense Log'!$J$5:$J$154,'Expense Log'!$B$5:$B$154,$A7,'Expense Log'!$E$5:$E$154,"Bottles")+SUMIFS('Expense Log'!$J$5:$J$154,'Expense Log'!$B$5:$B$154,$A7,'Expense Log'!$E$5:$E$154,"Sample Vials")) | J7: =IF($A7="","",SUMIFS('Expense Log'!$J$5:$J$154,'Expense Log'!$B$5:$B$154,$A7,'Expense Log'!$E$5:$E$154,"Packaging")) | K7: =IF($A7="","",SUMIFS('Expense Log'!$J$5:$J$154,'Expense Log'!$B$5:$B$154,$A7,'Expense Log'!$E$5:$E$154,"Labels")) | L7: =IF($A7="","",SUMIFS('Expense Log'!$J$5:$J$154,'Expense Log'!$B$5:$B$154,$A7,'Expense Log'!$E$5:$E$154,"Shipping")) | M7: =IF($A7="","",SUMIFS('Expense Log'!$J$5:$J$154,'Expense Log'!$B$5:$B$154,$A7,'Expense Log'!$E$5:$E$154,"Documentation")) | N7: =IF($A7="","",SUMIFS('Expense Log'!$J$5:$J$154,'Expense Log'!$B$5:$B$154,$A7,'Expense Log'!$E$5:$E$154,"SDS")) | O7: =IF($A7="","",SUMIFS('Expense Log'!$J$5:$J$154,'Expense Log'!$B$5:$B$154,$A7,'Expense Log'!$E$5:$E$154,"IFRA/Allergen")) | P7: =IF($A7="","",SUMIFS('Expense Log'!$J$5:$J$154,'Expense Log'!$B$5:$B$154,$A7,'Expense Log'!$E$5:$E$154,"CPSR")) | Q7: =IF($A7="","",SUMIFS('Expense Log'!$J$5:$J$154,'Expense Log'!$B$5:$B$154,$A7,'Expense Log'!$E$5:$E$154,"Compounding")) | R7: =IF($A7="","",SUMIFS('Expense Log'!$J$5:$J$154,'Expense Log'!$B$5:$B$154,$A7,'Expense Log'!$E$5:$E$154,"External Perfumer")) | S7: =IF($A7="","",SUMIFS('Expense Log'!$J$5:$J$154,'Expense Log'!$B$5:$B$154,$A7,'Expense Log'!$E$5:$E$154,"Payment Fees")) | T7: =IF($A7="","",SUMIFS('Expense Log'!$J$5:$J$154,'Expense Log'!$B$5:$B$154,$A7,'Expense Log'!$E$5:$E$154,"Testing")+SUMIFS('Expense Log'!$J$5:$J$154,'Expense Log'!$B$5:$B$154,$A7,'Expense Log'!$E$5:$E$154,"Software")+SUMIFS('Expense Log'!$J$5:$J$154,'Expense Log'!$B$5:$B$154,$A7,'Expense Log'!$E$5:$E$154,"Other")) | U7: =IF($A7="","",SUM($G7:$T7)) | V7: =IF($A7="","",SUMIFS('Iteration Tracker'!$T$5:$T$124,'Iteration Tracker'!$A$5:$A$124,$A7)) | X7: =IF($A7="","",$V7*$W7) | Y7: =IF($A7="","",$U7+$X7) | Z7: =IF($A7="","",$D7-$U7) | AA7: =IF($A7="","",$D7-$Y7) | AB7: =IF(OR($A7="",$D7=0),"",$Z7/$D7) | AC7: =IF(OR($A7="",$D7=0),"",$AA7/$D7) | AD7: =IFERROR(IF($A7="","",$Z7/$V7),"")
B8: =IF($A8="","",IFERROR(INDEX('Fragrance Projects'!$C$5:$C$64,MATCH($A8,'Fragrance Projects'!$A$5:$A$64,0)),"")) | C8: =IF($A8="","",IFERROR(INDEX('Fragrance Projects'!$D$5:$D$64,MATCH($A8,'Fragrance Projects'!$A$5:$A$64,0)),"")) | E8: =IF($A8="","",IFERROR(INDEX(Payments!$G$5:$G$64,MATCH($A8,Payments!$B$5:$B$64,0)),0)+IFERROR(INDEX(Payments!$K$5:$K$64,MATCH($A8,Payments!$B$5:$B$64,0)),0)) | F8: =IF($A8="","",$D8-$E8) | G8: =IF($A8="","",SUMIFS('Expense Log'!$J$5:$J$154,'Expense Log'!$B$5:$B$154,$A8,'Expense Log'!$E$5:$E$154,"Raw Materials")) | H8: =IF($A8="","",SUMIFS('Expense Log'!$J$5:$J$154,'Expense Log'!$B$5:$B$154,$A8,'Expense Log'!$E$5:$E$154,"Alcohol/Carrier")) | I8: =IF($A8="","",SUMIFS('Expense Log'!$J$5:$J$154,'Expense Log'!$B$5:$B$154,$A8,'Expense Log'!$E$5:$E$154,"Bottles")+SUMIFS('Expense Log'!$J$5:$J$154,'Expense Log'!$B$5:$B$154,$A8,'Expense Log'!$E$5:$E$154,"Sample Vials")) | J8: =IF($A8="","",SUMIFS('Expense Log'!$J$5:$J$154,'Expense Log'!$B$5:$B$154,$A8,'Expense Log'!$E$5:$E$154,"Packaging")) | K8: =IF($A8="","",SUMIFS('Expense Log'!$J$5:$J$154,'Expense Log'!$B$5:$B$154,$A8,'Expense Log'!$E$5:$E$154,"Labels")) | L8: =IF($A8="","",SUMIFS('Expense Log'!$J$5:$J$154,'Expense Log'!$B$5:$B$154,$A8,'Expense Log'!$E$5:$E$154,"Shipping")) | M8: =IF($A8="","",SUMIFS('Expense Log'!$J$5:$J$154,'Expense Log'!$B$5:$B$154,$A8,'Expense Log'!$E$5:$E$154,"Documentation")) | N8: =IF($A8="","",SUMIFS('Expense Log'!$J$5:$J$154,'Expense Log'!$B$5:$B$154,$A8,'Expense Log'!$E$5:$E$154,"SDS")) | O8: =IF($A8="","",SUMIFS('Expense Log'!$J$5:$J$154,'Expense Log'!$B$5:$B$154,$A8,'Expense Log'!$E$5:$E$154,"IFRA/Allergen")) | P8: =IF($A8="","",SUMIFS('Expense Log'!$J$5:$J$154,'Expense Log'!$B$5:$B$154,$A8,'Expense Log'!$E$5:$E$154,"CPSR")) | Q8: =IF($A8="","",SUMIFS('Expense Log'!$J$5:$J$154,'Expense Log'!$B$5:$B$154,$A8,'Expense Log'!$E$5:$E$154,"Compounding")) | R8: =IF($A8="","",SUMIFS('Expense Log'!$J$5:$J$154,'Expense Log'!$B$5:$B$154,$A8,'Expense Log'!$E$5:$E$154,"External Perfumer")) | S8: =IF($A8="","",SUMIFS('Expense Log'!$J$5:$J$154,'Expense Log'!$B$5:$B$154,$A8,'Expense Log'!$E$5:$E$154,"Payment Fees")) | T8: =IF($A8="","",SUMIFS('Expense Log'!$J$5:$J$154,'Expense Log'!$B$5:$B$154,$A8,'Expense Log'!$E$5:$E$154,"Testing")+SUMIFS('Expense Log'!$J$5:$J$154,'Expense Log'!$B$5:$B$154,$A8,'Expense Log'!$E$5:$E$154,"Software")+SUMIFS('Expense Log'!$J$5:$J$154,'Expense Log'!$B$5:$B$154,$A8,'Expense Log'!$E$5:$E$154,"Other")) | U8: =IF($A8="","",SUM($G8:$T8)) | V8: =IF($A8="","",SUMIFS('Iteration Tracker'!$T$5:$T$124,'Iteration Tracker'!$A$5:$A$124,$A8)) | X8: =IF($A8="","",$V8*$W8) | Y8: =IF($A8="","",$U8+$X8) | Z8: =IF($A8="","",$D8-$U8) | AA8: =IF($A8="","",$D8-$Y8) | AB8: =IF(OR($A8="",$D8=0),"",$Z8/$D8) | AC8: =IF(OR($A8="",$D8=0),"",$AA8/$D8) | AD8: =IFERROR(IF($A8="","",$Z8/$V8),"")
B9: =IF($A9="","",IFERROR(INDEX('Fragrance Projects'!$C$5:$C$64,MATCH($A9,'Fragrance Projects'!$A$5:$A$64,0)),"")) | C9: =IF($A9="","",IFERROR(INDEX('Fragrance Projects'!$D$5:$D$64,MATCH($A9,'Fragrance Projects'!$A$5:$A$64,0)),"")) | E9: =IF($A9="","",IFERROR(INDEX(Payments!$G$5:$G$64,MATCH($A9,Payments!$B$5:$B$64,0)),0)+IFERROR(INDEX(Payments!$K$5:$K$64,MATCH($A9,Payments!$B$5:$B$64,0)),0)) | F9: =IF($A9="","",$D9-$E9) | G9: =IF($A9="","",SUMIFS('Expense Log'!$J$5:$J$154,'Expense Log'!$B$5:$B$154,$A9,'Expense Log'!$E$5:$E$154,"Raw Materials")) | H9: =IF($A9="","",SUMIFS('Expense Log'!$J$5:$J$154,'Expense Log'!$B$5:$B$154,$A9,'Expense Log'!$E$5:$E$154,"Alcohol/Carrier")) | I9: =IF($A9="","",SUMIFS('Expense Log'!$J$5:$J$154,'Expense Log'!$B$5:$B$154,$A9,'Expense Log'!$E$5:$E$154,"Bottles")+SUMIFS('Expense Log'!$J$5:$J$154,'Expense Log'!$B$5:$B$154,$A9,'Expense Log'!$E$5:$E$154,"Sample Vials")) | J9: =IF($A9="","",SUMIFS('Expense Log'!$J$5:$J$154,'Expense Log'!$B$5:$B$154,$A9,'Expense Log'!$E$5:$E$154,"Packaging")) | K9: =IF($A9="","",SUMIFS('Expense Log'!$J$5:$J$154,'Expense Log'!$B$5:$B$154,$A9,'Expense Log'!$E$5:$E$154,"Labels")) | L9: =IF($A9="","",SUMIFS('Expense Log'!$J$5:$J$154,'Expense Log'!$B$5:$B$154,$A9,'Expense Log'!$E$5:$E$154,"Shipping")) | M9: =IF($A9="","",SUMIFS('Expense Log'!$J$5:$J$154,'Expense Log'!$B$5:$B$154,$A9,'Expense Log'!$E$5:$E$154,"Documentation")) | N9: =IF($A9="","",SUMIFS('Expense Log'!$J$5:$J$154,'Expense Log'!$B$5:$B$154,$A9,'Expense Log'!$E$5:$E$154,"SDS")) | O9: =IF($A9="","",SUMIFS('Expense Log'!$J$5:$J$154,'Expense Log'!$B$5:$B$154,$A9,'Expense Log'!$E$5:$E$154,"IFRA/Allergen")) | P9: =IF($A9="","",SUMIFS('Expense Log'!$J$5:$J$154,'Expense Log'!$B$5:$B$154,$A9,'Expense Log'!$E$5:$E$154,"CPSR")) | Q9: =IF($A9="","",SUMIFS('Expense Log'!$J$5:$J$154,'Expense Log'!$B$5:$B$154,$A9,'Expense Log'!$E$5:$E$154,"Compounding")) | R9: =IF($A9="","",SUMIFS('Expense Log'!$J$5:$J$154,'Expense Log'!$B$5:$B$154,$A9,'Expense Log'!$E$5:$E$154,"External Perfumer")) | S9: =IF($A9="","",SUMIFS('Expense Log'!$J$5:$J$154,'Expense Log'!$B$5:$B$154,$A9,'Expense Log'!$E$5:$E$154,"Payment Fees")) | T9: =IF($A9="","",SUMIFS('Expense Log'!$J$5:$J$154,'Expense Log'!$B$5:$B$154,$A9,'Expense Log'!$E$5:$E$154,"Testing")+SUMIFS('Expense Log'!$J$5:$J$154,'Expense Log'!$B$5:$B$154,$A9,'Expense Log'!$E$5:$E$154,"Software")+SUMIFS('Expense Log'!$J$5:$J$154,'Expense Log'!$B$5:$B$154,$A9,'Expense Log'!$E$5:$E$154,"Other")) | U9: =IF($A9="","",SUM($G9:$T9)) | V9: =IF($A9="","",SUMIFS('Iteration Tracker'!$T$5:$T$124,'Iteration Tracker'!$A$5:$A$124,$A9)) | X9: =IF($A9="","",$V9*$W9) | Y9: =IF($A9="","",$U9+$X9) | Z9: =IF($A9="","",$D9-$U9) | AA9: =IF($A9="","",$D9-$Y9) | AB9: =IF(OR($A9="",$D9=0),"",$Z9/$D9) | AC9: =IF(OR($A9="",$D9=0),"",$AA9/$D9) | AD9: =IFERROR(IF($A9="","",$Z9/$V9),"")
B10: =IF($A10="","",IFERROR(INDEX('Fragrance Projects'!$C$5:$C$64,MATCH($A10,'Fragrance Projects'!$A$5:$A$64,0)),"")) | C10: =IF($A10="","",IFERROR(INDEX('Fragrance Projects'!$D$5:$D$64,MATCH($A10,'Fragrance Projects'!$A$5:$A$64,0)),"")) | E10: =IF($A10="","",IFERROR(INDEX(Payments!$G$5:$G$64,MATCH($A10,Payments!$B$5:$B$64,0)),0)+IFERROR(INDEX(Payments!$K$5:$K$64,MATCH($A10,Payments!$B$5:$B$64,0)),0)) | F10: =IF($A10="","",$D10-$E10) | G10: =IF($A10="","",SUMIFS('Expense Log'!$J$5:$J$154,'Expense Log'!$B$5:$B$154,$A10,'Expense Log'!$E$5:$E$154,"Raw Materials")) | H10: =IF($A10="","",SUMIFS('Expense Log'!$J$5:$J$154,'Expense Log'!$B$5:$B$154,$A10,'Expense Log'!$E$5:$E$154,"Alcohol/Carrier")) | I10: =IF($A10="","",SUMIFS('Expense Log'!$J$5:$J$154,'Expense Log'!$B$5:$B$154,$A10,'Expense Log'!$E$5:$E$154,"Bottles")+SUMIFS('Expense Log'!$J$5:$J$154,'Expense Log'!$B$5:$B$154,$A10,'Expense Log'!$E$5:$E$154,"Sample Vials")) | J10: =IF($A10="","",SUMIFS('Expense Log'!$J$5:$J$154,'Expense Log'!$B$5:$B$154,$A10,'Expense Log'!$E$5:$E$154,"Packaging")) | K10: =IF($A10="","",SUMIFS('Expense Log'!$J$5:$J$154,'Expense Log'!$B$5:$B$154,$A10,'Expense Log'!$E$5:$E$154,"Labels")) | L10: =IF($A10="","",SUMIFS('Expense Log'!$J$5:$J$154,'Expense Log'!$B$5:$B$154,$A10,'Expense Log'!$E$5:$E$154,"Shipping")) | M10: =IF($A10="","",SUMIFS('Expense Log'!$J$5:$J$154,'Expense Log'!$B$5:$B$154,$A10,'Expense Log'!$E$5:$E$154,"Documentation")) | N10: =IF($A10="","",SUMIFS('Expense Log'!$J$5:$J$154,'Expense Log'!$B$5:$B$154,$A10,'Expense Log'!$E$5:$E$154,"SDS")) | O10: =IF($A10="","",SUMIFS('Expense Log'!$J$5:$J$154,'Expense Log'!$B$5:$B$154,$A10,'Expense Log'!$E$5:$E$154,"IFRA/Allergen")) | P10: =IF($A10="","",SUMIFS('Expense Log'!$J$5:$J$154,'Expense Log'!$B$5:$B$154,$A10,'Expense Log'!$E$5:$E$154,"CPSR")) | Q10: =IF($A10="","",SUMIFS('Expense Log'!$J$5:$J$154,'Expense Log'!$B$5:$B$154,$A10,'Expense Log'!$E$5:$E$154,"Compounding")) | R10: =IF($A10="","",SUMIFS('Expense Log'!$J$5:$J$154,'Expense Log'!$B$5:$B$154,$A10,'Expense Log'!$E$5:$E$154,"External Perfumer")) | S10: =IF($A10="","",SUMIFS('Expense Log'!$J$5:$J$154,'Expense Log'!$B$5:$B$154,$A10,'Expense Log'!$E$5:$E$154,"Payment Fees")) | T10: =IF($A10="","",SUMIFS('Expense Log'!$J$5:$J$154,'Expense Log'!$B$5:$B$154,$A10,'Expense Log'!$E$5:$E$154,"Testing")+SUMIFS('Expense Log'!$J$5:$J$154,'Expense Log'!$B$5:$B$154,$A10,'Expense Log'!$E$5:$E$154,"Software")+SUMIFS('Expense Log'!$J$5:$J$154,'Expense Log'!$B$5:$B$154,$A10,'Expense Log'!$E$5:$E$154,"Other")) | U10: =IF($A10="","",SUM($G10:$T10)) | V10: =IF($A10="","",SUMIFS('Iteration Tracker'!$T$5:$T$124,'Iteration Tracker'!$A$5:$A$124,$A10)) | X10: =IF($A10="","",$V10*$W10) | Y10: =IF($A10="","",$U10+$X10) | Z10: =IF($A10="","",$D10-$U10) | AA10: =IF($A10="","",$D10-$Y10) | AB10: =IF(OR($A10="",$D10=0),"",$Z10/$D10) | AC10: =IF(OR($A10="",$D10=0),"",$AA10/$D10) | AD10: =IFERROR(IF($A10="","",$Z10/$V10),"")
B11: =IF($A11="","",IFERROR(INDEX('Fragrance Projects'!$C$5:$C$64,MATCH($A11,'Fragrance Projects'!$A$5:$A$64,0)),"")) | C11: =IF($A11="","",IFERROR(INDEX('Fragrance Projects'!$D$5:$D$64,MATCH($A11,'Fragrance Projects'!$A$5:$A$64,0)),"")) | E11: =IF($A11="","",IFERROR(INDEX(Payments!$G$5:$G$64,MATCH($A11,Payments!$B$5:$B$64,0)),0)+IFERROR(INDEX(Payments!$K$5:$K$64,MATCH($A11,Payments!$B$5:$B$64,0)),0)) | F11: =IF($A11="","",$D11-$E11) | G11: =IF($A11="","",SUMIFS('Expense Log'!$J$5:$J$154,'Expense Log'!$B$5:$B$154,$A11,'Expense Log'!$E$5:$E$154,"Raw Materials")) | H11: =IF($A11="","",SUMIFS('Expense Log'!$J$5:$J$154,'Expense Log'!$B$5:$B$154,$A11,'Expense Log'!$E$5:$E$154,"Alcohol/Carrier")) | I11: =IF($A11="","",SUMIFS('Expense Log'!$J$5:$J$154,'Expense Log'!$B$5:$B$154,$A11,'Expense Log'!$E$5:$E$154,"Bottles")+SUMIFS('Expense Log'!$J$5:$J$154,'Expense Log'!$B$5:$B$154,$A11,'Expense Log'!$E$5:$E$154,"Sample Vials")) | J11: =IF($A11="","",SUMIFS('Expense Log'!$J$5:$J$154,'Expense Log'!$B$5:$B$154,$A11,'Expense Log'!$E$5:$E$154,"Packaging")) | K11: =IF($A11="","",SUMIFS('Expense Log'!$J$5:$J$154,'Expense Log'!$B$5:$B$154,$A11,'Expense Log'!$E$5:$E$154,"Labels")) | L11: =IF($A11="","",SUMIFS('Expense Log'!$J$5:$J$154,'Expense Log'!$B$5:$B$154,$A11,'Expense Log'!$E$5:$E$154,"Shipping")) | M11: =IF($A11="","",SUMIFS('Expense Log'!$J$5:$J$154,'Expense Log'!$B$5:$B$154,$A11,'Expense Log'!$E$5:$E$154,"Documentation")) | N11: =IF($A11="","",SUMIFS('Expense Log'!$J$5:$J$154,'Expense Log'!$B$5:$B$154,$A11,'Expense Log'!$E$5:$E$154,"SDS")) | O11: =IF($A11="","",SUMIFS('Expense Log'!$J$5:$J$154,'Expense Log'!$B$5:$B$154,$A11,'Expense Log'!$E$5:$E$154,"IFRA/Allergen")) | P11: =IF($A11="","",SUMIFS('Expense Log'!$J$5:$J$154,'Expense Log'!$B$5:$B$154,$A11,'Expense Log'!$E$5:$E$154,"CPSR")) | Q11: =IF($A11="","",SUMIFS('Expense Log'!$J$5:$J$154,'Expense Log'!$B$5:$B$154,$A11,'Expense Log'!$E$5:$E$154,"Compounding")) | R11: =IF($A11="","",SUMIFS('Expense Log'!$J$5:$J$154,'Expense Log'!$B$5:$B$154,$A11,'Expense Log'!$E$5:$E$154,"External Perfumer")) | S11: =IF($A11="","",SUMIFS('Expense Log'!$J$5:$J$154,'Expense Log'!$B$5:$B$154,$A11,'Expense Log'!$E$5:$E$154,"Payment Fees")) | T11: =IF($A11="","",SUMIFS('Expense Log'!$J$5:$J$154,'Expense Log'!$B$5:$B$154,$A11,'Expense Log'!$E$5:$E$154,"Testing")+SUMIFS('Expense Log'!$J$5:$J$154,'Expense Log'!$B$5:$B$154,$A11,'Expense Log'!$E$5:$E$154,"Software")+SUMIFS('Expense Log'!$J$5:$J$154,'Expense Log'!$B$5:$B$154,$A11,'Expense Log'!$E$5:$E$154,"Other")) | U11: =IF($A11="","",SUM($G11:$T11)) | V11: =IF($A11="","",SUMIFS('Iteration Tracker'!$T$5:$T$124,'Iteration Tracker'!$A$5:$A$124,$A11)) | X11: =IF($A11="","",$V11*$W11) | Y11: =IF($A11="","",$U11+$X11) | Z11: =IF($A11="","",$D11-$U11) | AA11: =IF($A11="","",$D11-$Y11) | AB11: =IF(OR($A11="",$D11=0),"",$Z11/$D11) | AC11: =IF(OR($A11="",$D11=0),"",$AA11/$D11) | AD11: =IFERROR(IF($A11="","",$Z11/$V11),"")
B12: =IF($A12="","",IFERROR(INDEX('Fragrance Projects'!$C$5:$C$64,MATCH($A12,'Fragrance Projects'!$A$5:$A$64,0)),"")) | C12: =IF($A12="","",IFERROR(INDEX('Fragrance Projects'!$D$5:$D$64,MATCH($A12,'Fragrance Projects'!$A$5:$A$64,0)),"")) | E12: =IF($A12="","",IFERROR(INDEX(Payments!$G$5:$G$64,MATCH($A12,Payments!$B$5:$B$64,0)),0)+IFERROR(INDEX(Payments!$K$5:$K$64,MATCH($A12,Payments!$B$5:$B$64,0)),0)) | F12: =IF($A12="","",$D12-$E12) | G12: =IF($A12="","",SUMIFS('Expense Log'!$J$5:$J$154,'Expense Log'!$B$5:$B$154,$A12,'Expense Log'!$E$5:$E$154,"Raw Materials")) | H12: =IF($A12="","",SUMIFS('Expense Log'!$J$5:$J$154,'Expense Log'!$B$5:$B$154,$A12,'Expense Log'!$E$5:$E$154,"Alcohol/Carrier")) | I12: =IF($A12="","",SUMIFS('Expense Log'!$J$5:$J$154,'Expense Log'!$B$5:$B$154,$A12,'Expense Log'!$E$5:$E$154,"Bottles")+SUMIFS('Expense Log'!$J$5:$J$154,'Expense Log'!$B$5:$B$154,$A12,'Expense Log'!$E$5:$E$154,"Sample Vials")) | J12: =IF($A12="","",SUMIFS('Expense Log'!$J$5:$J$154,'Expense Log'!$B$5:$B$154,$A12,'Expense Log'!$E$5:$E$154,"Packaging")) | K12: =IF($A12="","",SUMIFS('Expense Log'!$J$5:$J$154,'Expense Log'!$B$5:$B$154,$A12,'Expense Log'!$E$5:$E$154,"Labels")) | L12: =IF($A12="","",SUMIFS('Expense Log'!$J$5:$J$154,'Expense Log'!$B$5:$B$154,$A12,'Expense Log'!$E$5:$E$154,"Shipping")) | M12: =IF($A12="","",SUMIFS('Expense Log'!$J$5:$J$154,'Expense Log'!$B$5:$B$154,$A12,'Expense Log'!$E$5:$E$154,"Documentation")) | N12: =IF($A12="","",SUMIFS('Expense Log'!$J$5:$J$154,'Expense Log'!$B$5:$B$154,$A12,'Expense Log'!$E$5:$E$154,"SDS")) | O12: =IF($A12="","",SUMIFS('Expense Log'!$J$5:$J$154,'Expense Log'!$B$5:$B$154,$A12,'Expense Log'!$E$5:$E$154,"IFRA/Allergen")) | P12: =IF($A12="","",SUMIFS('Expense Log'!$J$5:$J$154,'Expense Log'!$B$5:$B$154,$A12,'Expense Log'!$E$5:$E$154,"CPSR")) | Q12: =IF($A12="","",SUMIFS('Expense Log'!$J$5:$J$154,'Expense Log'!$B$5:$B$154,$A12,'Expense Log'!$E$5:$E$154,"Compounding")) | R12: =IF($A12="","",SUMIFS('Expense Log'!$J$5:$J$154,'Expense Log'!$B$5:$B$154,$A12,'Expense Log'!$E$5:$E$154,"External Perfumer")) | S12: =IF($A12="","",SUMIFS('Expense Log'!$J$5:$J$154,'Expense Log'!$B$5:$B$154,$A12,'Expense Log'!$E$5:$E$154,"Payment Fees")) | T12: =IF($A12="","",SUMIFS('Expense Log'!$J$5:$J$154,'Expense Log'!$B$5:$B$154,$A12,'Expense Log'!$E$5:$E$154,"Testing")+SUMIFS('Expense Log'!$J$5:$J$154,'Expense Log'!$B$5:$B$154,$A12,'Expense Log'!$E$5:$E$154,"Software")+SUMIFS('Expense Log'!$J$5:$J$154,'Expense Log'!$B$5:$B$154,$A12,'Expense Log'!$E$5:$E$154,"Other")) | U12: =IF($A12="","",SUM($G12:$T12)) | V12: =IF($A12="","",SUMIFS('Iteration Tracker'!$T$5:$T$124,'Iteration Tracker'!$A$5:$A$124,$A12)) | X12: =IF($A12="","",$V12*$W12) | Y12: =IF($A12="","",$U12+$X12) | Z12: =IF($A12="","",$D12-$U12) | AA12: =IF($A12="","",$D12-$Y12) | AB12: =IF(OR($A12="",$D12=0),"",$Z12/$D12) | AC12: =IF(OR($A12="",$D12=0),"",$AA12/$D12) | AD12: =IFERROR(IF($A12="","",$Z12/$V12),"")
B13: =IF($A13="","",IFERROR(INDEX('Fragrance Projects'!$C$5:$C$64,MATCH($A13,'Fragrance Projects'!$A$5:$A$64,0)),"")) | C13: =IF($A13="","",IFERROR(INDEX('Fragrance Projects'!$D$5:$D$64,MATCH($A13,'Fragrance Projects'!$A$5:$A$64,0)),"")) | E13: =IF($A13="","",IFERROR(INDEX(Payments!$G$5:$G$64,MATCH($A13,Payments!$B$5:$B$64,0)),0)+IFERROR(INDEX(Payments!$K$5:$K$64,MATCH($A13,Payments!$B$5:$B$64,0)),0)) | F13: =IF($A13="","",$D13-$E13) | G13: =IF($A13="","",SUMIFS('Expense Log'!$J$5:$J$154,'Expense Log'!$B$5:$B$154,$A13,'Expense Log'!$E$5:$E$154,"Raw Materials")) | H13: =IF($A13="","",SUMIFS('Expense Log'!$J$5:$J$154,'Expense Log'!$B$5:$B$154,$A13,'Expense Log'!$E$5:$E$154,"Alcohol/Carrier")) | I13: =IF($A13="","",SUMIFS('Expense Log'!$J$5:$J$154,'Expense Log'!$B$5:$B$154,$A13,'Expense Log'!$E$5:$E$154,"Bottles")+SUMIFS('Expense Log'!$J$5:$J$154,'Expense Log'!$B$5:$B$154,$A13,'Expense Log'!$E$5:$E$154,"Sample Vials")) | J13: =IF($A13="","",SUMIFS('Expense Log'!$J$5:$J$154,'Expense Log'!$B$5:$B$154,$A13,'Expense Log'!$E$5:$E$154,"Packaging")) | K13: =IF($A13="","",SUMIFS('Expense Log'!$J$5:$J$154,'Expense Log'!$B$5:$B$154,$A13,'Expense Log'!$E$5:$E$154,"Labels")) | L13: =IF($A13="","",SUMIFS('Expense Log'!$J$5:$J$154,'Expense Log'!$B$5:$B$154,$A13,'Expense Log'!$E$5:$E$154,"Shipping")) | M13: =IF($A13="","",SUMIFS('Expense Log'!$J$5:$J$154,'Expense Log'!$B$5:$B$154,$A13,'Expense Log'!$E$5:$E$154,"Documentation")) | N13: =IF($A13="","",SUMIFS('Expense Log'!$J$5:$J$154,'Expense Log'!$B$5:$B$154,$A13,'Expense Log'!$E$5:$E$154,"SDS")) | O13: =IF($A13="","",SUMIFS('Expense Log'!$J$5:$J$154,'Expense Log'!$B$5:$B$154,$A13,'Expense Log'!$E$5:$E$154,"IFRA/Allergen")) | P13: =IF($A13="","",SUMIFS('Expense Log'!$J$5:$J$154,'Expense Log'!$B$5:$B$154,$A13,'Expense Log'!$E$5:$E$154,"CPSR")) | Q13: =IF($A13="","",SUMIFS('Expense Log'!$J$5:$J$154,'Expense Log'!$B$5:$B$154,$A13,'Expense Log'!$E$5:$E$154,"Compounding")) | R13: =IF($A13="","",SUMIFS('Expense Log'!$J$5:$J$154,'Expense Log'!$B$5:$B$154,$A13,'Expense Log'!$E$5:$E$154,"External Perfumer")) | S13: =IF($A13="","",SUMIFS('Expense Log'!$J$5:$J$154,'Expense Log'!$B$5:$B$154,$A13,'Expense Log'!$E$5:$E$154,"Payment Fees")) | T13: =IF($A13="","",SUMIFS('Expense Log'!$J$5:$J$154,'Expense Log'!$B$5:$B$154,$A13,'Expense Log'!$E$5:$E$154,"Testing")+SUMIFS('Expense Log'!$J$5:$J$154,'Expense Log'!$B$5:$B$154,$A13,'Expense Log'!$E$5:$E$154,"Software")+SUMIFS('Expense Log'!$J$5:$J$154,'Expense Log'!$B$5:$B$154,$A13,'Expense Log'!$E$5:$E$154,"Other")) | U13: =IF($A13="","",SUM($G13:$T13)) | V13: =IF($A13="","",SUMIFS('Iteration Tracker'!$T$5:$T$124,'Iteration Tracker'!$A$5:$A$124,$A13)) | X13: =IF($A13="","",$V13*$W13) | Y13: =IF($A13="","",$U13+$X13) | Z13: =IF($A13="","",$D13-$U13) | AA13: =IF($A13="","",$D13-$Y13) | AB13: =IF(OR($A13="",$D13=0),"",$Z13/$D13) | AC13: =IF(OR($A13="",$D13=0),"",$AA13/$D13) | AD13: =IFERROR(IF($A13="","",$Z13/$V13),"")
B14: =IF($A14="","",IFERROR(INDEX('Fragrance Projects'!$C$5:$C$64,MATCH($A14,'Fragrance Projects'!$A$5:$A$64,0)),"")) | C14: =IF($A14="","",IFERROR(INDEX('Fragrance Projects'!$D$5:$D$64,MATCH($A14,'Fragrance Projects'!$A$5:$A$64,0)),"")) | E14: =IF($A14="","",IFERROR(INDEX(Payments!$G$5:$G$64,MATCH($A14,Payments!$B$5:$B$64,0)),0)+IFERROR(INDEX(Payments!$K$5:$K$64,MATCH($A14,Payments!$B$5:$B$64,0)),0)) | F14: =IF($A14="","",$D14-$E14) | G14: =IF($A14="","",SUMIFS('Expense Log'!$J$5:$J$154,'Expense Log'!$B$5:$B$154,$A14,'Expense Log'!$E$5:$E$154,"Raw Materials")) | H14: =IF($A14="","",SUMIFS('Expense Log'!$J$5:$J$154,'Expense Log'!$B$5:$B$154,$A14,'Expense Log'!$E$5:$E$154,"Alcohol/Carrier")) | I14: =IF($A14="","",SUMIFS('Expense Log'!$J$5:$J$154,'Expense Log'!$B$5:$B$154,$A14,'Expense Log'!$E$5:$E$154,"Bottles")+SUMIFS('Expense Log'!$J$5:$J$154,'Expense Log'!$B$5:$B$154,$A14,'Expense Log'!$E$5:$E$154,"Sample Vials")) | J14: =IF($A14="","",SUMIFS('Expense Log'!$J$5:$J$154,'Expense Log'!$B$5:$B$154,$A14,'Expense Log'!$E$5:$E$154,"Packaging")) | K14: =IF($A14="","",SUMIFS('Expense Log'!$J$5:$J$154,'Expense Log'!$B$5:$B$154,$A14,'Expense Log'!$E$5:$E$154,"Labels")) | L14: =IF($A14="","",SUMIFS('Expense Log'!$J$5:$J$154,'Expense Log'!$B$5:$B$154,$A14,'Expense Log'!$E$5:$E$154,"Shipping")) | M14: =IF($A14="","",SUMIFS('Expense Log'!$J$5:$J$154,'Expense Log'!$B$5:$B$154,$A14,'Expense Log'!$E$5:$E$154,"Documentation")) | N14: =IF($A14="","",SUMIFS('Expense Log'!$J$5:$J$154,'Expense Log'!$B$5:$B$154,$A14,'Expense Log'!$E$5:$E$154,"SDS")) | O14: =IF($A14="","",SUMIFS('Expense Log'!$J$5:$J$154,'Expense Log'!$B$5:$B$154,$A14,'Expense Log'!$E$5:$E$154,"IFRA/Allergen")) | P14: =IF($A14="","",SUMIFS('Expense Log'!$J$5:$J$154,'Expense Log'!$B$5:$B$154,$A14,'Expense Log'!$E$5:$E$154,"CPSR")) | Q14: =IF($A14="","",SUMIFS('Expense Log'!$J$5:$J$154,'Expense Log'!$B$5:$B$154,$A14,'Expense Log'!$E$5:$E$154,"Compounding")) | R14: =IF($A14="","",SUMIFS('Expense Log'!$J$5:$J$154,'Expense Log'!$B$5:$B$154,$A14,'Expense Log'!$E$5:$E$154,"External Perfumer")) | S14: =IF($A14="","",SUMIFS('Expense Log'!$J$5:$J$154,'Expense Log'!$B$5:$B$154,$A14,'Expense Log'!$E$5:$E$154,"Payment Fees")) | T14: =IF($A14="","",SUMIFS('Expense Log'!$J$5:$J$154,'Expense Log'!$B$5:$B$154,$A14,'Expense Log'!$E$5:$E$154,"Testing")+SUMIFS('Expense Log'!$J$5:$J$154,'Expense Log'!$B$5:$B$154,$A14,'Expense Log'!$E$5:$E$154,"Software")+SUMIFS('Expense Log'!$J$5:$J$154,'Expense Log'!$B$5:$B$154,$A14,'Expense Log'!$E$5:$E$154,"Other")) | U14: =IF($A14="","",SUM($G14:$T14)) | V14: =IF($A14="","",SUMIFS('Iteration Tracker'!$T$5:$T$124,'Iteration Tracker'!$A$5:$A$124,$A14)) | X14: =IF($A14="","",$V14*$W14) | Y14: =IF($A14="","",$U14+$X14) | Z14: =IF($A14="","",$D14-$U14) | AA14: =IF($A14="","",$D14-$Y14) | AB14: =IF(OR($A14="",$D14=0),"",$Z14/$D14) | AC14: =IF(OR($A14="",$D14=0),"",$AA14/$D14) | AD14: =IFERROR(IF($A14="","",$Z14/$V14),"")
B15: =IF($A15="","",IFERROR(INDEX('Fragrance Projects'!$C$5:$C$64,MATCH($A15,'Fragrance Projects'!$A$5:$A$64,0)),"")) | C15: =IF($A15="","",IFERROR(INDEX('Fragrance Projects'!$D$5:$D$64,MATCH($A15,'Fragrance Projects'!$A$5:$A$64,0)),"")) | E15: =IF($A15="","",IFERROR(INDEX(Payments!$G$5:$G$64,MATCH($A15,Payments!$B$5:$B$64,0)),0)+IFERROR(INDEX(Payments!$K$5:$K$64,MATCH($A15,Payments!$B$5:$B$64,0)),0)) | F15: =IF($A15="","",$D15-$E15) | G15: =IF($A15="","",SUMIFS('Expense Log'!$J$5:$J$154,'Expense Log'!$B$5:$B$154,$A15,'Expense Log'!$E$5:$E$154,"Raw Materials")) | H15: =IF($A15="","",SUMIFS('Expense Log'!$J$5:$J$154,'Expense Log'!$B$5:$B$154,$A15,'Expense Log'!$E$5:$E$154,"Alcohol/Carrier")) | I15: =IF($A15="","",SUMIFS('Expense Log'!$J$5:$J$154,'Expense Log'!$B$5:$B$154,$A15,'Expense Log'!$E$5:$E$154,"Bottles")+SUMIFS('Expense Log'!$J$5:$J$154,'Expense Log'!$B$5:$B$154,$A15,'Expense Log'!$E$5:$E$154,"Sample Vials")) | J15: =IF($A15="","",SUMIFS('Expense Log'!$J$5:$J$154,'Expense Log'!$B$5:$B$154,$A15,'Expense Log'!$E$5:$E$154,"Packaging")) | K15: =IF($A15="","",SUMIFS('Expense Log'!$J$5:$J$154,'Expense Log'!$B$5:$B$154,$A15,'Expense Log'!$E$5:$E$154,"Labels")) | L15: =IF($A15="","",SUMIFS('Expense Log'!$J$5:$J$154,'Expense Log'!$B$5:$B$154,$A15,'Expense Log'!$E$5:$E$154,"Shipping")) | M15: =IF($A15="","",SUMIFS('Expense Log'!$J$5:$J$154,'Expense Log'!$B$5:$B$154,$A15,'Expense Log'!$E$5:$E$154,"Documentation")) | N15: =IF($A15="","",SUMIFS('Expense Log'!$J$5:$J$154,'Expense Log'!$B$5:$B$154,$A15,'Expense Log'!$E$5:$E$154,"SDS")) | O15: =IF($A15="","",SUMIFS('Expense Log'!$J$5:$J$154,'Expense Log'!$B$5:$B$154,$A15,'Expense Log'!$E$5:$E$154,"IFRA/Allergen")) | P15: =IF($A15="","",SUMIFS('Expense Log'!$J$5:$J$154,'Expense Log'!$B$5:$B$154,$A15,'Expense Log'!$E$5:$E$154,"CPSR")) | Q15: =IF($A15="","",SUMIFS('Expense Log'!$J$5:$J$154,'Expense Log'!$B$5:$B$154,$A15,'Expense Log'!$E$5:$E$154,"Compounding")) | R15: =IF($A15="","",SUMIFS('Expense Log'!$J$5:$J$154,'Expense Log'!$B$5:$B$154,$A15,'Expense Log'!$E$5:$E$154,"External Perfumer")) | S15: =IF($A15="","",SUMIFS('Expense Log'!$J$5:$J$154,'Expense Log'!$B$5:$B$154,$A15,'Expense Log'!$E$5:$E$154,"Payment Fees")) | T15: =IF($A15="","",SUMIFS('Expense Log'!$J$5:$J$154,'Expense Log'!$B$5:$B$154,$A15,'Expense Log'!$E$5:$E$154,"Testing")+SUMIFS('Expense Log'!$J$5:$J$154,'Expense Log'!$B$5:$B$154,$A15,'Expense Log'!$E$5:$E$154,"Software")+SUMIFS('Expense Log'!$J$5:$J$154,'Expense Log'!$B$5:$B$154,$A15,'Expense Log'!$E$5:$E$154,"Other")) | U15: =IF($A15="","",SUM($G15:$T15)) | V15: =IF($A15="","",SUMIFS('Iteration Tracker'!$T$5:$T$124,'Iteration Tracker'!$A$5:$A$124,$A15)) | X15: =IF($A15="","",$V15*$W15) | Y15: =IF($A15="","",$U15+$X15) | Z15: =IF($A15="","",$D15-$U15) | AA15: =IF($A15="","",$D15-$Y15) | AB15: =IF(OR($A15="",$D15=0),"",$Z15/$D15) | AC15: =IF(OR($A15="",$D15=0),"",$AA15/$D15) | AD15: =IFERROR(IF($A15="","",$Z15/$V15),"")
B16: =IF($A16="","",IFERROR(INDEX('Fragrance Projects'!$C$5:$C$64,MATCH($A16,'Fragrance Projects'!$A$5:$A$64,0)),"")) | C16: =IF($A16="","",IFERROR(INDEX('Fragrance Projects'!$D$5:$D$64,MATCH($A16,'Fragrance Projects'!$A$5:$A$64,0)),"")) | E16: =IF($A16="","",IFERROR(INDEX(Payments!$G$5:$G$64,MATCH($A16,Payments!$B$5:$B$64,0)),0)+IFERROR(INDEX(Payments!$K$5:$K$64,MATCH($A16,Payments!$B$5:$B$64,0)),0)) | F16: =IF($A16="","",$D16-$E16) | G16: =IF($A16="","",SUMIFS('Expense Log'!$J$5:$J$154,'Expense Log'!$B$5:$B$154,$A16,'Expense Log'!$E$5:$E$154,"Raw Materials")) | H16: =IF($A16="","",SUMIFS('Expense Log'!$J$5:$J$154,'Expense Log'!$B$5:$B$154,$A16,'Expense Log'!$E$5:$E$154,"Alcohol/Carrier")) | I16: =IF($A16="","",SUMIFS('Expense Log'!$J$5:$J$154,'Expense Log'!$B$5:$B$154,$A16,'Expense Log'!$E$5:$E$154,"Bottles")+SUMIFS('Expense Log'!$J$5:$J$154,'Expense Log'!$B$5:$B$154,$A16,'Expense Log'!$E$5:$E$154,"Sample Vials")) | J16: =IF($A16="","",SUMIFS('Expense Log'!$J$5:$J$154,'Expense Log'!$B$5:$B$154,$A16,'Expense Log'!$E$5:$E$154,"Packaging")) | K16: =IF($A16="","",SUMIFS('Expense Log'!$J$5:$J$154,'Expense Log'!$B$5:$B$154,$A16,'Expense Log'!$E$5:$E$154,"Labels")) | L16: =IF($A16="","",SUMIFS('Expense Log'!$J$5:$J$154,'Expense Log'!$B$5:$B$154,$A16,'Expense Log'!$E$5:$E$154,"Shipping")) | M16: =IF($A16="","",SUMIFS('Expense Log'!$J$5:$J$154,'Expense Log'!$B$5:$B$154,$A16,'Expense Log'!$E$5:$E$154,"Documentation")) | N16: =IF($A16="","",SUMIFS('Expense Log'!$J$5:$J$154,'Expense Log'!$B$5:$B$154,$A16,'Expense Log'!$E$5:$E$154,"SDS")) | O16: =IF($A16="","",SUMIFS('Expense Log'!$J$5:$J$154,'Expense Log'!$B$5:$B$154,$A16,'Expense Log'!$E$5:$E$154,"IFRA/Allergen")) | P16: =IF($A16="","",SUMIFS('Expense Log'!$J$5:$J$154,'Expense Log'!$B$5:$B$154,$A16,'Expense Log'!$E$5:$E$154,"CPSR")) | Q16: =IF($A16="","",SUMIFS('Expense Log'!$J$5:$J$154,'Expense Log'!$B$5:$B$154,$A16,'Expense Log'!$E$5:$E$154,"Compounding")) | R16: =IF($A16="","",SUMIFS('Expense Log'!$J$5:$J$154,'Expense Log'!$B$5:$B$154,$A16,'Expense Log'!$E$5:$E$154,"External Perfumer")) | S16: =IF($A16="","",SUMIFS('Expense Log'!$J$5:$J$154,'Expense Log'!$B$5:$B$154,$A16,'Expense Log'!$E$5:$E$154,"Payment Fees")) | T16: =IF($A16="","",SUMIFS('Expense Log'!$J$5:$J$154,'Expense Log'!$B$5:$B$154,$A16,'Expense Log'!$E$5:$E$154,"Testing")+SUMIFS('Expense Log'!$J$5:$J$154,'Expense Log'!$B$5:$B$154,$A16,'Expense Log'!$E$5:$E$154,"Software")+SUMIFS('Expense Log'!$J$5:$J$154,'Expense Log'!$B$5:$B$154,$A16,'Expense Log'!$E$5:$E$154,"Other")) | U16: =IF($A16="","",SUM($G16:$T16)) | V16: =IF($A16="","",SUMIFS('Iteration Tracker'!$T$5:$T$124,'Iteration Tracker'!$A$5:$A$124,$A16)) | X16: =IF($A16="","",$V16*$W16) | Y16: =IF($A16="","",$U16+$X16) | Z16: =IF($A16="","",$D16-$U16) | AA16: =IF($A16="","",$D16-$Y16) | AB16: =IF(OR($A16="",$D16=0),"",$Z16/$D16) | AC16: =IF(OR($A16="",$D16=0),"",$AA16/$D16) | AD16: =IFERROR(IF($A16="","",$Z16/$V16),"")
... B64: =IF($A64="","",IFERROR(INDEX('Fragrance Projects'!$C$5:$C$64,MATCH($A64,'Fragrance Projects'!$A$5:$A$64,0)),"")) | C64: =IF($A64="","",IFERROR(INDEX('Fragrance Projects'!$D$5:$D$64,MATCH($A64,'Fragrance Projects'!$A$5:$A$64,0)),"")) | E64: =IF($A64="","",IFERROR(INDEX(Payments!$G$5:$G$64,MATCH($A64,Payments!$B$5:$B$64,0)),0)+IFERROR(INDEX(Payments!$K$5:$K$64,MATCH($A64,Payments!$B$5:$B$64,0)),0)) | F64: =IF($A64="","",$D64-$E64) | G64: =IF($A64="","",SUMIFS('Expense Log'!$J$5:$J$154,'Expense Log'!$B$5:$B$154,$A64,'Expense Log'!$E$5:$E$154,"Raw Materials")) | H64: =IF($A64="","",SUMIFS('Expense Log'!$J$5:$J$154,'Expense Log'!$B$5:$B$154,$A64,'Expense Log'!$E$5:$E$154,"Alcohol/Carrier")) | I64: =IF($A64="","",SUMIFS('Expense Log'!$J$5:$J$154,'Expense Log'!$B$5:$B$154,$A64,'Expense Log'!$E$5:$E$154,"Bottles")+SUMIFS('Expense Log'!$J$5:$J$154,'Expense Log'!$B$5:$B$154,$A64,'Expense Log'!$E$5:$E$154,"Sample Vials")) | J64: =IF($A64="","",SUMIFS('Expense Log'!$J$5:$J$154,'Expense Log'!$B$5:$B$154,$A64,'Expense Log'!$E$5:$E$154,"Packaging")) | K64: =IF($A64="","",SUMIFS('Expense Log'!$J$5:$J$154,'Expense Log'!$B$5:$B$154,$A64,'Expense Log'!$E$5:$E$154,"Labels")) | L64: =IF($A64="","",SUMIFS('Expense Log'!$J$5:$J$154,'Expense Log'!$B$5:$B$154,$A64,'Expense Log'!$E$5:$E$154,"Shipping")) | M64: =IF($A64="","",SUMIFS('Expense Log'!$J$5:$J$154,'Expense Log'!$B$5:$B$154,$A64,'Expense Log'!$E$5:$E$154,"Documentation")) | N64: =IF($A64="","",SUMIFS('Expense Log'!$J$5:$J$154,'Expense Log'!$B$5:$B$154,$A64,'Expense Log'!$E$5:$E$154,"SDS")) | O64: =IF($A64="","",SUMIFS('Expense Log'!$J$5:$J$154,'Expense Log'!$B$5:$B$154,$A64,'Expense Log'!$E$5:$E$154,"IFRA/Allergen")) | P64: =IF($A64="","",SUMIFS('Expense Log'!$J$5:$J$154,'Expense Log'!$B$5:$B$154,$A64,'Expense Log'!$E$5:$E$154,"CPSR")) | Q64: =IF($A64="","",SUMIFS('Expense Log'!$J$5:$J$154,'Expense Log'!$B$5:$B$154,$A64,'Expense Log'!$E$5:$E$154,"Compounding")) | R64: =IF($A64="","",SUMIFS('Expense Log'!$J$5:$J$154,'Expense Log'!$B$5:$B$154,$A64,'Expense Log'!$E$5:$E$154,"External Perfumer")) | S64: =IF($A64="","",SUMIFS('Expense Log'!$J$5:$J$154,'Expense Log'!$B$5:$B$154,$A64,'Expense Log'!$E$5:$E$154,"Payment Fees")) | T64: =IF($A64="","",SUMIFS('Expense Log'!$J$5:$J$154,'Expense Log'!$B$5:$B$154,$A64,'Expense Log'!$E$5:$E$154,"Testing")+SUMIFS('Expense Log'!$J$5:$J$154,'Expense Log'!$B$5:$B$154,$A64,'Expense Log'!$E$5:$E$154,"Software")+SUMIFS('Expense Log'!$J$5:$J$154,'Expense Log'!$B$5:$B$154,$A64,'Expense Log'!$E$5:$E$154,"Other")) | U64: =IF($A64="","",SUM($G64:$T64)) | V64: =IF($A64="","",SUMIFS('Iteration Tracker'!$T$5:$T$124,'Iteration Tracker'!$A$5:$A$124,$A64)) | X64: =IF($A64="","",$V64*$W64) | Y64: =IF($A64="","",$U64+$X64) | Z64: =IF($A64="","",$D64-$U64) | AA64: =IF($A64="","",$D64-$Y64) | AB64: =IF(OR($A64="",$D64=0),"",$Z64/$D64) | AC64: =IF(OR($A64="",$D64=0),"",$AA64/$D64) | AD64: =IFERROR(IF($A64="","",$Z64/$V64),"")

Sheet Expense Log
A1: EXPENSE LOG — Detailed Expense Database
A2: Every cost, tagged by Project ID and category. Project Financials pulls these totals automatically.
B3: INPUT — type or choose here | F3: CALCULATED — formula, do not edit | J3: AUTO-LOOKUP — pulled from another sheet
A4: Date | B4: Project ID | C4: Client | D4: Fragrance | E4: Expense Category | F4: Supplier | G4: Description | H4: Quantity | I4: Unit Cost | J4: Total Cost | K4: Paid? | L4: Receipt/Invoice Available? | M4: Business Expense Type | N4: Notes
C5: =IF($B5="","",IFERROR(INDEX('Fragrance Projects'!$C$5:$C$64,MATCH($B5,'Fragrance Projects'!$A$5:$A$64,0)),"")) | D5: =IF($B5="","",IFERROR(INDEX('Fragrance Projects'!$D$5:$D$64,MATCH($B5,'Fragrance Projects'!$A$5:$A$64,0)),"")) | J5: =IF($H5="","",$H5*$I5)
C6: =IF($B6="","",IFERROR(INDEX('Fragrance Projects'!$C$5:$C$64,MATCH($B6,'Fragrance Projects'!$A$5:$A$64,0)),"")) | D6: =IF($B6="","",IFERROR(INDEX('Fragrance Projects'!$D$5:$D$64,MATCH($B6,'Fragrance Projects'!$A$5:$A$64,0)),"")) | J6: =IF($H6="","",$H6*$I6)
C7: =IF($B7="","",IFERROR(INDEX('Fragrance Projects'!$C$5:$C$64,MATCH($B7,'Fragrance Projects'!$A$5:$A$64,0)),"")) | D7: =IF($B7="","",IFERROR(INDEX('Fragrance Projects'!$D$5:$D$64,MATCH($B7,'Fragrance Projects'!$A$5:$A$64,0)),"")) | J7: =IF($H7="","",$H7*$I7)
C8: =IF($B8="","",IFERROR(INDEX('Fragrance Projects'!$C$5:$C$64,MATCH($B8,'Fragrance Projects'!$A$5:$A$64,0)),"")) | D8: =IF($B8="","",IFERROR(INDEX('Fragrance Projects'!$D$5:$D$64,MATCH($B8,'Fragrance Projects'!$A$5:$A$64,0)),"")) | J8: =IF($H8="","",$H8*$I8)
C9: =IF($B9="","",IFERROR(INDEX('Fragrance Projects'!$C$5:$C$64,MATCH($B9,'Fragrance Projects'!$A$5:$A$64,0)),"")) | D9: =IF($B9="","",IFERROR(INDEX('Fragrance Projects'!$D$5:$D$64,MATCH($B9,'Fragrance Projects'!$A$5:$A$64,0)),"")) | J9: =IF($H9="","",$H9*$I9)
C10: =IF($B10="","",IFERROR(INDEX('Fragrance Projects'!$C$5:$C$64,MATCH($B10,'Fragrance Projects'!$A$5:$A$64,0)),"")) | D10: =IF($B10="","",IFERROR(INDEX('Fragrance Projects'!$D$5:$D$64,MATCH($B10,'Fragrance Projects'!$A$5:$A$64,0)),"")) | J10: =IF($H10="","",$H10*$I10)
C11: =IF($B11="","",IFERROR(INDEX('Fragrance Projects'!$C$5:$C$64,MATCH($B11,'Fragrance Projects'!$A$5:$A$64,0)),"")) | D11: =IF($B11="","",IFERROR(INDEX('Fragrance Projects'!$D$5:$D$64,MATCH($B11,'Fragrance Projects'!$A$5:$A$64,0)),"")) | J11: =IF($H11="","",$H11*$I11)
C12: =IF($B12="","",IFERROR(INDEX('Fragrance Projects'!$C$5:$C$64,MATCH($B12,'Fragrance Projects'!$A$5:$A$64,0)),"")) | D12: =IF($B12="","",IFERROR(INDEX('Fragrance Projects'!$D$5:$D$64,MATCH($B12,'Fragrance Projects'!$A$5:$A$64,0)),"")) | J12: =IF($H12="","",$H12*$I12)
C13: =IF($B13="","",IFERROR(INDEX('Fragrance Projects'!$C$5:$C$64,MATCH($B13,'Fragrance Projects'!$A$5:$A$64,0)),"")) | D13: =IF($B13="","",IFERROR(INDEX('Fragrance Projects'!$D$5:$D$64,MATCH($B13,'Fragrance Projects'!$A$5:$A$64,0)),"")) | J13: =IF($H13="","",$H13*$I13)
C14: =IF($B14="","",IFERROR(INDEX('Fragrance Projects'!$C$5:$C$64,MATCH($B14,'Fragrance Projects'!$A$5:$A$64,0)),"")) | D14: =IF($B14="","",IFERROR(INDEX('Fragrance Projects'!$D$5:$D$64,MATCH($B14,'Fragrance Projects'!$A$5:$A$64,0)),"")) | J14: =IF($H14="","",$H14*$I14)
C15: =IF($B15="","",IFERROR(INDEX('Fragrance Projects'!$C$5:$C$64,MATCH($B15,'Fragrance Projects'!$A$5:$A$64,0)),"")) | D15: =IF($B15="","",IFERROR(INDEX('Fragrance Projects'!$D$5:$D$64,MATCH($B15,'Fragrance Projects'!$A$5:$A$64,0)),"")) | J15: =IF($H15="","",$H15*$I15)
C16: =IF($B16="","",IFERROR(INDEX('Fragrance Projects'!$C$5:$C$64,MATCH($B16,'Fragrance Projects'!$A$5:$A$64,0)),"")) | D16: =IF($B16="","",IFERROR(INDEX('Fragrance Projects'!$D$5:$D$64,MATCH($B16,'Fragrance Projects'!$A$5:$A$64,0)),"")) | J16: =IF($H16="","",$H16*$I16)
... C154: =IF($B154="","",IFERROR(INDEX('Fragrance Projects'!$C$5:$C$64,MATCH($B154,'Fragrance Projects'!$A$5:$A$64,0)),"")) | D154: =IF($B154="","",IFERROR(INDEX('Fragrance Projects'!$D$5:$D$64,MATCH($B154,'Fragrance Projects'!$A$5:$A$64,0)),"")) | J154: =IF($H154="","",$H154*$I154)

Sheet Payments
A1: PAYMENTS — Invoices & Client Payments
A2: Total Amount is pulled from Project Financials. Payment Status and Days Overdue are calculated automatically.
B3: INPUT — type or choose here | F3: CALCULATED — formula, do not edit | J3: AUTO-LOOKUP — pulled from another sheet
A4: Client | B4: Project ID | C4: Invoice Number | D4: Invoice Date | E4: Total Amount | F4: Deposit Required | G4: Deposit Received | H4: Deposit Date | I4: Remaining Balance | J4: Balance Due Date | K4: Balance Received | L4: Payment Method | M4: Payment Fees | N4: Payment Status | O4: Days Overdue | P4: Notes
A5: =IF($B5="","",IFERROR(INDEX('Fragrance Projects'!$C$5:$C$64,MATCH($B5,'Fragrance Projects'!$A$5:$A$64,0)),"")) | E5: =IF($B5="","",IFERROR(INDEX('Project Financials'!$D$5:$D$64,MATCH($B5,'Project Financials'!$A$5:$A$64,0)),"")) | I5: =IF($E5="","",$E5-$G5) | N5: =IF($B5="","",_xlfn.IFS(OR($E5="",$E5=0),"Not Invoiced",($G5+$K5)>=$E5,"Paid",AND($J5<>"",TODAY()>$J5,($G5+$K5)<$E5),"Overdue",$G5=0,"Awaiting Deposit",TRUE(),"Part Paid")) | O5: =IF($B5="","",IF($N5="Overdue",TODAY()-$J5,0))
A6: =IF($B6="","",IFERROR(INDEX('Fragrance Projects'!$C$5:$C$64,MATCH($B6,'Fragrance Projects'!$A$5:$A$64,0)),"")) | E6: =IF($B6="","",IFERROR(INDEX('Project Financials'!$D$5:$D$64,MATCH($B6,'Project Financials'!$A$5:$A$64,0)),"")) | I6: =IF($E6="","",$E6-$G6) | N6: =IF($B6="","",_xlfn.IFS(OR($E6="",$E6=0),"Not Invoiced",($G6+$K6)>=$E6,"Paid",AND($J6<>"",TODAY()>$J6,($G6+$K6)<$E6),"Overdue",$G6=0,"Awaiting Deposit",TRUE(),"Part Paid")) | O6: =IF($B6="","",IF($N6="Overdue",TODAY()-$J6,0))
A7: =IF($B7="","",IFERROR(INDEX('Fragrance Projects'!$C$5:$C$64,MATCH($B7,'Fragrance Projects'!$A$5:$A$64,0)),"")) | E7: =IF($B7="","",IFERROR(INDEX('Project Financials'!$D$5:$D$64,MATCH($B7,'Project Financials'!$A$5:$A$64,0)),"")) | I7: =IF($E7="","",$E7-$G7) | N7: =IF($B7="","",_xlfn.IFS(OR($E7="",$E7=0),"Not Invoiced",($G7+$K7)>=$E7,"Paid",AND($J7<>"",TODAY()>$J7,($G7+$K7)<$E7),"Overdue",$G7=0,"Awaiting Deposit",TRUE(),"Part Paid")) | O7: =IF($B7="","",IF($N7="Overdue",TODAY()-$J7,0))
A8: =IF($B8="","",IFERROR(INDEX('Fragrance Projects'!$C$5:$C$64,MATCH($B8,'Fragrance Projects'!$A$5:$A$64,0)),"")) | E8: =IF($B8="","",IFERROR(INDEX('Project Financials'!$D$5:$D$64,MATCH($B8,'Project Financials'!$A$5:$A$64,0)),"")) | I8: =IF($E8="","",$E8-$G8) | N8: =IF($B8="","",_xlfn.IFS(OR($E8="",$E8=0),"Not Invoiced",($G8+$K8)>=$E8,"Paid",AND($J8<>"",TODAY()>$J8,($G8+$K8)<$E8),"Overdue",$G8=0,"Awaiting Deposit",TRUE(),"Part Paid")) | O8: =IF($B8="","",IF($N8="Overdue",TODAY()-$J8,0))
A9: =IF($B9="","",IFERROR(INDEX('Fragrance Projects'!$C$5:$C$64,MATCH($B9,'Fragrance Projects'!$A$5:$A$64,0)),"")) | E9: =IF($B9="","",IFERROR(INDEX('Project Financials'!$D$5:$D$64,MATCH($B9,'Project Financials'!$A$5:$A$64,0)),"")) | I9: =IF($E9="","",$E9-$G9) | N9: =IF($B9="","",_xlfn.IFS(OR($E9="",$E9=0),"Not Invoiced",($G9+$K9)>=$E9,"Paid",AND($J9<>"",TODAY()>$J9,($G9+$K9)<$E9),"Overdue",$G9=0,"Awaiting Deposit",TRUE(),"Part Paid")) | O9: =IF($B9="","",IF($N9="Overdue",TODAY()-$J9,0))
A10: =IF($B10="","",IFERROR(INDEX('Fragrance Projects'!$C$5:$C$64,MATCH($B10,'Fragrance Projects'!$A$5:$A$64,0)),"")) | E10: =IF($B10="","",IFERROR(INDEX('Project Financials'!$D$5:$D$64,MATCH($B10,'Project Financials'!$A$5:$A$64,0)),"")) | I10: =IF($E10="","",$E10-$G10) | N10: =IF($B10="","",_xlfn.IFS(OR($E10="",$E10=0),"Not Invoiced",($G10+$K10)>=$E10,"Paid",AND($J10<>"",TODAY()>$J10,($G10+$K10)<$E10),"Overdue",$G10=0,"Awaiting Deposit",TRUE(),"Part Paid")) | O10: =IF($B10="","",IF($N10="Overdue",TODAY()-$J10,0))
A11: =IF($B11="","",IFERROR(INDEX('Fragrance Projects'!$C$5:$C$64,MATCH($B11,'Fragrance Projects'!$A$5:$A$64,0)),"")) | E11: =IF($B11="","",IFERROR(INDEX('Project Financials'!$D$5:$D$64,MATCH($B11,'Project Financials'!$A$5:$A$64,0)),"")) | I11: =IF($E11="","",$E11-$G11) | N11: =IF($B11="","",_xlfn.IFS(OR($E11="",$E11=0),"Not Invoiced",($G11+$K11)>=$E11,"Paid",AND($J11<>"",TODAY()>$J11,($G11+$K11)<$E11),"Overdue",$G11=0,"Awaiting Deposit",TRUE(),"Part Paid")) | O11: =IF($B11="","",IF($N11="Overdue",TODAY()-$J11,0))
A12: =IF($B12="","",IFERROR(INDEX('Fragrance Projects'!$C$5:$C$64,MATCH($B12,'Fragrance Projects'!$A$5:$A$64,0)),"")) | E12: =IF($B12="","",IFERROR(INDEX('Project Financials'!$D$5:$D$64,MATCH($B12,'Project Financials'!$A$5:$A$64,0)),"")) | I12: =IF($E12="","",$E12-$G12) | N12: =IF($B12="","",_xlfn.IFS(OR($E12="",$E12=0),"Not Invoiced",($G12+$K12)>=$E12,"Paid",AND($J12<>"",TODAY()>$J12,($G12+$K12)<$E12),"Overdue",$G12=0,"Awaiting Deposit",TRUE(),"Part Paid")) | O12: =IF($B12="","",IF($N12="Overdue",TODAY()-$J12,0))
A13: =IF($B13="","",IFERROR(INDEX('Fragrance Projects'!$C$5:$C$64,MATCH($B13,'Fragrance Projects'!$A$5:$A$64,0)),"")) | E13: =IF($B13="","",IFERROR(INDEX('Project Financials'!$D$5:$D$64,MATCH($B13,'Project Financials'!$A$5:$A$64,0)),"")) | I13: =IF($E13="","",$E13-$G13) | N13: =IF($B13="","",_xlfn.IFS(OR($E13="",$E13=0),"Not Invoiced",($G13+$K13)>=$E13,"Paid",AND($J13<>"",TODAY()>$J13,($G13+$K13)<$E13),"Overdue",$G13=0,"Awaiting Deposit",TRUE(),"Part Paid")) | O13: =IF($B13="","",IF($N13="Overdue",TODAY()-$J13,0))
A14: =IF($B14="","",IFERROR(INDEX('Fragrance Projects'!$C$5:$C$64,MATCH($B14,'Fragrance Projects'!$A$5:$A$64,0)),"")) | E14: =IF($B14="","",IFERROR(INDEX('Project Financials'!$D$5:$D$64,MATCH($B14,'Project Financials'!$A$5:$A$64,0)),"")) | I14: =IF($E14="","",$E14-$G14) | N14: =IF($B14="","",_xlfn.IFS(OR($E14="",$E14=0),"Not Invoiced",($G14+$K14)>=$E14,"Paid",AND($J14<>"",TODAY()>$J14,($G14+$K14)<$E14),"Overdue",$G14=0,"Awaiting Deposit",TRUE(),"Part Paid")) | O14: =IF($B14="","",IF($N14="Overdue",TODAY()-$J14,0))
A15: =IF($B15="","",IFERROR(INDEX('Fragrance Projects'!$C$5:$C$64,MATCH($B15,'Fragrance Projects'!$A$5:$A$64,0)),"")) | E15: =IF($B15="","",IFERROR(INDEX('Project Financials'!$D$5:$D$64,MATCH($B15,'Project Financials'!$A$5:$A$64,0)),"")) | I15: =IF($E15="","",$E15-$G15) | N15: =IF($B15="","",_xlfn.IFS(OR($E15="",$E15=0),"Not Invoiced",($G15+$K15)>=$E15,"Paid",AND($J15<>"",TODAY()>$J15,($G15+$K15)<$E15),"Overdue",$G15=0,"Awaiting Deposit",TRUE(),"Part Paid")) | O15: =IF($B15="","",IF($N15="Overdue",TODAY()-$J15,0))
A16: =IF($B16="","",IFERROR(INDEX('Fragrance Projects'!$C$5:$C$64,MATCH($B16,'Fragrance Projects'!$A$5:$A$64,0)),"")) | E16: =IF($B16="","",IFERROR(INDEX('Project Financials'!$D$5:$D$64,MATCH($B16,'Project Financials'!$A$5:$A$64,0)),"")) | I16: =IF($E16="","",$E16-$G16) | N16: =IF($B16="","",_xlfn.IFS(OR($E16="",$E16=0),"Not Invoiced",($G16+$K16)>=$E16,"Paid",AND($J16<>"",TODAY()>$J16,($G16+$K16)<$E16),"Overdue",$G16=0,"Awaiting Deposit",TRUE(),"Part Paid")) | O16: =IF($B16="","",IF($N16="Overdue",TODAY()-$J16,0))
... A64: =IF($B64="","",IFERROR(INDEX('Fragrance Projects'!$C$5:$C$64,MATCH($B64,'Fragrance Projects'!$A$5:$A$64,0)),"")) | E64: =IF($B64="","",IFERROR(INDEX('Project Financials'!$D$5:$D$64,MATCH($B64,'Project Financials'!$A$5:$A$64,0)),"")) | I64: =IF($E64="","",$E64-$G64) | N64: =IF($B64="","",_xlfn.IFS(OR($E64="",$E64=0),"Not Invoiced",($G64+$K64)>=$E64,"Paid",AND($J64<>"",TODAY()>$J64,($G64+$K64)<$E64),"Overdue",$G64=0,"Awaiting Deposit",TRUE(),"Part Paid")) | O64: =IF($B64="","",IF($N64="Overdue",TODAY()-$J64,0))

Sheet Workload Planner
A1: WORKLOAD PLANNER — Capacity & Priorities
A2: Mirrors every fragrance project automatically. Urgency Score blends deadline, priority, iterations left and who's waiting on whom.
B3: INPUT — type or choose here | F3: CALCULATED — formula, do not edit | J3: AUTO-LOOKUP — pulled from another sheet
A4: Project ID | B4: Client | C4: Project / Fragrance | D4: Priority | E4: Current Stage | F4: Deadline | G4: Days Remaining | H4: Next Action | I4: Est. Hours Remaining | J4: Iterations Remaining | K4: Waiting On | L4: Urgency Score | M4: Assigned To
A5: =IF('Fragrance Projects'!A5="","",'Fragrance Projects'!A5) | B5: =IF('Fragrance Projects'!A5="","",'Fragrance Projects'!C5) | C5: =IF('Fragrance Projects'!A5="","",'Fragrance Projects'!D5) | D5: =IF('Fragrance Projects'!A5="","",'Fragrance Projects'!I5) | E5: =IF('Fragrance Projects'!A5="","",'Fragrance Projects'!H5) | F5: =IF('Fragrance Projects'!A5="","",'Fragrance Projects'!F5) | G5: =IF('Fragrance Projects'!A5="","",'Fragrance Projects'!G5) | H5: =IF('Fragrance Projects'!A5="","",'Fragrance Projects'!P5) | J5: =IF('Fragrance Projects'!A5="","",'Fragrance Projects'!M5) | K5: =IF('Fragrance Projects'!A5="","",'Fragrance Projects'!O5) | L5: =IF($A5="","",IF($E5="Complete",0,_xlfn.IFS($G5<0,40,$G5<=3,35,$G5<=7,25,$G5<=14,15,$G5<=30,8,TRUE(),0)+_xlfn.IFS($D5="Urgent",25,$D5="High",18,$D5="Normal",10,$D5="Low",5,TRUE(),0)+IF($K5="Us",20,0)+IF($J5<=0,15,IF($J5=1,8,0)))) | M5: =IF('Fragrance Projects'!A5="","",'Fragrance Projects'!AK5)
A6: =IF('Fragrance Projects'!A6="","",'Fragrance Projects'!A6) | B6: =IF('Fragrance Projects'!A6="","",'Fragrance Projects'!C6) | C6: =IF('Fragrance Projects'!A6="","",'Fragrance Projects'!D6) | D6: =IF('Fragrance Projects'!A6="","",'Fragrance Projects'!I6) | E6: =IF('Fragrance Projects'!A6="","",'Fragrance Projects'!H6) | F6: =IF('Fragrance Projects'!A6="","",'Fragrance Projects'!F6) | G6: =IF('Fragrance Projects'!A6="","",'Fragrance Projects'!G6) | H6: =IF('Fragrance Projects'!A6="","",'Fragrance Projects'!P6) | J6: =IF('Fragrance Projects'!A6="","",'Fragrance Projects'!M6) | K6: =IF('Fragrance Projects'!A6="","",'Fragrance Projects'!O6) | L6: =IF($A6="","",IF($E6="Complete",0,_xlfn.IFS($G6<0,40,$G6<=3,35,$G6<=7,25,$G6<=14,15,$G6<=30,8,TRUE(),0)+_xlfn.IFS($D6="Urgent",25,$D6="High",18,$D6="Normal",10,$D6="Low",5,TRUE(),0)+IF($K6="Us",20,0)+IF($J6<=0,15,IF($J6=1,8,0)))) | M6: =IF('Fragrance Projects'!A6="","",'Fragrance Projects'!AK6)
A7: =IF('Fragrance Projects'!A7="","",'Fragrance Projects'!A7) | B7: =IF('Fragrance Projects'!A7="","",'Fragrance Projects'!C7) | C7: =IF('Fragrance Projects'!A7="","",'Fragrance Projects'!D7) | D7: =IF('Fragrance Projects'!A7="","",'Fragrance Projects'!I7) | E7: =IF('Fragrance Projects'!A7="","",'Fragrance Projects'!H7) | F7: =IF('Fragrance Projects'!A7="","",'Fragrance Projects'!F7) | G7: =IF('Fragrance Projects'!A7="","",'Fragrance Projects'!G7) | H7: =IF('Fragrance Projects'!A7="","",'Fragrance Projects'!P7) | J7: =IF('Fragrance Projects'!A7="","",'Fragrance Projects'!M7) | K7: =IF('Fragrance Projects'!A7="","",'Fragrance Projects'!O7) | L7: =IF($A7="","",IF($E7="Complete",0,_xlfn.IFS($G7<0,40,$G7<=3,35,$G7<=7,25,$G7<=14,15,$G7<=30,8,TRUE(),0)+_xlfn.IFS($D7="Urgent",25,$D7="High",18,$D7="Normal",10,$D7="Low",5,TRUE(),0)+IF($K7="Us",20,0)+IF($J7<=0,15,IF($J7=1,8,0)))) | M7: =IF('Fragrance Projects'!A7="","",'Fragrance Projects'!AK7)
A8: =IF('Fragrance Projects'!A8="","",'Fragrance Projects'!A8) | B8: =IF('Fragrance Projects'!A8="","",'Fragrance Projects'!C8) | C8: =IF('Fragrance Projects'!A8="","",'Fragrance Projects'!D8) | D8: =IF('Fragrance Projects'!A8="","",'Fragrance Projects'!I8) | E8: =IF('Fragrance Projects'!A8="","",'Fragrance Projects'!H8) | F8: =IF('Fragrance Projects'!A8="","",'Fragrance Projects'!F8) | G8: =IF('Fragrance Projects'!A8="","",'Fragrance Projects'!G8) | H8: =IF('Fragrance Projects'!A8="","",'Fragrance Projects'!P8) | J8: =IF('Fragrance Projects'!A8="","",'Fragrance Projects'!M8) | K8: =IF('Fragrance Projects'!A8="","",'Fragrance Projects'!O8) | L8: =IF($A8="","",IF($E8="Complete",0,_xlfn.IFS($G8<0,40,$G8<=3,35,$G8<=7,25,$G8<=14,15,$G8<=30,8,TRUE(),0)+_xlfn.IFS($D8="Urgent",25,$D8="High",18,$D8="Normal",10,$D8="Low",5,TRUE(),0)+IF($K8="Us",20,0)+IF($J8<=0,15,IF($J8=1,8,0)))) | M8: =IF('Fragrance Projects'!A8="","",'Fragrance Projects'!AK8)
A9: =IF('Fragrance Projects'!A9="","",'Fragrance Projects'!A9) | B9: =IF('Fragrance Projects'!A9="","",'Fragrance Projects'!C9) | C9: =IF('Fragrance Projects'!A9="","",'Fragrance Projects'!D9) | D9: =IF('Fragrance Projects'!A9="","",'Fragrance Projects'!I9) | E9: =IF('Fragrance Projects'!A9="","",'Fragrance Projects'!H9) | F9: =IF('Fragrance Projects'!A9="","",'Fragrance Projects'!F9) | G9: =IF('Fragrance Projects'!A9="","",'Fragrance Projects'!G9) | H9: =IF('Fragrance Projects'!A9="","",'Fragrance Projects'!P9) | J9: =IF('Fragrance Projects'!A9="","",'Fragrance Projects'!M9) | K9: =IF('Fragrance Projects'!A9="","",'Fragrance Projects'!O9) | L9: =IF($A9="","",IF($E9="Complete",0,_xlfn.IFS($G9<0,40,$G9<=3,35,$G9<=7,25,$G9<=14,15,$G9<=30,8,TRUE(),0)+_xlfn.IFS($D9="Urgent",25,$D9="High",18,$D9="Normal",10,$D9="Low",5,TRUE(),0)+IF($K9="Us",20,0)+IF($J9<=0,15,IF($J9=1,8,0)))) | M9: =IF('Fragrance Projects'!A9="","",'Fragrance Projects'!AK9)
A10: =IF('Fragrance Projects'!A10="","",'Fragrance Projects'!A10) | B10: =IF('Fragrance Projects'!A10="","",'Fragrance Projects'!C10) | C10: =IF('Fragrance Projects'!A10="","",'Fragrance Projects'!D10) | D10: =IF('Fragrance Projects'!A10="","",'Fragrance Projects'!I10) | E10: =IF('Fragrance Projects'!A10="","",'Fragrance Projects'!H10) | F10: =IF('Fragrance Projects'!A10="","",'Fragrance Projects'!F10) | G10: =IF('Fragrance Projects'!A10="","",'Fragrance Projects'!G10) | H10: =IF('Fragrance Projects'!A10="","",'Fragrance Projects'!P10) | J10: =IF('Fragrance Projects'!A10="","",'Fragrance Projects'!M10) | K10: =IF('Fragrance Projects'!A10="","",'Fragrance Projects'!O10) | L10: =IF($A10="","",IF($E10="Complete",0,_xlfn.IFS($G10<0,40,$G10<=3,35,$G10<=7,25,$G10<=14,15,$G10<=30,8,TRUE(),0)+_xlfn.IFS($D10="Urgent",25,$D10="High",18,$D10="Normal",10,$D10="Low",5,TRUE(),0)+IF($K10="Us",20,0)+IF($J10<=0,15,IF($J10=1,8,0)))) | M10: =IF('Fragrance Projects'!A10="","",'Fragrance Projects'!AK10)
A11: =IF('Fragrance Projects'!A11="","",'Fragrance Projects'!A11) | B11: =IF('Fragrance Projects'!A11="","",'Fragrance Projects'!C11) | C11: =IF('Fragrance Projects'!A11="","",'Fragrance Projects'!D11) | D11: =IF('Fragrance Projects'!A11="","",'Fragrance Projects'!I11) | E11: =IF('Fragrance Projects'!A11="","",'Fragrance Projects'!H11) | F11: =IF('Fragrance Projects'!A11="","",'Fragrance Projects'!F11) | G11: =IF('Fragrance Projects'!A11="","",'Fragrance Projects'!G11) | H11: =IF('Fragrance Projects'!A11="","",'Fragrance Projects'!P11) | J11: =IF('Fragrance Projects'!A11="","",'Fragrance Projects'!M11) | K11: =IF('Fragrance Projects'!A11="","",'Fragrance Projects'!O11) | L11: =IF($A11="","",IF($E11="Complete",0,_xlfn.IFS($G11<0,40,$G11<=3,35,$G11<=7,25,$G11<=14,15,$G11<=30,8,TRUE(),0)+_xlfn.IFS($D11="Urgent",25,$D11="High",18,$D11="Normal",10,$D11="Low",5,TRUE(),0)+IF($K11="Us",20,0)+IF($J11<=0,15,IF($J11=1,8,0)))) | M11: =IF('Fragrance Projects'!A11="","",'Fragrance Projects'!AK11)
A12: =IF('Fragrance Projects'!A12="","",'Fragrance Projects'!A12) | B12: =IF('Fragrance Projects'!A12="","",'Fragrance Projects'!C12) | C12: =IF('Fragrance Projects'!A12="","",'Fragrance Projects'!D12) | D12: =IF('Fragrance Projects'!A12="","",'Fragrance Projects'!I12) | E12: =IF('Fragrance Projects'!A12="","",'Fragrance Projects'!H12) | F12: =IF('Fragrance Projects'!A12="","",'Fragrance Projects'!F12) | G12: =IF('Fragrance Projects'!A12="","",'Fragrance Projects'!G12) | H12: =IF('Fragrance Projects'!A12="","",'Fragrance Projects'!P12) | J12: =IF('Fragrance Projects'!A12="","",'Fragrance Projects'!M12) | K12: =IF('Fragrance Projects'!A12="","",'Fragrance Projects'!O12) | L12: =IF($A12="","",IF($E12="Complete",0,_xlfn.IFS($G12<0,40,$G12<=3,35,$G12<=7,25,$G12<=14,15,$G12<=30,8,TRUE(),0)+_xlfn.IFS($D12="Urgent",25,$D12="High",18,$D12="Normal",10,$D12="Low",5,TRUE(),0)+IF($K12="Us",20,0)+IF($J12<=0,15,IF($J12=1,8,0)))) | M12: =IF('Fragrance Projects'!A12="","",'Fragrance Projects'!AK12)
A13: =IF('Fragrance Projects'!A13="","",'Fragrance Projects'!A13) | B13: =IF('Fragrance Projects'!A13="","",'Fragrance Projects'!C13) | C13: =IF('Fragrance Projects'!A13="","",'Fragrance Projects'!D13) | D13: =IF('Fragrance Projects'!A13="","",'Fragrance Projects'!I13) | E13: =IF('Fragrance Projects'!A13="","",'Fragrance Projects'!H13) | F13: =IF('Fragrance Projects'!A13="","",'Fragrance Projects'!F13) | G13: =IF('Fragrance Projects'!A13="","",'Fragrance Projects'!G13) | H13: =IF('Fragrance Projects'!A13="","",'Fragrance Projects'!P13) | J13: =IF('Fragrance Projects'!A13="","",'Fragrance Projects'!M13) | K13: =IF('Fragrance Projects'!A13="","",'Fragrance Projects'!O13) | L13: =IF($A13="","",IF($E13="Complete",0,_xlfn.IFS($G13<0,40,$G13<=3,35,$G13<=7,25,$G13<=14,15,$G13<=30,8,TRUE(),0)+_xlfn.IFS($D13="Urgent",25,$D13="High",18,$D13="Normal",10,$D13="Low",5,TRUE(),0)+IF($K13="Us",20,0)+IF($J13<=0,15,IF($J13=1,8,0)))) | M13: =IF('Fragrance Projects'!A13="","",'Fragrance Projects'!AK13)
A14: =IF('Fragrance Projects'!A14="","",'Fragrance Projects'!A14) | B14: =IF('Fragrance Projects'!A14="","",'Fragrance Projects'!C14) | C14: =IF('Fragrance Projects'!A14="","",'Fragrance Projects'!D14) | D14: =IF('Fragrance Projects'!A14="","",'Fragrance Projects'!I14) | E14: =IF('Fragrance Projects'!A14="","",'Fragrance Projects'!H14) | F14: =IF('Fragrance Projects'!A14="","",'Fragrance Projects'!F14) | G14: =IF('Fragrance Projects'!A14="","",'Fragrance Projects'!G14) | H14: =IF('Fragrance Projects'!A14="","",'Fragrance Projects'!P14) | J14: =IF('Fragrance Projects'!A14="","",'Fragrance Projects'!M14) | K14: =IF('Fragrance Projects'!A14="","",'Fragrance Projects'!O14) | L14: =IF($A14="","",IF($E14="Complete",0,_xlfn.IFS($G14<0,40,$G14<=3,35,$G14<=7,25,$G14<=14,15,$G14<=30,8,TRUE(),0)+_xlfn.IFS($D14="Urgent",25,$D14="High",18,$D14="Normal",10,$D14="Low",5,TRUE(),0)+IF($K14="Us",20,0)+IF($J14<=0,15,IF($J14=1,8,0)))) | M14: =IF('Fragrance Projects'!A14="","",'Fragrance Projects'!AK14)
A15: =IF('Fragrance Projects'!A15="","",'Fragrance Projects'!A15) | B15: =IF('Fragrance Projects'!A15="","",'Fragrance Projects'!C15) | C15: =IF('Fragrance Projects'!A15="","",'Fragrance Projects'!D15) | D15: =IF('Fragrance Projects'!A15="","",'Fragrance Projects'!I15) | E15: =IF('Fragrance Projects'!A15="","",'Fragrance Projects'!H15) | F15: =IF('Fragrance Projects'!A15="","",'Fragrance Projects'!F15) | G15: =IF('Fragrance Projects'!A15="","",'Fragrance Projects'!G15) | H15: =IF('Fragrance Projects'!A15="","",'Fragrance Projects'!P15) | J15: =IF('Fragrance Projects'!A15="","",'Fragrance Projects'!M15) | K15: =IF('Fragrance Projects'!A15="","",'Fragrance Projects'!O15) | L15: =IF($A15="","",IF($E15="Complete",0,_xlfn.IFS($G15<0,40,$G15<=3,35,$G15<=7,25,$G15<=14,15,$G15<=30,8,TRUE(),0)+_xlfn.IFS($D15="Urgent",25,$D15="High",18,$D15="Normal",10,$D15="Low",5,TRUE(),0)+IF($K15="Us",20,0)+IF($J15<=0,15,IF($J15=1,8,0)))) | M15: =IF('Fragrance Projects'!A15="","",'Fragrance Projects'!AK15)
A16: =IF('Fragrance Projects'!A16="","",'Fragrance Projects'!A16) | B16: =IF('Fragrance Projects'!A16="","",'Fragrance Projects'!C16) | C16: =IF('Fragrance Projects'!A16="","",'Fragrance Projects'!D16) | D16: =IF('Fragrance Projects'!A16="","",'Fragrance Projects'!I16) | E16: =IF('Fragrance Projects'!A16="","",'Fragrance Projects'!H16) | F16: =IF('Fragrance Projects'!A16="","",'Fragrance Projects'!F16) | G16: =IF('Fragrance Projects'!A16="","",'Fragrance Projects'!G16) | H16: =IF('Fragrance Projects'!A16="","",'Fragrance Projects'!P16) | J16: =IF('Fragrance Projects'!A16="","",'Fragrance Projects'!M16) | K16: =IF('Fragrance Projects'!A16="","",'Fragrance Projects'!O16) | L16: =IF($A16="","",IF($E16="Complete",0,_xlfn.IFS($G16<0,40,$G16<=3,35,$G16<=7,25,$G16<=14,15,$G16<=30,8,TRUE(),0)+_xlfn.IFS($D16="Urgent",25,$D16="High",18,$D16="Normal",10,$D16="Low",5,TRUE(),0)+IF($K16="Us",20,0)+IF($J16<=0,15,IF($J16=1,8,0)))) | M16: =IF('Fragrance Projects'!A16="","",'Fragrance Projects'!AK16)
... A64: =IF('Fragrance Projects'!A64="","",'Fragrance Projects'!A64) | B64: =IF('Fragrance Projects'!A64="","",'Fragrance Projects'!C64) | C64: =IF('Fragrance Projects'!A64="","",'Fragrance Projects'!D64) | D64: =IF('Fragrance Projects'!A64="","",'Fragrance Projects'!I64) | E64: =IF('Fragrance Projects'!A64="","",'Fragrance Projects'!H64) | F64: =IF('Fragrance Projects'!A64="","",'Fragrance Projects'!F64) | G64: =IF('Fragrance Projects'!A64="","",'Fragrance Projects'!G64) | H64: =IF('Fragrance Projects'!A64="","",'Fragrance Projects'!P64) | J64: =IF('Fragrance Projects'!A64="","",'Fragrance Projects'!M64) | K64: =IF('Fragrance Projects'!A64="","",'Fragrance Projects'!O64) | L64: =IF($A64="","",IF($E64="Complete",0,_xlfn.IFS($G64<0,40,$G64<=3,35,$G64<=7,25,$G64<=14,15,$G64<=30,8,TRUE(),0)+_xlfn.IFS($D64="Urgent",25,$D64="High",18,$D64="Normal",10,$D64="Low",5,TRUE(),0)+IF($K64="Us",20,0)+IF($J64<=0,15,IF($J64=1,8,0)))) | M64: =IF('Fragrance Projects'!A64="","",'Fragrance Projects'!AK64)
A67: THIS WEEK — Automatically Generated Action List
A69: Category | B69: Count | C69: Example Projects (up to 3)
A70: Formulas to create | B70: =COUNTIFS('Fragrance Projects'!$H$5:$H$64,"Formula Development",'Fragrance Projects'!$O$5:$O$64,"Us") -> 0 | C70: =IF(LEN(IF(LEN(IFERROR(INDEX('Fragrance Projects'!$D$5:$D$64,SUMPRODUCT(SMALL(IF((('Fragrance Projects'!$H$5:$H$64="Formula Development")*('Fragrance Projects'!$O$5:$O$64="Us")),ROW('Fragrance Projects'!$H$5:$H$64)-ROW(INDEX('Fragrance Projects'!$H$5:$H$64,1))+1),1))),""))>0,IFERROR(INDEX('Fragrance Projects'!$D$5:$D$64,SUMPRODUCT(SMALL(IF((('Fragrance Projects'!$H$5:$H$64="Formula Development")*('Fragrance Projects'!$O$5:$O$64="Us")),ROW('Fragrance Projects'!$H$5:$H$64)-ROW(INDEX('Fragrance Projects'!$H$5:$H$64,1))+1),1))),"")&"; ","")&IF(LEN(IFERROR(INDEX('Fragrance Projects'!$D$5:$D$64,SUMPRODUCT(SMALL(IF((('Fragrance Projects'!$H$5:$H$64="Formula Development")*('Fragrance Projects'!$O$5:$O$64="Us")),ROW('Fragrance Projects'!$H$5:$H$64)-ROW(INDEX('Fragrance Projects'!$H$5:$H$64,1))+1),2))),""))>0,IFERROR(INDEX('Fragrance Projects'!$D$5:$D$64,SUMPRODUCT(SMALL(IF((('Fragrance Projects'!$H$5:$H$64="Formula Development")*('Fragrance Projects'!$O$5:$O$64="Us")),ROW('Fragrance Projects'!$H$5:$H$64)-ROW(INDEX('Fragrance Projects'!$H$5:$H$64,1))+1),2))),"")&"; ","")&IF(LEN(IFERROR(INDEX('Fragrance Projects'!$D$5:$D$64,SUMPRODUCT(SMALL(IF((('Fragrance Projects'!$H$5:$H$64="Formula Development")*('Fragrance Projects'!$O$5:$O$64="Us")),ROW('Fragrance Projects'!$H$5:$H$64)-ROW(INDEX('Fragrance Projects'!$H$5:$H$64,1))+1),3))),""))>0,IFERROR(INDEX('Fragrance Projects'!$D$5:$D$64,SUMPRODUCT(SMALL(IF((('Fragrance Projects'!$H$5:$H$64="Formula Development")*('Fragrance Projects'!$O$5:$O$64="Us")),ROW('Fragrance Projects'!$H$5:$H$64)-ROW(INDEX('Fragrance Projects'!$H$5:$H$64,1))+1),3))),"")&"; ",""))=0,"",LEFT(IF(LEN(IFERROR(INDEX('Fragrance Projects'!$D$5:$D$64,SUMPRODUCT(SMALL(IF((('Fragrance Projects'!$H$5:$H$64="Formula Development")*('Fragrance Projects'!$O$5:$O$64="Us")),ROW('Fragrance Projects'!$H$5:$H$64)-ROW(INDEX('Fragrance Projects'!$H$5:$H$64,1))+1),1))),""))>0,IFERROR(INDEX('Fragrance Projects'!$D$5:$D$64,SUMPRODUCT(SMALL(IF((('Fragrance Projects'!$H$5:$H$64="Formula Development")*('Fragrance Projects'!$O$5:$O$64="Us")),ROW('Fragrance Projects'!$H$5:$H$64)-ROW(INDEX('Fragrance Projects'!$H$5:$H$64,1))+1),1))),"")&"; ","")&IF(LEN(IFERROR(INDEX('Fragrance Projects'!$D$5:$D$64,SUMPRODUCT(SMALL(IF((('Fragrance Projects'!$H$5:$H$64="Formula Development")*('Fragrance Projects'!$O$5:$O$64="Us")),ROW('Fragrance Projects'!$H$5:$H$64)-ROW(INDEX('Fragrance Projects'!$H$5:$H$64,1))+1),2))),""))>0,IFERROR(INDEX('Fragrance Projects'!$D$5:$D$64,SUMPRODUCT(SMALL(IF((('Fragrance Projects'!$H$5:$H$64="Formula Development")*('Fragrance Projects'!$O$5:$O$64="Us")),ROW('Fragrance Projects'!$H$5:$H$64)-ROW(INDEX('Fragrance Projects'!$H$5:$H$64,1))+1),2))),"")&"; ","")&IF(LEN(IFERROR(INDEX('Fragrance Projects'!$D$5:$D$64,SUMPRODUCT(SMALL(IF((('Fragrance Projects'!$H$5:$H$64="Formula Development")*('Fragrance Projects'!$O$5:$O$64="Us")),ROW('Fragrance Projects'!$H$5:$H$64)-ROW(INDEX('Fragrance Projects'!$H$5:$H$64,1))+1),3))),""))>0,IFERROR(INDEX('Fragrance Projects'!$D$5:$D$64,SUMPRODUCT(SMALL(IF((('Fragrance Projects'!$H$5:$H$64="Formula Development")*('Fragrance Projects'!$O$5:$O$64="Us")),ROW('Fragrance Projects'!$H$5:$H$64)-ROW(INDEX('Fragrance Projects'!$H$5:$H$64,1))+1),3))),"")&"; ",""),LEN(IF(LEN(IFERROR(INDEX('Fragrance Projects'!$D$5:$D$64,SUMPRODUCT(SMALL(IF((('Fragrance Projects'!$H$5:$H$64="Formula Development")*('Fragrance Projects'!$O$5:$O$64="Us")),ROW('Fragrance Projects'!$H$5:$H$64)-ROW(INDEX('Fragrance Projects'!$H$5:$H$64,1))+1),1))),""))>0,IFERROR(INDEX('Fragrance Projects'!$D$5:$D$64,SUMPRODUCT(SMALL(IF((('Fragrance Projects'!$H$5:$H$64="Formula Development")*('Fragrance Projects'!$O$5:$O$64="Us")),ROW('Fragrance Projects'!$H$5:$H$64)-ROW(INDEX('Fragrance Projects'!$H$5:$H$64,1))+1),1))),"")&"; ","")&IF(LEN(IFERROR(INDEX('Fragrance Projects'!$D$5:$D$64,SUMPRODUCT(SMALL(IF((('Fragrance Projects'!$H$5:$H$64="Formula Development")*('Fragrance Projects'!$O$5:$O$64="Us")),ROW('Fragrance Projects'!$H$5:$H$64)-ROW(INDEX('Fragrance Projects'!$H$5:$H$64,1))+1),2))),""))>0,IFERROR(INDEX('Fragrance Projects'!$D$5:$D$64,SUMPRODUCT(SMALL(IF((('Fragrance Projects'!$H$5:$H$64="Formula Development")*('Fragrance Projects'!$O$5:$O$64="Us")),ROW('Fragrance Projects'!$H$5:$H$64)-ROW(INDEX('Fragrance Projects'!$H$5:$H$64,1))+1),2))),"")&"; ","")&IF(LEN(IFERROR(INDEX('Fragrance Projects'!$D$5:$D$64,SUMPRODUCT(SMALL(IF((('Fragrance Projects'!$H$5:$H$64="Formula Development")*('Fragrance Projects'!$O$5:$O$64="Us")),ROW('Fragrance Projects'!$H$5:$H$64)-ROW(INDEX('Fragrance Projects'!$H$5:$H$64,1))+1),3))),""))>0,IFERROR(INDEX('Fragrance Projects'!$D$5:$D$64,SUMPRODUCT(SMALL(IF((('Fragrance Projects'!$H$5:$H$64="Formula Development")*('Fragrance Projects'!$O$5:$O$64="Us")),ROW('Fragrance Projects'!$H$5:$H$64)-ROW(INDEX('Fragrance Projects'!$H$5:$H$64,1))+1),3))),"")&"; ",""))-2))
A71: Reformulations required | B71: =COUNTIF('Fragrance Projects'!$H$5:$H$64,"Reformulation") -> 0 | C71: =IF(LEN(IF(LEN(IFERROR(INDEX('Fragrance Projects'!$D$5:$D$64,SUMPRODUCT(SMALL(IF((('Fragrance Projects'!$H$5:$H$64="Reformulation")),ROW('Fragrance Projects'!$H$5:$H$64)-ROW(INDEX('Fragrance Projects'!$H$5:$H$64,1))+1),1))),""))>0,IFERROR(INDEX('Fragrance Projects'!$D$5:$D$64,SUMPRODUCT(SMALL(IF((('Fragrance Projects'!$H$5:$H$64="Reformulation")),ROW('Fragrance Projects'!$H$5:$H$64)-ROW(INDEX('Fragrance Projects'!$H$5:$H$64,1))+1),1))),"")&"; ","")&IF(LEN(IFERROR(INDEX('Fragrance Projects'!$D$5:$D$64,SUMPRODUCT(SMALL(IF((('Fragrance Projects'!$H$5:$H$64="Reformulation")),ROW('Fragrance Projects'!$H$5:$H$64)-ROW(INDEX('Fragrance Projects'!$H$5:$H$64,1))+1),2))),""))>0,IFERROR(INDEX('Fragrance Projects'!$D$5:$D$64,SUMPRODUCT(SMALL(IF((('Fragrance Projects'!$H$5:$H$64="Reformulation")),ROW('Fragrance Projects'!$H$5:$H$64)-ROW(INDEX('Fragrance Projects'!$H$5:$H$64,1))+1),2))),"")&"; ","")&IF(LEN(IFERROR(INDEX('Fragrance Projects'!$D$5:$D$64,SUMPRODUCT(SMALL(IF((('Fragrance Projects'!$H$5:$H$64="Reformulation")),ROW('Fragrance Projects'!$H$5:$H$64)-ROW(INDEX('Fragrance Projects'!$H$5:$H$64,1))+1),3))),""))>0,IFERROR(INDEX('Fragrance Projects'!$D$5:$D$64,SUMPRODUCT(SMALL(IF((('Fragrance Projects'!$H$5:$H$64="Reformulation")),ROW('Fragrance Projects'!$H$5:$H$64)-ROW(INDEX('Fragrance Projects'!$H$5:$H$64,1))+1),3))),"")&"; ",""))=0,"",LEFT(IF(LEN(IFERROR(INDEX('Fragrance Projects'!$D$5:$D$64,SUMPRODUCT(SMALL(IF((('Fragrance Projects'!$H$5:$H$64="Reformulation")),ROW('Fragrance Projects'!$H$5:$H$64)-ROW(INDEX('Fragrance Projects'!$H$5:$H$64,1))+1),1))),""))>0,IFERROR(INDEX('Fragrance Projects'!$D$5:$D$64,SUMPRODUCT(SMALL(IF((('Fragrance Projects'!$H$5:$H$64="Reformulation")),ROW('Fragrance Projects'!$H$5:$H$64)-ROW(INDEX('Fragrance Projects'!$H$5:$H$64,1))+1),1))),"")&"; ","")&IF(LEN(IFERROR(INDEX('Fragrance Projects'!$D$5:$D$64,SUMPRODUCT(SMALL(IF((('Fragrance Projects'!$H$5:$H$64="Reformulation")),ROW('Fragrance Projects'!$H$5:$H$64)-ROW(INDEX('Fragrance Projects'!$H$5:$H$64,1))+1),2))),""))>0,IFERROR(INDEX('Fragrance Projects'!$D$5:$D$64,SUMPRODUCT(SMALL(IF((('Fragrance Projects'!$H$5:$H$64="Reformulation")),ROW('Fragrance Projects'!$H$5:$H$64)-ROW(INDEX('Fragrance Projects'!$H$5:$H$64,1))+1),2))),"")&"; ","")&IF(LEN(IFERROR(INDEX('Fragrance Projects'!$D$5:$D$64,SUMPRODUCT(SMALL(IF((('Fragrance Projects'!$H$5:$H$64="Reformulation")),ROW('Fragrance Projects'!$H$5:$H$64)-ROW(INDEX('Fragrance Projects'!$H$5:$H$64,1))+1),3))),""))>0,IFERROR(INDEX('Fragrance Projects'!$D$5:$D$64,SUMPRODUCT(SMALL(IF((('Fragrance Projects'!$H$5:$H$64="Reformulation")),ROW('Fragrance Projects'!$H$5:$H$64)-ROW(INDEX('Fragrance Projects'!$H$5:$H$64,1))+1),3))),"")&"; ",""),LEN(IF(LEN(IFERROR(INDEX('Fragrance Projects'!$D$5:$D$64,SUMPRODUCT(SMALL(IF((('Fragrance Projects'!$H$5:$H$64="Reformulation")),ROW('Fragrance Projects'!$H$5:$H$64)-ROW(INDEX('Fragrance Projects'!$H$5:$H$64,1))+1),1))),""))>0,IFERROR(INDEX('Fragrance Projects'!$D$5:$D$64,SUMPRODUCT(SMALL(IF((('Fragrance Projects'!$H$5:$H$64="Reformulation")),ROW('Fragrance Projects'!$H$5:$H$64)-ROW(INDEX('Fragrance Projects'!$H$5:$H$64,1))+1),1))),"")&"; ","")&IF(LEN(IFERROR(INDEX('Fragrance Projects'!$D$5:$D$64,SUMPRODUCT(SMALL(IF((('Fragrance Projects'!$H$5:$H$64="Reformulation")),ROW('Fragrance Projects'!$H$5:$H$64)-ROW(INDEX('Fragrance Projects'!$H$5:$H$64,1))+1),2))),""))>0,IFERROR(INDEX('Fragrance Projects'!$D$5:$D$64,SUMPRODUCT(SMALL(IF((('Fragrance Projects'!$H$5:$H$64="Reformulation")),ROW('Fragrance Projects'!$H$5:$H$64)-ROW(INDEX('Fragrance Projects'!$H$5:$H$64,1))+1),2))),"")&"; ","")&IF(LEN(IFERROR(INDEX('Fragrance Projects'!$D$5:$D$64,SUMPRODUCT(SMALL(IF((('Fragrance Projects'!$H$5:$H$64="Reformulation")),ROW('Fragrance Projects'!$H$5:$H$64)-ROW(INDEX('Fragrance Projects'!$H$5:$H$64,1))+1),3))),""))>0,IFERROR(INDEX('Fragrance Projects'!$D$5:$D$64,SUMPRODUCT(SMALL(IF((('Fragrance Projects'!$H$5:$H$64="Reformulation")),ROW('Fragrance Projects'!$H$5:$H$64)-ROW(INDEX('Fragrance Projects'!$H$5:$H$64,1))+1),3))),"")&"; ",""))-2))
A72: Samples to compound | B72: =COUNTIF('Fragrance Projects'!$H$5:$H$64,"Compounding") -> 0 | C72: =IF(LEN(IF(LEN(IFERROR(INDEX('Fragrance Projects'!$D$5:$D$64,SUMPRODUCT(SMALL(IF((('Fragrance Projects'!$H$5:$H$64="Compounding")),ROW('Fragrance Projects'!$H$5:$H$64)-ROW(INDEX('Fragrance Projects'!$H$5:$H$64,1))+1),1))),""))>0,IFERROR(INDEX('Fragrance Projects'!$D$5:$D$64,SUMPRODUCT(SMALL(IF((('Fragrance Projects'!$H$5:$H$64="Compounding")),ROW('Fragrance Projects'!$H$5:$H$64)-ROW(INDEX('Fragrance Projects'!$H$5:$H$64,1))+1),1))),"")&"; ","")&IF(LEN(IFERROR(INDEX('Fragrance Projects'!$D$5:$D$64,SUMPRODUCT(SMALL(IF((('Fragrance Projects'!$H$5:$H$64="Compounding")),ROW('Fragrance Projects'!$H$5:$H$64)-ROW(INDEX('Fragrance Projects'!$H$5:$H$64,1))+1),2))),""))>0,IFERROR(INDEX('Fragrance Projects'!$D$5:$D$64,SUMPRODUCT(SMALL(IF((('Fragrance Projects'!$H$5:$H$64="Compounding")),ROW('Fragrance Projects'!$H$5:$H$64)-ROW(INDEX('Fragrance Projects'!$H$5:$H$64,1))+1),2))),"")&"; ","")&IF(LEN(IFERROR(INDEX('Fragrance Projects'!$D$5:$D$64,SUMPRODUCT(SMALL(IF((('Fragrance Projects'!$H$5:$H$64="Compounding")),ROW('Fragrance Projects'!$H$5:$H$64)-ROW(INDEX('Fragrance Projects'!$H$5:$H$64,1))+1),3))),""))>0,IFERROR(INDEX('Fragrance Projects'!$D$5:$D$64,SUMPRODUCT(SMALL(IF((('Fragrance Projects'!$H$5:$H$64="Compounding")),ROW('Fragrance Projects'!$H$5:$H$64)-ROW(INDEX('Fragrance Projects'!$H$5:$H$64,1))+1),3))),"")&"; ",""))=0,"",LEFT(IF(LEN(IFERROR(INDEX('Fragrance Projects'!$D$5:$D$64,SUMPRODUCT(SMALL(IF((('Fragrance Projects'!$H$5:$H$64="Compounding")),ROW('Fragrance Projects'!$H$5:$H$64)-ROW(INDEX('Fragrance Projects'!$H$5:$H$64,1))+1),1))),""))>0,IFERROR(INDEX('Fragrance Projects'!$D$5:$D$64,SUMPRODUCT(SMALL(IF((('Fragrance Projects'!$H$5:$H$64="Compounding")),ROW('Fragrance Projects'!$H$5:$H$64)-ROW(INDEX('Fragrance Projects'!$H$5:$H$64,1))+1),1))),"")&"; ","")&IF(LEN(IFERROR(INDEX('Fragrance Projects'!$D$5:$D$64,SUMPRODUCT(SMALL(IF((('Fragrance Projects'!$H$5:$H$64="Compounding")),ROW('Fragrance Projects'!$H$5:$H$64)-ROW(INDEX('Fragrance Projects'!$H$5:$H$64,1))+1),2))),""))>0,IFERROR(INDEX('Fragrance Projects'!$D$5:$D$64,SUMPRODUCT(SMALL(IF((('Fragrance Projects'!$H$5:$H$64="Compounding")),ROW('Fragrance Projects'!$H$5:$H$64)-ROW(INDEX('Fragrance Projects'!$H$5:$H$64,1))+1),2))),"")&"; ","")&IF(LEN(IFERROR(INDEX('Fragrance Projects'!$D$5:$D$64,SUMPRODUCT(SMALL(IF((('Fragrance Projects'!$H$5:$H$64="Compounding")),ROW('Fragrance Projects'!$H$5:$H$64)-ROW(INDEX('Fragrance Projects'!$H$5:$H$64,1))+1),3))),""))>0,IFERROR(INDEX('Fragrance Projects'!$D$5:$D$64,SUMPRODUCT(SMALL(IF((('Fragrance Projects'!$H$5:$H$64="Compounding")),ROW('Fragrance Projects'!$H$5:$H$64)-ROW(INDEX('Fragrance Projects'!$H$5:$H$64,1))+1),3))),"")&"; ",""),LEN(IF(LEN(IFERROR(INDEX('Fragrance Projects'!$D$5:$D$64,SUMPRODUCT(SMALL(IF((('Fragrance Projects'!$H$5:$H$64="Compounding")),ROW('Fragrance Projects'!$H$5:$H$64)-ROW(INDEX('Fragrance Projects'!$H$5:$H$64,1))+1),1))),""))>0,IFERROR(INDEX('Fragrance Projects'!$D$5:$D$64,SUMPRODUCT(SMALL(IF((('Fragrance Projects'!$H$5:$H$64="Compounding")),ROW('Fragrance Projects'!$H$5:$H$64)-ROW(INDEX('Fragrance Projects'!$H$5:$H$64,1))+1),1))),"")&"; ","")&IF(LEN(IFERROR(INDEX('Fragrance Projects'!$D$5:$D$64,SUMPRODUCT(SMALL(IF((('Fragrance Projects'!$H$5:$H$64="Compounding")),ROW('Fragrance Projects'!$H$5:$H$64)-ROW(INDEX('Fragrance Projects'!$H$5:$H$64,1))+1),2))),""))>0,IFERROR(INDEX('Fragrance Projects'!$D$5:$D$64,SUMPRODUCT(SMALL(IF((('Fragrance Projects'!$H$5:$H$64="Compounding")),ROW('Fragrance Projects'!$H$5:$H$64)-ROW(INDEX('Fragrance Projects'!$H$5:$H$64,1))+1),2))),"")&"; ","")&IF(LEN(IFERROR(INDEX('Fragrance Projects'!$D$5:$D$64,SUMPRODUCT(SMALL(IF((('Fragrance Projects'!$H$5:$H$64="Compounding")),ROW('Fragrance Projects'!$H$5:$H$64)-ROW(INDEX('Fragrance Projects'!$H$5:$H$64,1))+1),3))),""))>0,IFERROR(INDEX('Fragrance Projects'!$D$5:$D$64,SUMPRODUCT(SMALL(IF((('Fragrance Projects'!$H$5:$H$64="Compounding")),ROW('Fragrance Projects'!$H$5:$H$64)-ROW(INDEX('Fragrance Projects'!$H$5:$H$64,1))+1),3))),"")&"; ",""))-2))
A73: Samples to ship | B73: =COUNTIFS('Fragrance Projects'!$H$5:$H$64,"Evaluation",'Fragrance Projects'!$O$5:$O$64,"Us") -> 0 | C73: =IF(LEN(IF(LEN(IFERROR(INDEX('Fragrance Projects'!$D$5:$D$64,SUMPRODUCT(SMALL(IF((('Fragrance Projects'!$H$5:$H$64="Evaluation")*('Fragrance Projects'!$O$5:$O$64="Us")),ROW('Fragrance Projects'!$H$5:$H$64)-ROW(INDEX('Fragrance Projects'!$H$5:$H$64,1))+1),1))),""))>0,IFERROR(INDEX('Fragrance Projects'!$D$5:$D$64,SUMPRODUCT(SMALL(IF((('Fragrance Projects'!$H$5:$H$64="Evaluation")*('Fragrance Projects'!$O$5:$O$64="Us")),ROW('Fragrance Projects'!$H$5:$H$64)-ROW(INDEX('Fragrance Projects'!$H$5:$H$64,1))+1),1))),"")&"; ","")&IF(LEN(IFERROR(INDEX('Fragrance Projects'!$D$5:$D$64,SUMPRODUCT(SMALL(IF((('Fragrance Projects'!$H$5:$H$64="Evaluation")*('Fragrance Projects'!$O$5:$O$64="Us")),ROW('Fragrance Projects'!$H$5:$H$64)-ROW(INDEX('Fragrance Projects'!$H$5:$H$64,1))+1),2))),""))>0,IFERROR(INDEX('Fragrance Projects'!$D$5:$D$64,SUMPRODUCT(SMALL(IF((('Fragrance Projects'!$H$5:$H$64="Evaluation")*('Fragrance Projects'!$O$5:$O$64="Us")),ROW('Fragrance Projects'!$H$5:$H$64)-ROW(INDEX('Fragrance Projects'!$H$5:$H$64,1))+1),2))),"")&"; ","")&IF(LEN(IFERROR(INDEX('Fragrance Projects'!$D$5:$D$64,SUMPRODUCT(SMALL(IF((('Fragrance Projects'!$H$5:$H$64="Evaluation")*('Fragrance Projects'!$O$5:$O$64="Us")),ROW('Fragrance Projects'!$H$5:$H$64)-ROW(INDEX('Fragrance Projects'!$H$5:$H$64,1))+1),3))),""))>0,IFERROR(INDEX('Fragrance Projects'!$D$5:$D$64,SUMPRODUCT(SMALL(IF((('Fragrance Projects'!$H$5:$H$64="Evaluation")*('Fragrance Projects'!$O$5:$O$64="Us")),ROW('Fragrance Projects'!$H$5:$H$64)-ROW(INDEX('Fragrance Projects'!$H$5:$H$64,1))+1),3))),"")&"; ",""))=0,"",LEFT(IF(LEN(IFERROR(INDEX('Fragrance Projects'!$D$5:$D$64,SUMPRODUCT(SMALL(IF((('Fragrance Projects'!$H$5:$H$64="Evaluation")*('Fragrance Projects'!$O$5:$O$64="Us")),ROW('Fragrance Projects'!$H$5:$H$64)-ROW(INDEX('Fragrance Projects'!$H$5:$H$64,1))+1),1))),""))>0,IFERROR(INDEX('Fragrance Projects'!$D$5:$D$64,SUMPRODUCT(SMALL(IF((('Fragrance Projects'!$H$5:$H$64="Evaluation")*('Fragrance Projects'!$O$5:$O$64="Us")),ROW('Fragrance Projects'!$H$5:$H$64)-ROW(INDEX('Fragrance Projects'!$H$5:$H$64,1))+1),1))),"")&"; ","")&IF(LEN(IFERROR(INDEX('Fragrance Projects'!$D$5:$D$64,SUMPRODUCT(SMALL(IF((('Fragrance Projects'!$H$5:$H$64="Evaluation")*('Fragrance Projects'!$O$5:$O$64="Us")),ROW('Fragrance Projects'!$H$5:$H$64)-ROW(INDEX('Fragrance Projects'!$H$5:$H$64,1))+1),2))),""))>0,IFERROR(INDEX('Fragrance Projects'!$D$5:$D$64,SUMPRODUCT(SMALL(IF((('Fragrance Projects'!$H$5:$H$64="Evaluation")*('Fragrance Projects'!$O$5:$O$64="Us")),ROW('Fragrance Projects'!$H$5:$H$64)-ROW(INDEX('Fragrance Projects'!$H$5:$H$64,1))+1),2))),"")&"; ","")&IF(LEN(IFERROR(INDEX('Fragrance Projects'!$D$5:$D$64,SUMPRODUCT(SMALL(IF((('Fragrance Projects'!$H$5:$H$64="Evaluation")*('Fragrance Projects'!$O$5:$O$64="Us")),ROW('Fragrance Projects'!$H$5:$H$64)-ROW(INDEX('Fragrance Projects'!$H$5:$H$64,1))+1),3))),""))>0,IFERROR(INDEX('Fragrance Projects'!$D$5:$D$64,SUMPRODUCT(SMALL(IF((('Fragrance Projects'!$H$5:$H$64="Evaluation")*('Fragrance Projects'!$O$5:$O$64="Us")),ROW('Fragrance Projects'!$H$5:$H$64)-ROW(INDEX('Fragrance Projects'!$H$5:$H$64,1))+1),3))),"")&"; ",""),LEN(IF(LEN(IFERROR(INDEX('Fragrance Projects'!$D$5:$D$64,SUMPRODUCT(SMALL(IF((('Fragrance Projects'!$H$5:$H$64="Evaluation")*('Fragrance Projects'!$O$5:$O$64="Us")),ROW('Fragrance Projects'!$H$5:$H$64)-ROW(INDEX('Fragrance Projects'!$H$5:$H$64,1))+1),1))),""))>0,IFERROR(INDEX('Fragrance Projects'!$D$5:$D$64,SUMPRODUCT(SMALL(IF((('Fragrance Projects'!$H$5:$H$64="Evaluation")*('Fragrance Projects'!$O$5:$O$64="Us")),ROW('Fragrance Projects'!$H$5:$H$64)-ROW(INDEX('Fragrance Projects'!$H$5:$H$64,1))+1),1))),"")&"; ","")&IF(LEN(IFERROR(INDEX('Fragrance Projects'!$D$5:$D$64,SUMPRODUCT(SMALL(IF((('Fragrance Projects'!$H$5:$H$64="Evaluation")*('Fragrance Projects'!$O$5:$O$64="Us")),ROW('Fragrance Projects'!$H$5:$H$64)-ROW(INDEX('Fragrance Projects'!$H$5:$H$64,1))+1),2))),""))>0,IFERROR(INDEX('Fragrance Projects'!$D$5:$D$64,SUMPRODUCT(SMALL(IF((('Fragrance Projects'!$H$5:$H$64="Evaluation")*('Fragrance Projects'!$O$5:$O$64="Us")),ROW('Fragrance Projects'!$H$5:$H$64)-ROW(INDEX('Fragrance Projects'!$H$5:$H$64,1))+1),2))),"")&"; ","")&IF(LEN(IFERROR(INDEX('Fragrance Projects'!$D$5:$D$64,SUMPRODUCT(SMALL(IF((('Fragrance Projects'!$H$5:$H$64="Evaluation")*('Fragrance Projects'!$O$5:$O$64="Us")),ROW('Fragrance Projects'!$H$5:$H$64)-ROW(INDEX('Fragrance Projects'!$H$5:$H$64,1))+1),3))),""))>0,IFERROR(INDEX('Fragrance Projects'!$D$5:$D$64,SUMPRODUCT(SMALL(IF((('Fragrance Projects'!$H$5:$H$64="Evaluation")*('Fragrance Projects'!$O$5:$O$64="Us")),ROW('Fragrance Projects'!$H$5:$H$64)-ROW(INDEX('Fragrance Projects'!$H$5:$H$64,1))+1),3))),"")&"; ",""))-2))
A74: Client feedback to review | B74: =COUNTIFS('Fragrance Projects'!$H$5:$H$64,"Awaiting Feedback",'Fragrance Projects'!$O$5:$O$64,"Us") -> 0 | C74: =IF(LEN(IF(LEN(IFERROR(INDEX('Fragrance Projects'!$D$5:$D$64,SUMPRODUCT(SMALL(IF((('Fragrance Projects'!$H$5:$H$64="Awaiting Feedback")*('Fragrance Projects'!$O$5:$O$64="Us")),ROW('Fragrance Projects'!$H$5:$H$64)-ROW(INDEX('Fragrance Projects'!$H$5:$H$64,1))+1),1))),""))>0,IFERROR(INDEX('Fragrance Projects'!$D$5:$D$64,SUMPRODUCT(SMALL(IF((('Fragrance Projects'!$H$5:$H$64="Awaiting Feedback")*('Fragrance Projects'!$O$5:$O$64="Us")),ROW('Fragrance Projects'!$H$5:$H$64)-ROW(INDEX('Fragrance Projects'!$H$5:$H$64,1))+1),1))),"")&"; ","")&IF(LEN(IFERROR(INDEX('Fragrance Projects'!$D$5:$D$64,SUMPRODUCT(SMALL(IF((('Fragrance Projects'!$H$5:$H$64="Awaiting Feedback")*('Fragrance Projects'!$O$5:$O$64="Us")),ROW('Fragrance Projects'!$H$5:$H$64)-ROW(INDEX('Fragrance Projects'!$H$5:$H$64,1))+1),2))),""))>0,IFERROR(INDEX('Fragrance Projects'!$D$5:$D$64,SUMPRODUCT(SMALL(IF((('Fragrance Projects'!$H$5:$H$64="Awaiting Feedback")*('Fragrance Projects'!$O$5:$O$64="Us")),ROW('Fragrance Projects'!$H$5:$H$64)-ROW(INDEX('Fragrance Projects'!$H$5:$H$64,1))+1),2))),"")&"; ","")&IF(LEN(IFERROR(INDEX('Fragrance Projects'!$D$5:$D$64,SUMPRODUCT(SMALL(IF((('Fragrance Projects'!$H$5:$H$64="Awaiting Feedback")*('Fragrance Projects'!$O$5:$O$64="Us")),ROW('Fragrance Projects'!$H$5:$H$64)-ROW(INDEX('Fragrance Projects'!$H$5:$H$64,1))+1),3))),""))>0,IFERROR(INDEX('Fragrance Projects'!$D$5:$D$64,SUMPRODUCT(SMALL(IF((('Fragrance Projects'!$H$5:$H$64="Awaiting Feedback")*('Fragrance Projects'!$O$5:$O$64="Us")),ROW('Fragrance Projects'!$H$5:$H$64)-ROW(INDEX('Fragrance Projects'!$H$5:$H$64,1))+1),3))),"")&"; ",""))=0,"",LEFT(IF(LEN(IFERROR(INDEX('Fragrance Projects'!$D$5:$D$64,SUMPRODUCT(SMALL(IF((('Fragrance Projects'!$H$5:$H$64="Awaiting Feedback")*('Fragrance Projects'!$O$5:$O$64="Us")),ROW('Fragrance Projects'!$H$5:$H$64)-ROW(INDEX('Fragrance Projects'!$H$5:$H$64,1))+1),1))),""))>0,IFERROR(INDEX('Fragrance Projects'!$D$5:$D$64,SUMPRODUCT(SMALL(IF((('Fragrance Projects'!$H$5:$H$64="Awaiting Feedback")*('Fragrance Projects'!$O$5:$O$64="Us")),ROW('Fragrance Projects'!$H$5:$H$64)-ROW(INDEX('Fragrance Projects'!$H$5:$H$64,1))+1),1))),"")&"; ","")&IF(LEN(IFERROR(INDEX('Fragrance Projects'!$D$5:$D$64,SUMPRODUCT(SMALL(IF((('Fragrance Projects'!$H$5:$H$64="Awaiting Feedback")*('Fragrance Projects'!$O$5:$O$64="Us")),ROW('Fragrance Projects'!$H$5:$H$64)-ROW(INDEX('Fragrance Projects'!$H$5:$H$64,1))+1),2))),""))>0,IFERROR(INDEX('Fragrance Projects'!$D$5:$D$64,SUMPRODUCT(SMALL(IF((('Fragrance Projects'!$H$5:$H$64="Awaiting Feedback")*('Fragrance Projects'!$O$5:$O$64="Us")),ROW('Fragrance Projects'!$H$5:$H$64)-ROW(INDEX('Fragrance Projects'!$H$5:$H$64,1))+1),2))),"")&"; ","")&IF(LEN(IFERROR(INDEX('Fragrance Projects'!$D$5:$D$64,SUMPRODUCT(SMALL(IF((('Fragrance Projects'!$H$5:$H$64="Awaiting Feedback")*('Fragrance Projects'!$O$5:$O$64="Us")),ROW('Fragrance Projects'!$H$5:$H$64)-ROW(INDEX('Fragrance Projects'!$H$5:$H$64,1))+1),3))),""))>0,IFERROR(INDEX('Fragrance Projects'!$D$5:$D$64,SUMPRODUCT(SMALL(IF((('Fragrance Projects'!$H$5:$H$64="Awaiting Feedback")*('Fragrance Projects'!$O$5:$O$64="Us")),ROW('Fragrance Projects'!$H$5:$H$64)-ROW(INDEX('Fragrance Projects'!$H$5:$H$64,1))+1),3))),"")&"; ",""),LEN(IF(LEN(IFERROR(INDEX('Fragrance Projects'!$D$5:$D$64,SUMPRODUCT(SMALL(IF((('Fragrance Projects'!$H$5:$H$64="Awaiting Feedback")*('Fragrance Projects'!$O$5:$O$64="Us")),ROW('Fragrance Projects'!$H$5:$H$64)-ROW(INDEX('Fragrance Projects'!$H$5:$H$64,1))+1),1))),""))>0,IFERROR(INDEX('Fragrance Projects'!$D$5:$D$64,SUMPRODUCT(SMALL(IF((('Fragrance Projects'!$H$5:$H$64="Awaiting Feedback")*('Fragrance Projects'!$O$5:$O$64="Us")),ROW('Fragrance Projects'!$H$5:$H$64)-ROW(INDEX('Fragrance Projects'!$H$5:$H$64,1))+1),1))),"")&"; ","")&IF(LEN(IFERROR(INDEX('Fragrance Projects'!$D$5:$D$64,SUMPRODUCT(SMALL(IF((('Fragrance Projects'!$H$5:$H$64="Awaiting Feedback")*('Fragrance Projects'!$O$5:$O$64="Us")),ROW('Fragrance Projects'!$H$5:$H$64)-ROW(INDEX('Fragrance Projects'!$H$5:$H$64,1))+1),2))),""))>0,IFERROR(INDEX('Fragrance Projects'!$D$5:$D$64,SUMPRODUCT(SMALL(IF((('Fragrance Projects'!$H$5:$H$64="Awaiting Feedback")*('Fragrance Projects'!$O$5:$O$64="Us")),ROW('Fragrance Projects'!$H$5:$H$64)-ROW(INDEX('Fragrance Projects'!$H$5:$H$64,1))+1),2))),"")&"; ","")&IF(LEN(IFERROR(INDEX('Fragrance Projects'!$D$5:$D$64,SUMPRODUCT(SMALL(IF((('Fragrance Projects'!$H$5:$H$64="Awaiting Feedback")*('Fragrance Projects'!$O$5:$O$64="Us")),ROW('Fragrance Projects'!$H$5:$H$64)-ROW(INDEX('Fragrance Projects'!$H$5:$H$64,1))+1),3))),""))>0,IFERROR(INDEX('Fragrance Projects'!$D$5:$D$64,SUMPRODUCT(SMALL(IF((('Fragrance Projects'!$H$5:$H$64="Awaiting Feedback")*('Fragrance Projects'!$O$5:$O$64="Us")),ROW('Fragrance Projects'!$H$5:$H$64)-ROW(INDEX('Fragrance Projects'!$H$5:$H$64,1))+1),3))),"")&"; ",""))-2))
A75: Documentation to complete | B75: =COUNTIFS('Fragrance Projects'!$U$5:$U$64,"No",'Fragrance Projects'!$T$5:$T$64,"Yes") -> 0 | C75: =IF(LEN(IF(LEN(IFERROR(INDEX('Fragrance Projects'!$D$5:$D$64,SUMPRODUCT(SMALL(IF((('Fragrance Projects'!$U$5:$U$64="No")*('Fragrance Projects'!$T$5:$T$64="Yes")),ROW('Fragrance Projects'!$U$5:$U$64)-ROW(INDEX('Fragrance Projects'!$U$5:$U$64,1))+1),1))),""))>0,IFERROR(INDEX('Fragrance Projects'!$D$5:$D$64,SUMPRODUCT(SMALL(IF((('Fragrance Projects'!$U$5:$U$64="No")*('Fragrance Projects'!$T$5:$T$64="Yes")),ROW('Fragrance Projects'!$U$5:$U$64)-ROW(INDEX('Fragrance Projects'!$U$5:$U$64,1))+1),1))),"")&"; ","")&IF(LEN(IFERROR(INDEX('Fragrance Projects'!$D$5:$D$64,SUMPRODUCT(SMALL(IF((('Fragrance Projects'!$U$5:$U$64="No")*('Fragrance Projects'!$T$5:$T$64="Yes")),ROW('Fragrance Projects'!$U$5:$U$64)-ROW(INDEX('Fragrance Projects'!$U$5:$U$64,1))+1),2))),""))>0,IFERROR(INDEX('Fragrance Projects'!$D$5:$D$64,SUMPRODUCT(SMALL(IF((('Fragrance Projects'!$U$5:$U$64="No")*('Fragrance Projects'!$T$5:$T$64="Yes")),ROW('Fragrance Projects'!$U$5:$U$64)-ROW(INDEX('Fragrance Projects'!$U$5:$U$64,1))+1),2))),"")&"; ","")&IF(LEN(IFERROR(INDEX('Fragrance Projects'!$D$5:$D$64,SUMPRODUCT(SMALL(IF((('Fragrance Projects'!$U$5:$U$64="No")*('Fragrance Projects'!$T$5:$T$64="Yes")),ROW('Fragrance Projects'!$U$5:$U$64)-ROW(INDEX('Fragrance Projects'!$U$5:$U$64,1))+1),3))),""))>0,IFERROR(INDEX('Fragrance Projects'!$D$5:$D$64,SUMPRODUCT(SMALL(IF((('Fragrance Projects'!$U$5:$U$64="No")*('Fragrance Projects'!$T$5:$T$64="Yes")),ROW('Fragrance Projects'!$U$5:$U$64)-ROW(INDEX('Fragrance Projects'!$U$5:$U$64,1))+1),3))),"")&"; ",""))=0,"",LEFT(IF(LEN(IFERROR(INDEX('Fragrance Projects'!$D$5:$D$64,SUMPRODUCT(SMALL(IF((('Fragrance Projects'!$U$5:$U$64="No")*('Fragrance Projects'!$T$5:$T$64="Yes")),ROW('Fragrance Projects'!$U$5:$U$64)-ROW(INDEX('Fragrance Projects'!$U$5:$U$64,1))+1),1))),""))>0,IFERROR(INDEX('Fragrance Projects'!$D$5:$D$64,SUMPRODUCT(SMALL(IF((('Fragrance Projects'!$U$5:$U$64="No")*('Fragrance Projects'!$T$5:$T$64="Yes")),ROW('Fragrance Projects'!$U$5:$U$64)-ROW(INDEX('Fragrance Projects'!$U$5:$U$64,1))+1),1))),"")&"; ","")&IF(LEN(IFERROR(INDEX('Fragrance Projects'!$D$5:$D$64,SUMPRODUCT(SMALL(IF((('Fragrance Projects'!$U$5:$U$64="No")*('Fragrance Projects'!$T$5:$T$64="Yes")),ROW('Fragrance Projects'!$U$5:$U$64)-ROW(INDEX('Fragrance Projects'!$U$5:$U$64,1))+1),2))),""))>0,IFERROR(INDEX('Fragrance Projects'!$D$5:$D$64,SUMPRODUCT(SMALL(IF((('Fragrance Projects'!$U$5:$U$64="No")*('Fragrance Projects'!$T$5:$T$64="Yes")),ROW('Fragrance Projects'!$U$5:$U$64)-ROW(INDEX('Fragrance Projects'!$U$5:$U$64,1))+1),2))),"")&"; ","")&IF(LEN(IFERROR(INDEX('Fragrance Projects'!$D$5:$D$64,SUMPRODUCT(SMALL(IF((('Fragrance Projects'!$U$5:$U$64="No")*('Fragrance Projects'!$T$5:$T$64="Yes")),ROW('Fragrance Projects'!$U$5:$U$64)-ROW(INDEX('Fragrance Projects'!$U$5:$U$64,1))+1),3))),""))>0,IFERROR(INDEX('Fragrance Projects'!$D$5:$D$64,SUMPRODUCT(SMALL(IF((('Fragrance Projects'!$U$5:$U$64="No")*('Fragrance Projects'!$T$5:$T$64="Yes")),ROW('Fragrance Projects'!$U$5:$U$64)-ROW(INDEX('Fragrance Projects'!$U$5:$U$64,1))+1),3))),"")&"; ",""),LEN(IF(LEN(IFERROR(INDEX('Fragrance Projects'!$D$5:$D$64,SUMPRODUCT(SMALL(IF((('Fragrance Projects'!$U$5:$U$64="No")*('Fragrance Projects'!$T$5:$T$64="Yes")),ROW('Fragrance Projects'!$U$5:$U$64)-ROW(INDEX('Fragrance Projects'!$U$5:$U$64,1))+1),1))),""))>0,IFERROR(INDEX('Fragrance Projects'!$D$5:$D$64,SUMPRODUCT(SMALL(IF((('Fragrance Projects'!$U$5:$U$64="No")*('Fragrance Projects'!$T$5:$T$64="Yes")),ROW('Fragrance Projects'!$U$5:$U$64)-ROW(INDEX('Fragrance Projects'!$U$5:$U$64,1))+1),1))),"")&"; ","")&IF(LEN(IFERROR(INDEX('Fragrance Projects'!$D$5:$D$64,SUMPRODUCT(SMALL(IF((('Fragrance Projects'!$U$5:$U$64="No")*('Fragrance Projects'!$T$5:$T$64="Yes")),ROW('Fragrance Projects'!$U$5:$U$64)-ROW(INDEX('Fragrance Projects'!$U$5:$U$64,1))+1),2))),""))>0,IFERROR(INDEX('Fragrance Projects'!$D$5:$D$64,SUMPRODUCT(SMALL(IF((('Fragrance Projects'!$U$5:$U$64="No")*('Fragrance Projects'!$T$5:$T$64="Yes")),ROW('Fragrance Projects'!$U$5:$U$64)-ROW(INDEX('Fragrance Projects'!$U$5:$U$64,1))+1),2))),"")&"; ","")&IF(LEN(IFERROR(INDEX('Fragrance Projects'!$D$5:$D$64,SUMPRODUCT(SMALL(IF((('Fragrance Projects'!$U$5:$U$64="No")*('Fragrance Projects'!$T$5:$T$64="Yes")),ROW('Fragrance Projects'!$U$5:$U$64)-ROW(INDEX('Fragrance Projects'!$U$5:$U$64,1))+1),3))),""))>0,IFERROR(INDEX('Fragrance Projects'!$D$5:$D$64,SUMPRODUCT(SMALL(IF((('Fragrance Projects'!$U$5:$U$64="No")*('Fragrance Projects'!$T$5:$T$64="Yes")),ROW('Fragrance Projects'!$U$5:$U$64)-ROW(INDEX('Fragrance Projects'!$U$5:$U$64,1))+1),3))),"")&"; ",""))-2))
A76: Payments to chase | B76: =COUNTIF(Payments!$N$5:$N$64,"Overdue")+COUNTIF(Payments!$N$5:$N$64,"Awaiting Deposit") -> 0 | C76: =IF(LEN(IF(LEN(IFERROR(INDEX(Payments!$A$5:$A$64,SUMPRODUCT(SMALL(IF((((Payments!$N$5:$N$64="Overdue")+(Payments!$N$5:$N$64="Awaiting Deposit"))),ROW(Payments!$N$5:$N$64)-ROW(INDEX(Payments!$N$5:$N$64,1))+1),1))),""))>0,IFERROR(INDEX(Payments!$A$5:$A$64,SUMPRODUCT(SMALL(IF((((Payments!$N$5:$N$64="Overdue")+(Payments!$N$5:$N$64="Awaiting Deposit"))),ROW(Payments!$N$5:$N$64)-ROW(INDEX(Payments!$N$5:$N$64,1))+1),1))),"")&"; ","")&IF(LEN(IFERROR(INDEX(Payments!$A$5:$A$64,SUMPRODUCT(SMALL(IF((((Payments!$N$5:$N$64="Overdue")+(Payments!$N$5:$N$64="Awaiting Deposit"))),ROW(Payments!$N$5:$N$64)-ROW(INDEX(Payments!$N$5:$N$64,1))+1),2))),""))>0,IFERROR(INDEX(Payments!$A$5:$A$64,SUMPRODUCT(SMALL(IF((((Payments!$N$5:$N$64="Overdue")+(Payments!$N$5:$N$64="Awaiting Deposit"))),ROW(Payments!$N$5:$N$64)-ROW(INDEX(Payments!$N$5:$N$64,1))+1),2))),"")&"; ","")&IF(LEN(IFERROR(INDEX(Payments!$A$5:$A$64,SUMPRODUCT(SMALL(IF((((Payments!$N$5:$N$64="Overdue")+(Payments!$N$5:$N$64="Awaiting Deposit"))),ROW(Payments!$N$5:$N$64)-ROW(INDEX(Payments!$N$5:$N$64,1))+1),3))),""))>0,IFERROR(INDEX(Payments!$A$5:$A$64,SUMPRODUCT(SMALL(IF((((Payments!$N$5:$N$64="Overdue")+(Payments!$N$5:$N$64="Awaiting Deposit"))),ROW(Payments!$N$5:$N$64)-ROW(INDEX(Payments!$N$5:$N$64,1))+1),3))),"")&"; ",""))=0,"",LEFT(IF(LEN(IFERROR(INDEX(Payments!$A$5:$A$64,SUMPRODUCT(SMALL(IF((((Payments!$N$5:$N$64="Overdue")+(Payments!$N$5:$N$64="Awaiting Deposit"))),ROW(Payments!$N$5:$N$64)-ROW(INDEX(Payments!$N$5:$N$64,1))+1),1))),""))>0,IFERROR(INDEX(Payments!$A$5:$A$64,SUMPRODUCT(SMALL(IF((((Payments!$N$5:$N$64="Overdue")+(Payments!$N$5:$N$64="Awaiting Deposit"))),ROW(Payments!$N$5:$N$64)-ROW(INDEX(Payments!$N$5:$N$64,1))+1),1))),"")&"; ","")&IF(LEN(IFERROR(INDEX(Payments!$A$5:$A$64,SUMPRODUCT(SMALL(IF((((Payments!$N$5:$N$64="Overdue")+(Payments!$N$5:$N$64="Awaiting Deposit"))),ROW(Payments!$N$5:$N$64)-ROW(INDEX(Payments!$N$5:$N$64,1))+1),2))),""))>0,IFERROR(INDEX(Payments!$A$5:$A$64,SUMPRODUCT(SMALL(IF((((Payments!$N$5:$N$64="Overdue")+(Payments!$N$5:$N$64="Awaiting Deposit"))),ROW(Payments!$N$5:$N$64)-ROW(INDEX(Payments!$N$5:$N$64,1))+1),2))),"")&"; ","")&IF(LEN(IFERROR(INDEX(Payments!$A$5:$A$64,SUMPRODUCT(SMALL(IF((((Payments!$N$5:$N$64="Overdue")+(Payments!$N$5:$N$64="Awaiting Deposit"))),ROW(Payments!$N$5:$N$64)-ROW(INDEX(Payments!$N$5:$N$64,1))+1),3))),""))>0,IFERROR(INDEX(Payments!$A$5:$A$64,SUMPRODUCT(SMALL(IF((((Payments!$N$5:$N$64="Overdue")+(Payments!$N$5:$N$64="Awaiting Deposit"))),ROW(Payments!$N$5:$N$64)-ROW(INDEX(Payments!$N$5:$N$64,1))+1),3))),"")&"; ",""),LEN(IF(LEN(IFERROR(INDEX(Payments!$A$5:$A$64,SUMPRODUCT(SMALL(IF((((Payments!$N$5:$N$64="Overdue")+(Payments!$N$5:$N$64="Awaiting Deposit"))),ROW(Payments!$N$5:$N$64)-ROW(INDEX(Payments!$N$5:$N$64,1))+1),1))),""))>0,IFERROR(INDEX(Payments!$A$5:$A$64,SUMPRODUCT(SMALL(IF((((Payments!$N$5:$N$64="Overdue")+(Payments!$N$5:$N$64="Awaiting Deposit"))),ROW(Payments!$N$5:$N$64)-ROW(INDEX(Payments!$N$5:$N$64,1))+1),1))),"")&"; ","")&IF(LEN(IFERROR(INDEX(Payments!$A$5:$A$64,SUMPRODUCT(SMALL(IF((((Payments!$N$5:$N$64="Overdue")+(Payments!$N$5:$N$64="Awaiting Deposit"))),ROW(Payments!$N$5:$N$64)-ROW(INDEX(Payments!$N$5:$N$64,1))+1),2))),""))>0,IFERROR(INDEX(Payments!$A$5:$A$64,SUMPRODUCT(SMALL(IF((((Payments!$N$5:$N$64="Overdue")+(Payments!$N$5:$N$64="Awaiting Deposit"))),ROW(Payments!$N$5:$N$64)-ROW(INDEX(Payments!$N$5:$N$64,1))+1),2))),"")&"; ","")&IF(LEN(IFERROR(INDEX(Payments!$A$5:$A$64,SUMPRODUCT(SMALL(IF((((Payments!$N$5:$N$64="Overdue")+(Payments!$N$5:$N$64="Awaiting Deposit"))),ROW(Payments!$N$5:$N$64)-ROW(INDEX(Payments!$N$5:$N$64,1))+1),3))),""))>0,IFERROR(INDEX(Payments!$A$5:$A$64,SUMPRODUCT(SMALL(IF((((Payments!$N$5:$N$64="Overdue")+(Payments!$N$5:$N$64="Awaiting Deposit"))),ROW(Payments!$N$5:$N$64)-ROW(INDEX(Payments!$N$5:$N$64,1))+1),3))),"")&"; ",""))-2))

Sheet Client Risk
A1: CLIENT RISK — Watch List
A2: Answer the judgement-call questions; Contract/Deposit/Ownership/Budget/Margin/Payment are pulled in automatically. Risk Level and Attention Required are calculated.
B3: INPUT — type or choose here | F3: CALCULATED — formula, do not edit | J3: AUTO-LOOKUP — pulled from another sheet
A4: Project ID | B4: Client | C4: Fragrance | D4: Scope Clearly Defined? | E4: Brief Clear? | F4: Contract Signed? | G4: Deposit Paid? | H4: No. of Revisions Agreed | I4: Formula Ownership Agreed? | J4: Deadline Realistic? | K4: Client Responds Promptly? | L4: Client Frequently Changes Brief? | M4: Additional Work Requested? | N4: Project Exceeding Expected Hours? | O4: Expenses Exceeding Budget? | P4: Margin Becoming Too Low? | Q4: Payment Overdue? | R4: Scope Creep? | S4: Compliance Requirements Understood? | T4: Manufacturing Responsibility Clear? | U4: Risk Level | V4: Attention Required
B5: =IF($A5="","",IFERROR(INDEX('Fragrance Projects'!$C$5:$C$64,MATCH($A5,'Fragrance Projects'!$A$5:$A$64,0)),"")) | C5: =IF($A5="","",IFERROR(INDEX('Fragrance Projects'!$D$5:$D$64,MATCH($A5,'Fragrance Projects'!$A$5:$A$64,0)),"")) | F5: =IF($A5="","",IFERROR(INDEX(Clients!$R$5:$R$44,MATCH($W5,Clients!$A$5:$A$44,0)),"")) | G5: =IF($A5="","",IF(IFERROR(INDEX(Payments!$G$5:$G$64,MATCH($A5,Payments!$B$5:$B$64,0)),0)>0,"Yes","No")) | H5: =IF($A5="","",IFERROR(INDEX('Fragrance Projects'!$L$5:$L$64,MATCH($A5,'Fragrance Projects'!$A$5:$A$64,0)),"")) | I5: =IF($A5="","",IF(AND(IFERROR(INDEX(Clients!$T$5:$T$44,MATCH($W5,Clients!$A$5:$A$44,0)),"")<>"",IFERROR(INDEX(Clients!$T$5:$T$44,MATCH($W5,Clients!$A$5:$A$44,0)),"")<>"Not Yet Agreed"),"Yes","No")) | O5: =IF($A5="","",IF(AND($Y5<>"",$Y5>0,$X5>0.4*$Y5),"Yes","No")) | P5: =IF($A5="","",IF(AND($Z5<>"",$Z5<0.15),"Yes","No")) | Q5: =IF($A5="","",IF($AA5="Overdue","Yes","No")) | U5: =IF($A5="","",_xlfn.IFS((IF($D5="No",1,0)+IF($E5="No",1,0)+IF($F5="No",1,0)+IF($G5="No",1,0)+IF($I5="No",1,0)+IF($J5="No",1,0)+IF($K5="No",1,0)+IF($L5="Yes",1,0)+IF($M5="Yes",1,0)+IF($N5="Yes",1,0)+IF($O5="Yes",1,0)+IF($P5="Yes",1,0)+IF($Q5="Yes",1,0)+IF($R5="Yes",1,0)+IF($S5="No",1,0)+IF($T5="No",1,0))<=2,"LOW",(IF($D5="No",1,0)+IF($E5="No",1,0)+IF($F5="No",1,0)+IF($G5="No",1,0)+IF($I5="No",1,0)+IF($J5="No",1,0)+IF($K5="No",1,0)+IF($L5="Yes",1,0)+IF($M5="Yes",1,0)+IF($N5="Yes",1,0)+IF($O5="Yes",1,0)+IF($P5="Yes",1,0)+IF($Q5="Yes",1,0)+IF($R5="Yes",1,0)+IF($S5="No",1,0)+IF($T5="No",1,0))<=5,"MEDIUM",TRUE(),"HIGH")) | V5: =IF($A5="","",IF(LEN(IF($D5="No","Scope undefined; ","")&IF($E5="No","Brief unclear; ","")&IF($F5="No","Contract not signed; ","")&IF($G5="No","Deposit unpaid; ","")&IF($I5="No","Ownership not agreed; ","")&IF($J5="No","Deadline unrealistic; ","")&IF($K5="No","Slow client response; ","")&IF($L5="Yes","Brief keeps changing; ","")&IF($M5="Yes","Extra work requested; ","")&IF($N5="Yes","Exceeding expected hours; ","")&IF($O5="Yes","Expenses over budget; ","")&IF($P5="Yes","Margin too low; ","")&IF($Q5="Yes","Payment overdue; ","")&IF($R5="Yes","Scope creep; ","")&IF($S5="No","Compliance unclear; ","")&IF($T5="No","Manufacturing handover unclear; ",""))=0,"None — healthy",LEFT(IF($D5="No","Scope undefined; ","")&IF($E5="No","Brief unclear; ","")&IF($F5="No","Contract not signed; ","")&IF($G5="No","Deposit unpaid; ","")&IF($I5="No","Ownership not agreed; ","")&IF($J5="No","Deadline unrealistic; ","")&IF($K5="No","Slow client response; ","")&IF($L5="Yes","Brief keeps changing; ","")&IF($M5="Yes","Extra work requested; ","")&IF($N5="Yes","Exceeding expected hours; ","")&IF($O5="Yes","Expenses over budget; ","")&IF($P5="Yes","Margin too low; ","")&IF($Q5="Yes","Payment overdue; ","")&IF($R5="Yes","Scope creep; ","")&IF($S5="No","Compliance unclear; ","")&IF($T5="No","Manufacturing handover unclear; ",""),LEN(IF($D5="No","Scope undefined; ","")&IF($E5="No","Brief unclear; ","")&IF($F5="No","Contract not signed; ","")&IF($G5="No","Deposit unpaid; ","")&IF($I5="No","Ownership not agreed; ","")&IF($J5="No","Deadline unrealistic; ","")&IF($K5="No","Slow client response; ","")&IF($L5="Yes","Brief keeps changing; ","")&IF($M5="Yes","Extra work requested; ","")&IF($N5="Yes","Exceeding expected hours; ","")&IF($O5="Yes","Expenses over budget; ","")&IF($P5="Yes","Margin too low; ","")&IF($Q5="Yes","Payment overdue; ","")&IF($R5="Yes","Scope creep; ","")&IF($S5="No","Compliance unclear; ","")&IF($T5="No","Manufacturing handover unclear; ",""))-2))) | W5: =IF($A5="","",IFERROR(INDEX('Fragrance Projects'!$B$5:$B$64,MATCH($A5,'Fragrance Projects'!$A$5:$A$64,0)),"")) | X5: =IF($A5="","",IFERROR(INDEX('Project Financials'!$U$5:$U$64,MATCH($A5,'Project Financials'!$A$5:$A$64,0)),"")) | Y5: =IF($A5="","",IFERROR(INDEX('Project Financials'!$D$5:$D$64,MATCH($A5,'Project Financials'!$A$5:$A$64,0)),"")) | Z5: =IF($A5="","",IFERROR(INDEX('Project Financials'!$AC$5:$AC$64,MATCH($A5,'Project Financials'!$A$5:$A$64,0)),"")) | AA5: =IF($A5="","",IFERROR(INDEX(Payments!$N$5:$N$64,MATCH($A5,Payments!$B$5:$B$64,0)),""))
B6: =IF($A6="","",IFERROR(INDEX('Fragrance Projects'!$C$5:$C$64,MATCH($A6,'Fragrance Projects'!$A$5:$A$64,0)),"")) | C6: =IF($A6="","",IFERROR(INDEX('Fragrance Projects'!$D$5:$D$64,MATCH($A6,'Fragrance Projects'!$A$5:$A$64,0)),"")) | F6: =IF($A6="","",IFERROR(INDEX(Clients!$R$5:$R$44,MATCH($W6,Clients!$A$5:$A$44,0)),"")) | G6: =IF($A6="","",IF(IFERROR(INDEX(Payments!$G$5:$G$64,MATCH($A6,Payments!$B$5:$B$64,0)),0)>0,"Yes","No")) | H6: =IF($A6="","",IFERROR(INDEX('Fragrance Projects'!$L$5:$L$64,MATCH($A6,'Fragrance Projects'!$A$5:$A$64,0)),"")) | I6: =IF($A6="","",IF(AND(IFERROR(INDEX(Clients!$T$5:$T$44,MATCH($W6,Clients!$A$5:$A$44,0)),"")<>"",IFERROR(INDEX(Clients!$T$5:$T$44,MATCH($W6,Clients!$A$5:$A$44,0)),"")<>"Not Yet Agreed"),"Yes","No")) | O6: =IF($A6="","",IF(AND($Y6<>"",$Y6>0,$X6>0.4*$Y6),"Yes","No")) | P6: =IF($A6="","",IF(AND($Z6<>"",$Z6<0.15),"Yes","No")) | Q6: =IF($A6="","",IF($AA6="Overdue","Yes","No")) | U6: =IF($A6="","",_xlfn.IFS((IF($D6="No",1,0)+IF($E6="No",1,0)+IF($F6="No",1,0)+IF($G6="No",1,0)+IF($I6="No",1,0)+IF($J6="No",1,0)+IF($K6="No",1,0)+IF($L6="Yes",1,0)+IF($M6="Yes",1,0)+IF($N6="Yes",1,0)+IF($O6="Yes",1,0)+IF($P6="Yes",1,0)+IF($Q6="Yes",1,0)+IF($R6="Yes",1,0)+IF($S6="No",1,0)+IF($T6="No",1,0))<=2,"LOW",(IF($D6="No",1,0)+IF($E6="No",1,0)+IF($F6="No",1,0)+IF($G6="No",1,0)+IF($I6="No",1,0)+IF($J6="No",1,0)+IF($K6="No",1,0)+IF($L6="Yes",1,0)+IF($M6="Yes",1,0)+IF($N6="Yes",1,0)+IF($O6="Yes",1,0)+IF($P6="Yes",1,0)+IF($Q6="Yes",1,0)+IF($R6="Yes",1,0)+IF($S6="No",1,0)+IF($T6="No",1,0))<=5,"MEDIUM",TRUE(),"HIGH")) | V6: =IF($A6="","",IF(LEN(IF($D6="No","Scope undefined; ","")&IF($E6="No","Brief unclear; ","")&IF($F6="No","Contract not signed; ","")&IF($G6="No","Deposit unpaid; ","")&IF($I6="No","Ownership not agreed; ","")&IF($J6="No","Deadline unrealistic; ","")&IF($K6="No","Slow client response; ","")&IF($L6="Yes","Brief keeps changing; ","")&IF($M6="Yes","Extra work requested; ","")&IF($N6="Yes","Exceeding expected hours; ","")&IF($O6="Yes","Expenses over budget; ","")&IF($P6="Yes","Margin too low; ","")&IF($Q6="Yes","Payment overdue; ","")&IF($R6="Yes","Scope creep; ","")&IF($S6="No","Compliance unclear; ","")&IF($T6="No","Manufacturing handover unclear; ",""))=0,"None — healthy",LEFT(IF($D6="No","Scope undefined; ","")&IF($E6="No","Brief unclear; ","")&IF($F6="No","Contract not signed; ","")&IF($G6="No","Deposit unpaid; ","")&IF($I6="No","Ownership not agreed; ","")&IF($J6="No","Deadline unrealistic; ","")&IF($K6="No","Slow client response; ","")&IF($L6="Yes","Brief keeps changing; ","")&IF($M6="Yes","Extra work requested; ","")&IF($N6="Yes","Exceeding expected hours; ","")&IF($O6="Yes","Expenses over budget; ","")&IF($P6="Yes","Margin too low; ","")&IF($Q6="Yes","Payment overdue; ","")&IF($R6="Yes","Scope creep; ","")&IF($S6="No","Compliance unclear; ","")&IF($T6="No","Manufacturing handover unclear; ",""),LEN(IF($D6="No","Scope undefined; ","")&IF($E6="No","Brief unclear; ","")&IF($F6="No","Contract not signed; ","")&IF($G6="No","Deposit unpaid; ","")&IF($I6="No","Ownership not agreed; ","")&IF($J6="No","Deadline unrealistic; ","")&IF($K6="No","Slow client response; ","")&IF($L6="Yes","Brief keeps changing; ","")&IF($M6="Yes","Extra work requested; ","")&IF($N6="Yes","Exceeding expected hours; ","")&IF($O6="Yes","Expenses over budget; ","")&IF($P6="Yes","Margin too low; ","")&IF($Q6="Yes","Payment overdue; ","")&IF($R6="Yes","Scope creep; ","")&IF($S6="No","Compliance unclear; ","")&IF($T6="No","Manufacturing handover unclear; ",""))-2))) | W6: =IF($A6="","",IFERROR(INDEX('Fragrance Projects'!$B$5:$B$64,MATCH($A6,'Fragrance Projects'!$A$5:$A$64,0)),"")) | X6: =IF($A6="","",IFERROR(INDEX('Project Financials'!$U$5:$U$64,MATCH($A6,'Project Financials'!$A$5:$A$64,0)),"")) | Y6: =IF($A6="","",IFERROR(INDEX('Project Financials'!$D$5:$D$64,MATCH($A6,'Project Financials'!$A$5:$A$64,0)),"")) | Z6: =IF($A6="","",IFERROR(INDEX('Project Financials'!$AC$5:$AC$64,MATCH($A6,'Project Financials'!$A$5:$A$64,0)),"")) | AA6: =IF($A6="","",IFERROR(INDEX(Payments!$N$5:$N$64,MATCH($A6,Payments!$B$5:$B$64,0)),""))
B7: =IF($A7="","",IFERROR(INDEX('Fragrance Projects'!$C$5:$C$64,MATCH($A7,'Fragrance Projects'!$A$5:$A$64,0)),"")) | C7: =IF($A7="","",IFERROR(INDEX('Fragrance Projects'!$D$5:$D$64,MATCH($A7,'Fragrance Projects'!$A$5:$A$64,0)),"")) | F7: =IF($A7="","",IFERROR(INDEX(Clients!$R$5:$R$44,MATCH($W7,Clients!$A$5:$A$44,0)),"")) | G7: =IF($A7="","",IF(IFERROR(INDEX(Payments!$G$5:$G$64,MATCH($A7,Payments!$B$5:$B$64,0)),0)>0,"Yes","No")) | H7: =IF($A7="","",IFERROR(INDEX('Fragrance Projects'!$L$5:$L$64,MATCH($A7,'Fragrance Projects'!$A$5:$A$64,0)),"")) | I7: =IF($A7="","",IF(AND(IFERROR(INDEX(Clients!$T$5:$T$44,MATCH($W7,Clients!$A$5:$A$44,0)),"")<>"",IFERROR(INDEX(Clients!$T$5:$T$44,MATCH($W7,Clients!$A$5:$A$44,0)),"")<>"Not Yet Agreed"),"Yes","No")) | O7: =IF($A7="","",IF(AND($Y7<>"",$Y7>0,$X7>0.4*$Y7),"Yes","No")) | P7: =IF($A7="","",IF(AND($Z7<>"",$Z7<0.15),"Yes","No")) | Q7: =IF($A7="","",IF($AA7="Overdue","Yes","No")) | U7: =IF($A7="","",_xlfn.IFS((IF($D7="No",1,0)+IF($E7="No",1,0)+IF($F7="No",1,0)+IF($G7="No",1,0)+IF($I7="No",1,0)+IF($J7="No",1,0)+IF($K7="No",1,0)+IF($L7="Yes",1,0)+IF($M7="Yes",1,0)+IF($N7="Yes",1,0)+IF($O7="Yes",1,0)+IF($P7="Yes",1,0)+IF($Q7="Yes",1,0)+IF($R7="Yes",1,0)+IF($S7="No",1,0)+IF($T7="No",1,0))<=2,"LOW",(IF($D7="No",1,0)+IF($E7="No",1,0)+IF($F7="No",1,0)+IF($G7="No",1,0)+IF($I7="No",1,0)+IF($J7="No",1,0)+IF($K7="No",1,0)+IF($L7="Yes",1,0)+IF($M7="Yes",1,0)+IF($N7="Yes",1,0)+IF($O7="Yes",1,0)+IF($P7="Yes",1,0)+IF($Q7="Yes",1,0)+IF($R7="Yes",1,0)+IF($S7="No",1,0)+IF($T7="No",1,0))<=5,"MEDIUM",TRUE(),"HIGH")) | V7: =IF($A7="","",IF(LEN(IF($D7="No","Scope undefined; ","")&IF($E7="No","Brief unclear; ","")&IF($F7="No","Contract not signed; ","")&IF($G7="No","Deposit unpaid; ","")&IF($I7="No","Ownership not agreed; ","")&IF($J7="No","Deadline unrealistic; ","")&IF($K7="No","Slow client response; ","")&IF($L7="Yes","Brief keeps changing; ","")&IF($M7="Yes","Extra work requested; ","")&IF($N7="Yes","Exceeding expected hours; ","")&IF($O7="Yes","Expenses over budget; ","")&IF($P7="Yes","Margin too low; ","")&IF($Q7="Yes","Payment overdue; ","")&IF($R7="Yes","Scope creep; ","")&IF($S7="No","Compliance unclear; ","")&IF($T7="No","Manufacturing handover unclear; ",""))=0,"None — healthy",LEFT(IF($D7="No","Scope undefined; ","")&IF($E7="No","Brief unclear; ","")&IF($F7="No","Contract not signed; ","")&IF($G7="No","Deposit unpaid; ","")&IF($I7="No","Ownership not agreed; ","")&IF($J7="No","Deadline unrealistic; ","")&IF($K7="No","Slow client response; ","")&IF($L7="Yes","Brief keeps changing; ","")&IF($M7="Yes","Extra work requested; ","")&IF($N7="Yes","Exceeding expected hours; ","")&IF($O7="Yes","Expenses over budget; ","")&IF($P7="Yes","Margin too low; ","")&IF($Q7="Yes","Payment overdue; ","")&IF($R7="Yes","Scope creep; ","")&IF($S7="No","Compliance unclear; ","")&IF($T7="No","Manufacturing handover unclear; ",""),LEN(IF($D7="No","Scope undefined; ","")&IF($E7="No","Brief unclear; ","")&IF($F7="No","Contract not signed; ","")&IF($G7="No","Deposit unpaid; ","")&IF($I7="No","Ownership not agreed; ","")&IF($J7="No","Deadline unrealistic; ","")&IF($K7="No","Slow client response; ","")&IF($L7="Yes","Brief keeps changing; ","")&IF($M7="Yes","Extra work requested; ","")&IF($N7="Yes","Exceeding expected hours; ","")&IF($O7="Yes","Expenses over budget; ","")&IF($P7="Yes","Margin too low; ","")&IF($Q7="Yes","Payment overdue; ","")&IF($R7="Yes","Scope creep; ","")&IF($S7="No","Compliance unclear; ","")&IF($T7="No","Manufacturing handover unclear; ",""))-2))) | W7: =IF($A7="","",IFERROR(INDEX('Fragrance Projects'!$B$5:$B$64,MATCH($A7,'Fragrance Projects'!$A$5:$A$64,0)),"")) | X7: =IF($A7="","",IFERROR(INDEX('Project Financials'!$U$5:$U$64,MATCH($A7,'Project Financials'!$A$5:$A$64,0)),"")) | Y7: =IF($A7="","",IFERROR(INDEX('Project Financials'!$D$5:$D$64,MATCH($A7,'Project Financials'!$A$5:$A$64,0)),"")) | Z7: =IF($A7="","",IFERROR(INDEX('Project Financials'!$AC$5:$AC$64,MATCH($A7,'Project Financials'!$A$5:$A$64,0)),"")) | AA7: =IF($A7="","",IFERROR(INDEX(Payments!$N$5:$N$64,MATCH($A7,Payments!$B$5:$B$64,0)),""))
B8: =IF($A8="","",IFERROR(INDEX('Fragrance Projects'!$C$5:$C$64,MATCH($A8,'Fragrance Projects'!$A$5:$A$64,0)),"")) | C8: =IF($A8="","",IFERROR(INDEX('Fragrance Projects'!$D$5:$D$64,MATCH($A8,'Fragrance Projects'!$A$5:$A$64,0)),"")) | F8: =IF($A8="","",IFERROR(INDEX(Clients!$R$5:$R$44,MATCH($W8,Clients!$A$5:$A$44,0)),"")) | G8: =IF($A8="","",IF(IFERROR(INDEX(Payments!$G$5:$G$64,MATCH($A8,Payments!$B$5:$B$64,0)),0)>0,"Yes","No")) | H8: =IF($A8="","",IFERROR(INDEX('Fragrance Projects'!$L$5:$L$64,MATCH($A8,'Fragrance Projects'!$A$5:$A$64,0)),"")) | I8: =IF($A8="","",IF(AND(IFERROR(INDEX(Clients!$T$5:$T$44,MATCH($W8,Clients!$A$5:$A$44,0)),"")<>"",IFERROR(INDEX(Clients!$T$5:$T$44,MATCH($W8,Clients!$A$5:$A$44,0)),"")<>"Not Yet Agreed"),"Yes","No")) | O8: =IF($A8="","",IF(AND($Y8<>"",$Y8>0,$X8>0.4*$Y8),"Yes","No")) | P8: =IF($A8="","",IF(AND($Z8<>"",$Z8<0.15),"Yes","No")) | Q8: =IF($A8="","",IF($AA8="Overdue","Yes","No")) | U8: =IF($A8="","",_xlfn.IFS((IF($D8="No",1,0)+IF($E8="No",1,0)+IF($F8="No",1,0)+IF($G8="No",1,0)+IF($I8="No",1,0)+IF($J8="No",1,0)+IF($K8="No",1,0)+IF($L8="Yes",1,0)+IF($M8="Yes",1,0)+IF($N8="Yes",1,0)+IF($O8="Yes",1,0)+IF($P8="Yes",1,0)+IF($Q8="Yes",1,0)+IF($R8="Yes",1,0)+IF($S8="No",1,0)+IF($T8="No",1,0))<=2,"LOW",(IF($D8="No",1,0)+IF($E8="No",1,0)+IF($F8="No",1,0)+IF($G8="No",1,0)+IF($I8="No",1,0)+IF($J8="No",1,0)+IF($K8="No",1,0)+IF($L8="Yes",1,0)+IF($M8="Yes",1,0)+IF($N8="Yes",1,0)+IF($O8="Yes",1,0)+IF($P8="Yes",1,0)+IF($Q8="Yes",1,0)+IF($R8="Yes",1,0)+IF($S8="No",1,0)+IF($T8="No",1,0))<=5,"MEDIUM",TRUE(),"HIGH")) | V8: =IF($A8="","",IF(LEN(IF($D8="No","Scope undefined; ","")&IF($E8="No","Brief unclear; ","")&IF($F8="No","Contract not signed; ","")&IF($G8="No","Deposit unpaid; ","")&IF($I8="No","Ownership not agreed; ","")&IF($J8="No","Deadline unrealistic; ","")&IF($K8="No","Slow client response; ","")&IF($L8="Yes","Brief keeps changing; ","")&IF($M8="Yes","Extra work requested; ","")&IF($N8="Yes","Exceeding expected hours; ","")&IF($O8="Yes","Expenses over budget; ","")&IF($P8="Yes","Margin too low; ","")&IF($Q8="Yes","Payment overdue; ","")&IF($R8="Yes","Scope creep; ","")&IF($S8="No","Compliance unclear; ","")&IF($T8="No","Manufacturing handover unclear; ",""))=0,"None — healthy",LEFT(IF($D8="No","Scope undefined; ","")&IF($E8="No","Brief unclear; ","")&IF($F8="No","Contract not signed; ","")&IF($G8="No","Deposit unpaid; ","")&IF($I8="No","Ownership not agreed; ","")&IF($J8="No","Deadline unrealistic; ","")&IF($K8="No","Slow client response; ","")&IF($L8="Yes","Brief keeps changing; ","")&IF($M8="Yes","Extra work requested; ","")&IF($N8="Yes","Exceeding expected hours; ","")&IF($O8="Yes","Expenses over budget; ","")&IF($P8="Yes","Margin too low; ","")&IF($Q8="Yes","Payment overdue; ","")&IF($R8="Yes","Scope creep; ","")&IF($S8="No","Compliance unclear; ","")&IF($T8="No","Manufacturing handover unclear; ",""),LEN(IF($D8="No","Scope undefined; ","")&IF($E8="No","Brief unclear; ","")&IF($F8="No","Contract not signed; ","")&IF($G8="No","Deposit unpaid; ","")&IF($I8="No","Ownership not agreed; ","")&IF($J8="No","Deadline unrealistic; ","")&IF($K8="No","Slow client response; ","")&IF($L8="Yes","Brief keeps changing; ","")&IF($M8="Yes","Extra work requested; ","")&IF($N8="Yes","Exceeding expected hours; ","")&IF($O8="Yes","Expenses over budget; ","")&IF($P8="Yes","Margin too low; ","")&IF($Q8="Yes","Payment overdue; ","")&IF($R8="Yes","Scope creep; ","")&IF($S8="No","Compliance unclear; ","")&IF($T8="No","Manufacturing handover unclear; ",""))-2))) | W8: =IF($A8="","",IFERROR(INDEX('Fragrance Projects'!$B$5:$B$64,MATCH($A8,'Fragrance Projects'!$A$5:$A$64,0)),"")) | X8: =IF($A8="","",IFERROR(INDEX('Project Financials'!$U$5:$U$64,MATCH($A8,'Project Financials'!$A$5:$A$64,0)),"")) | Y8: =IF($A8="","",IFERROR(INDEX('Project Financials'!$D$5:$D$64,MATCH($A8,'Project Financials'!$A$5:$A$64,0)),"")) | Z8: =IF($A8="","",IFERROR(INDEX('Project Financials'!$AC$5:$AC$64,MATCH($A8,'Project Financials'!$A$5:$A$64,0)),"")) | AA8: =IF($A8="","",IFERROR(INDEX(Payments!$N$5:$N$64,MATCH($A8,Payments!$B$5:$B$64,0)),""))
B9: =IF($A9="","",IFERROR(INDEX('Fragrance Projects'!$C$5:$C$64,MATCH($A9,'Fragrance Projects'!$A$5:$A$64,0)),"")) | C9: =IF($A9="","",IFERROR(INDEX('Fragrance Projects'!$D$5:$D$64,MATCH($A9,'Fragrance Projects'!$A$5:$A$64,0)),"")) | F9: =IF($A9="","",IFERROR(INDEX(Clients!$R$5:$R$44,MATCH($W9,Clients!$A$5:$A$44,0)),"")) | G9: =IF($A9="","",IF(IFERROR(INDEX(Payments!$G$5:$G$64,MATCH($A9,Payments!$B$5:$B$64,0)),0)>0,"Yes","No")) | H9: =IF($A9="","",IFERROR(INDEX('Fragrance Projects'!$L$5:$L$64,MATCH($A9,'Fragrance Projects'!$A$5:$A$64,0)),"")) | I9: =IF($A9="","",IF(AND(IFERROR(INDEX(Clients!$T$5:$T$44,MATCH($W9,Clients!$A$5:$A$44,0)),"")<>"",IFERROR(INDEX(Clients!$T$5:$T$44,MATCH($W9,Clients!$A$5:$A$44,0)),"")<>"Not Yet Agreed"),"Yes","No")) | O9: =IF($A9="","",IF(AND($Y9<>"",$Y9>0,$X9>0.4*$Y9),"Yes","No")) | P9: =IF($A9="","",IF(AND($Z9<>"",$Z9<0.15),"Yes","No")) | Q9: =IF($A9="","",IF($AA9="Overdue","Yes","No")) | U9: =IF($A9="","",_xlfn.IFS((IF($D9="No",1,0)+IF($E9="No",1,0)+IF($F9="No",1,0)+IF($G9="No",1,0)+IF($I9="No",1,0)+IF($J9="No",1,0)+IF($K9="No",1,0)+IF($L9="Yes",1,0)+IF($M9="Yes",1,0)+IF($N9="Yes",1,0)+IF($O9="Yes",1,0)+IF($P9="Yes",1,0)+IF($Q9="Yes",1,0)+IF($R9="Yes",1,0)+IF($S9="No",1,0)+IF($T9="No",1,0))<=2,"LOW",(IF($D9="No",1,0)+IF($E9="No",1,0)+IF($F9="No",1,0)+IF($G9="No",1,0)+IF($I9="No",1,0)+IF($J9="No",1,0)+IF($K9="No",1,0)+IF($L9="Yes",1,0)+IF($M9="Yes",1,0)+IF($N9="Yes",1,0)+IF($O9="Yes",1,0)+IF($P9="Yes",1,0)+IF($Q9="Yes",1,0)+IF($R9="Yes",1,0)+IF($S9="No",1,0)+IF($T9="No",1,0))<=5,"MEDIUM",TRUE(),"HIGH")) | V9: =IF($A9="","",IF(LEN(IF($D9="No","Scope undefined; ","")&IF($E9="No","Brief unclear; ","")&IF($F9="No","Contract not signed; ","")&IF($G9="No","Deposit unpaid; ","")&IF($I9="No","Ownership not agreed; ","")&IF($J9="No","Deadline unrealistic; ","")&IF($K9="No","Slow client response; ","")&IF($L9="Yes","Brief keeps changing; ","")&IF($M9="Yes","Extra work requested; ","")&IF($N9="Yes","Exceeding expected hours; ","")&IF($O9="Yes","Expenses over budget; ","")&IF($P9="Yes","Margin too low; ","")&IF($Q9="Yes","Payment overdue; ","")&IF($R9="Yes","Scope creep; ","")&IF($S9="No","Compliance unclear; ","")&IF($T9="No","Manufacturing handover unclear; ",""))=0,"None — healthy",LEFT(IF($D9="No","Scope undefined; ","")&IF($E9="No","Brief unclear; ","")&IF($F9="No","Contract not signed; ","")&IF($G9="No","Deposit unpaid; ","")&IF($I9="No","Ownership not agreed; ","")&IF($J9="No","Deadline unrealistic; ","")&IF($K9="No","Slow client response; ","")&IF($L9="Yes","Brief keeps changing; ","")&IF($M9="Yes","Extra work requested; ","")&IF($N9="Yes","Exceeding expected hours; ","")&IF($O9="Yes","Expenses over budget; ","")&IF($P9="Yes","Margin too low; ","")&IF($Q9="Yes","Payment overdue; ","")&IF($R9="Yes","Scope creep; ","")&IF($S9="No","Compliance unclear; ","")&IF($T9="No","Manufacturing handover unclear; ",""),LEN(IF($D9="No","Scope undefined; ","")&IF($E9="No","Brief unclear; ","")&IF($F9="No","Contract not signed; ","")&IF($G9="No","Deposit unpaid; ","")&IF($I9="No","Ownership not agreed; ","")&IF($J9="No","Deadline unrealistic; ","")&IF($K9="No","Slow client response; ","")&IF($L9="Yes","Brief keeps changing; ","")&IF($M9="Yes","Extra work requested; ","")&IF($N9="Yes","Exceeding expected hours; ","")&IF($O9="Yes","Expenses over budget; ","")&IF($P9="Yes","Margin too low; ","")&IF($Q9="Yes","Payment overdue; ","")&IF($R9="Yes","Scope creep; ","")&IF($S9="No","Compliance unclear; ","")&IF($T9="No","Manufacturing handover unclear; ",""))-2))) | W9: =IF($A9="","",IFERROR(INDEX('Fragrance Projects'!$B$5:$B$64,MATCH($A9,'Fragrance Projects'!$A$5:$A$64,0)),"")) | X9: =IF($A9="","",IFERROR(INDEX('Project Financials'!$U$5:$U$64,MATCH($A9,'Project Financials'!$A$5:$A$64,0)),"")) | Y9: =IF($A9="","",IFERROR(INDEX('Project Financials'!$D$5:$D$64,MATCH($A9,'Project Financials'!$A$5:$A$64,0)),"")) | Z9: =IF($A9="","",IFERROR(INDEX('Project Financials'!$AC$5:$AC$64,MATCH($A9,'Project Financials'!$A$5:$A$64,0)),"")) | AA9: =IF($A9="","",IFERROR(INDEX(Payments!$N$5:$N$64,MATCH($A9,Payments!$B$5:$B$64,0)),""))
B10: =IF($A10="","",IFERROR(INDEX('Fragrance Projects'!$C$5:$C$64,MATCH($A10,'Fragrance Projects'!$A$5:$A$64,0)),"")) | C10: =IF($A10="","",IFERROR(INDEX('Fragrance Projects'!$D$5:$D$64,MATCH($A10,'Fragrance Projects'!$A$5:$A$64,0)),"")) | F10: =IF($A10="","",IFERROR(INDEX(Clients!$R$5:$R$44,MATCH($W10,Clients!$A$5:$A$44,0)),"")) | G10: =IF($A10="","",IF(IFERROR(INDEX(Payments!$G$5:$G$64,MATCH($A10,Payments!$B$5:$B$64,0)),0)>0,"Yes","No")) | H10: =IF($A10="","",IFERROR(INDEX('Fragrance Projects'!$L$5:$L$64,MATCH($A10,'Fragrance Projects'!$A$5:$A$64,0)),"")) | I10: =IF($A10="","",IF(AND(IFERROR(INDEX(Clients!$T$5:$T$44,MATCH($W10,Clients!$A$5:$A$44,0)),"")<>"",IFERROR(INDEX(Clients!$T$5:$T$44,MATCH($W10,Clients!$A$5:$A$44,0)),"")<>"Not Yet Agreed"),"Yes","No")) | O10: =IF($A10="","",IF(AND($Y10<>"",$Y10>0,$X10>0.4*$Y10),"Yes","No")) | P10: =IF($A10="","",IF(AND($Z10<>"",$Z10<0.15),"Yes","No")) | Q10: =IF($A10="","",IF($AA10="Overdue","Yes","No")) | U10: =IF($A10="","",_xlfn.IFS((IF($D10="No",1,0)+IF($E10="No",1,0)+IF($F10="No",1,0)+IF($G10="No",1,0)+IF($I10="No",1,0)+IF($J10="No",1,0)+IF($K10="No",1,0)+IF($L10="Yes",1,0)+IF($M10="Yes",1,0)+IF($N10="Yes",1,0)+IF($O10="Yes",1,0)+IF($P10="Yes",1,0)+IF($Q10="Yes",1,0)+IF($R10="Yes",1,0)+IF($S10="No",1,0)+IF($T10="No",1,0))<=2,"LOW",(IF($D10="No",1,0)+IF($E10="No",1,0)+IF($F10="No",1,0)+IF($G10="No",1,0)+IF($I10="No",1,0)+IF($J10="No",1,0)+IF($K10="No",1,0)+IF($L10="Yes",1,0)+IF($M10="Yes",1,0)+IF($N10="Yes",1,0)+IF($O10="Yes",1,0)+IF($P10="Yes",1,0)+IF($Q10="Yes",1,0)+IF($R10="Yes",1,0)+IF($S10="No",1,0)+IF($T10="No",1,0))<=5,"MEDIUM",TRUE(),"HIGH")) | V10: =IF($A10="","",IF(LEN(IF($D10="No","Scope undefined; ","")&IF($E10="No","Brief unclear; ","")&IF($F10="No","Contract not signed; ","")&IF($G10="No","Deposit unpaid; ","")&IF($I10="No","Ownership not agreed; ","")&IF($J10="No","Deadline unrealistic; ","")&IF($K10="No","Slow client response; ","")&IF($L10="Yes","Brief keeps changing; ","")&IF($M10="Yes","Extra work requested; ","")&IF($N10="Yes","Exceeding expected hours; ","")&IF($O10="Yes","Expenses over budget; ","")&IF($P10="Yes","Margin too low; ","")&IF($Q10="Yes","Payment overdue; ","")&IF($R10="Yes","Scope creep; ","")&IF($S10="No","Compliance unclear; ","")&IF($T10="No","Manufacturing handover unclear; ",""))=0,"None — healthy",LEFT(IF($D10="No","Scope undefined; ","")&IF($E10="No","Brief unclear; ","")&IF($F10="No","Contract not signed; ","")&IF($G10="No","Deposit unpaid; ","")&IF($I10="No","Ownership not agreed; ","")&IF($J10="No","Deadline unrealistic; ","")&IF($K10="No","Slow client response; ","")&IF($L10="Yes","Brief keeps changing; ","")&IF($M10="Yes","Extra work requested; ","")&IF($N10="Yes","Exceeding expected hours; ","")&IF($O10="Yes","Expenses over budget; ","")&IF($P10="Yes","Margin too low; ","")&IF($Q10="Yes","Payment overdue; ","")&IF($R10="Yes","Scope creep; ","")&IF($S10="No","Compliance unclear; ","")&IF($T10="No","Manufacturing handover unclear; ",""),LEN(IF($D10="No","Scope undefined; ","")&IF($E10="No","Brief unclear; ","")&IF($F10="No","Contract not signed; ","")&IF($G10="No","Deposit unpaid; ","")&IF($I10="No","Ownership not agreed; ","")&IF($J10="No","Deadline unrealistic; ","")&IF($K10="No","Slow client response; ","")&IF($L10="Yes","Brief keeps changing; ","")&IF($M10="Yes","Extra work requested; ","")&IF($N10="Yes","Exceeding expected hours; ","")&IF($O10="Yes","Expenses over budget; ","")&IF($P10="Yes","Margin too low; ","")&IF($Q10="Yes","Payment overdue; ","")&IF($R10="Yes","Scope creep; ","")&IF($S10="No","Compliance unclear; ","")&IF($T10="No","Manufacturing handover unclear; ",""))-2))) | W10: =IF($A10="","",IFERROR(INDEX('Fragrance Projects'!$B$5:$B$64,MATCH($A10,'Fragrance Projects'!$A$5:$A$64,0)),"")) | X10: =IF($A10="","",IFERROR(INDEX('Project Financials'!$U$5:$U$64,MATCH($A10,'Project Financials'!$A$5:$A$64,0)),"")) | Y10: =IF($A10="","",IFERROR(INDEX('Project Financials'!$D$5:$D$64,MATCH($A10,'Project Financials'!$A$5:$A$64,0)),"")) | Z10: =IF($A10="","",IFERROR(INDEX('Project Financials'!$AC$5:$AC$64,MATCH($A10,'Project Financials'!$A$5:$A$64,0)),"")) | AA10: =IF($A10="","",IFERROR(INDEX(Payments!$N$5:$N$64,MATCH($A10,Payments!$B$5:$B$64,0)),""))
B11: =IF($A11="","",IFERROR(INDEX('Fragrance Projects'!$C$5:$C$64,MATCH($A11,'Fragrance Projects'!$A$5:$A$64,0)),"")) | C11: =IF($A11="","",IFERROR(INDEX('Fragrance Projects'!$D$5:$D$64,MATCH($A11,'Fragrance Projects'!$A$5:$A$64,0)),"")) | F11: =IF($A11="","",IFERROR(INDEX(Clients!$R$5:$R$44,MATCH($W11,Clients!$A$5:$A$44,0)),"")) | G11: =IF($A11="","",IF(IFERROR(INDEX(Payments!$G$5:$G$64,MATCH($A11,Payments!$B$5:$B$64,0)),0)>0,"Yes","No")) | H11: =IF($A11="","",IFERROR(INDEX('Fragrance Projects'!$L$5:$L$64,MATCH($A11,'Fragrance Projects'!$A$5:$A$64,0)),"")) | I11: =IF($A11="","",IF(AND(IFERROR(INDEX(Clients!$T$5:$T$44,MATCH($W11,Clients!$A$5:$A$44,0)),"")<>"",IFERROR(INDEX(Clients!$T$5:$T$44,MATCH($W11,Clients!$A$5:$A$44,0)),"")<>"Not Yet Agreed"),"Yes","No")) | O11: =IF($A11="","",IF(AND($Y11<>"",$Y11>0,$X11>0.4*$Y11),"Yes","No")) | P11: =IF($A11="","",IF(AND($Z11<>"",$Z11<0.15),"Yes","No")) | Q11: =IF($A11="","",IF($AA11="Overdue","Yes","No")) | U11: =IF($A11="","",_xlfn.IFS((IF($D11="No",1,0)+IF($E11="No",1,0)+IF($F11="No",1,0)+IF($G11="No",1,0)+IF($I11="No",1,0)+IF($J11="No",1,0)+IF($K11="No",1,0)+IF($L11="Yes",1,0)+IF($M11="Yes",1,0)+IF($N11="Yes",1,0)+IF($O11="Yes",1,0)+IF($P11="Yes",1,0)+IF($Q11="Yes",1,0)+IF($R11="Yes",1,0)+IF($S11="No",1,0)+IF($T11="No",1,0))<=2,"LOW",(IF($D11="No",1,0)+IF($E11="No",1,0)+IF($F11="No",1,0)+IF($G11="No",1,0)+IF($I11="No",1,0)+IF($J11="No",1,0)+IF($K11="No",1,0)+IF($L11="Yes",1,0)+IF($M11="Yes",1,0)+IF($N11="Yes",1,0)+IF($O11="Yes",1,0)+IF($P11="Yes",1,0)+IF($Q11="Yes",1,0)+IF($R11="Yes",1,0)+IF($S11="No",1,0)+IF($T11="No",1,0))<=5,"MEDIUM",TRUE(),"HIGH")) | V11: =IF($A11="","",IF(LEN(IF($D11="No","Scope undefined; ","")&IF($E11="No","Brief unclear; ","")&IF($F11="No","Contract not signed; ","")&IF($G11="No","Deposit unpaid; ","")&IF($I11="No","Ownership not agreed; ","")&IF($J11="No","Deadline unrealistic; ","")&IF($K11="No","Slow client response; ","")&IF($L11="Yes","Brief keeps changing; ","")&IF($M11="Yes","Extra work requested; ","")&IF($N11="Yes","Exceeding expected hours; ","")&IF($O11="Yes","Expenses over budget; ","")&IF($P11="Yes","Margin too low; ","")&IF($Q11="Yes","Payment overdue; ","")&IF($R11="Yes","Scope creep; ","")&IF($S11="No","Compliance unclear; ","")&IF($T11="No","Manufacturing handover unclear; ",""))=0,"None — healthy",LEFT(IF($D11="No","Scope undefined; ","")&IF($E11="No","Brief unclear; ","")&IF($F11="No","Contract not signed; ","")&IF($G11="No","Deposit unpaid; ","")&IF($I11="No","Ownership not agreed; ","")&IF($J11="No","Deadline unrealistic; ","")&IF($K11="No","Slow client response; ","")&IF($L11="Yes","Brief keeps changing; ","")&IF($M11="Yes","Extra work requested; ","")&IF($N11="Yes","Exceeding expected hours; ","")&IF($O11="Yes","Expenses over budget; ","")&IF($P11="Yes","Margin too low; ","")&IF($Q11="Yes","Payment overdue; ","")&IF($R11="Yes","Scope creep; ","")&IF($S11="No","Compliance unclear; ","")&IF($T11="No","Manufacturing handover unclear; ",""),LEN(IF($D11="No","Scope undefined; ","")&IF($E11="No","Brief unclear; ","")&IF($F11="No","Contract not signed; ","")&IF($G11="No","Deposit unpaid; ","")&IF($I11="No","Ownership not agreed; ","")&IF($J11="No","Deadline unrealistic; ","")&IF($K11="No","Slow client response; ","")&IF($L11="Yes","Brief keeps changing; ","")&IF($M11="Yes","Extra work requested; ","")&IF($N11="Yes","Exceeding expected hours; ","")&IF($O11="Yes","Expenses over budget; ","")&IF($P11="Yes","Margin too low; ","")&IF($Q11="Yes","Payment overdue; ","")&IF($R11="Yes","Scope creep; ","")&IF($S11="No","Compliance unclear; ","")&IF($T11="No","Manufacturing handover unclear; ",""))-2))) | W11: =IF($A11="","",IFERROR(INDEX('Fragrance Projects'!$B$5:$B$64,MATCH($A11,'Fragrance Projects'!$A$5:$A$64,0)),"")) | X11: =IF($A11="","",IFERROR(INDEX('Project Financials'!$U$5:$U$64,MATCH($A11,'Project Financials'!$A$5:$A$64,0)),"")) | Y11: =IF($A11="","",IFERROR(INDEX('Project Financials'!$D$5:$D$64,MATCH($A11,'Project Financials'!$A$5:$A$64,0)),"")) | Z11: =IF($A11="","",IFERROR(INDEX('Project Financials'!$AC$5:$AC$64,MATCH($A11,'Project Financials'!$A$5:$A$64,0)),"")) | AA11: =IF($A11="","",IFERROR(INDEX(Payments!$N$5:$N$64,MATCH($A11,Payments!$B$5:$B$64,0)),""))
B12: =IF($A12="","",IFERROR(INDEX('Fragrance Projects'!$C$5:$C$64,MATCH($A12,'Fragrance Projects'!$A$5:$A$64,0)),"")) | C12: =IF($A12="","",IFERROR(INDEX('Fragrance Projects'!$D$5:$D$64,MATCH($A12,'Fragrance Projects'!$A$5:$A$64,0)),"")) | F12: =IF($A12="","",IFERROR(INDEX(Clients!$R$5:$R$44,MATCH($W12,Clients!$A$5:$A$44,0)),"")) | G12: =IF($A12="","",IF(IFERROR(INDEX(Payments!$G$5:$G$64,MATCH($A12,Payments!$B$5:$B$64,0)),0)>0,"Yes","No")) | H12: =IF($A12="","",IFERROR(INDEX('Fragrance Projects'!$L$5:$L$64,MATCH($A12,'Fragrance Projects'!$A$5:$A$64,0)),"")) | I12: =IF($A12="","",IF(AND(IFERROR(INDEX(Clients!$T$5:$T$44,MATCH($W12,Clients!$A$5:$A$44,0)),"")<>"",IFERROR(INDEX(Clients!$T$5:$T$44,MATCH($W12,Clients!$A$5:$A$44,0)),"")<>"Not Yet Agreed"),"Yes","No")) | O12: =IF($A12="","",IF(AND($Y12<>"",$Y12>0,$X12>0.4*$Y12),"Yes","No")) | P12: =IF($A12="","",IF(AND($Z12<>"",$Z12<0.15),"Yes","No")) | Q12: =IF($A12="","",IF($AA12="Overdue","Yes","No")) | U12: =IF($A12="","",_xlfn.IFS((IF($D12="No",1,0)+IF($E12="No",1,0)+IF($F12="No",1,0)+IF($G12="No",1,0)+IF($I12="No",1,0)+IF($J12="No",1,0)+IF($K12="No",1,0)+IF($L12="Yes",1,0)+IF($M12="Yes",1,0)+IF($N12="Yes",1,0)+IF($O12="Yes",1,0)+IF($P12="Yes",1,0)+IF($Q12="Yes",1,0)+IF($R12="Yes",1,0)+IF($S12="No",1,0)+IF($T12="No",1,0))<=2,"LOW",(IF($D12="No",1,0)+IF($E12="No",1,0)+IF($F12="No",1,0)+IF($G12="No",1,0)+IF($I12="No",1,0)+IF($J12="No",1,0)+IF($K12="No",1,0)+IF($L12="Yes",1,0)+IF($M12="Yes",1,0)+IF($N12="Yes",1,0)+IF($O12="Yes",1,0)+IF($P12="Yes",1,0)+IF($Q12="Yes",1,0)+IF($R12="Yes",1,0)+IF($S12="No",1,0)+IF($T12="No",1,0))<=5,"MEDIUM",TRUE(),"HIGH")) | V12: =IF($A12="","",IF(LEN(IF($D12="No","Scope undefined; ","")&IF($E12="No","Brief unclear; ","")&IF($F12="No","Contract not signed; ","")&IF($G12="No","Deposit unpaid; ","")&IF($I12="No","Ownership not agreed; ","")&IF($J12="No","Deadline unrealistic; ","")&IF($K12="No","Slow client response; ","")&IF($L12="Yes","Brief keeps changing; ","")&IF($M12="Yes","Extra work requested; ","")&IF($N12="Yes","Exceeding expected hours; ","")&IF($O12="Yes","Expenses over budget; ","")&IF($P12="Yes","Margin too low; ","")&IF($Q12="Yes","Payment overdue; ","")&IF($R12="Yes","Scope creep; ","")&IF($S12="No","Compliance unclear; ","")&IF($T12="No","Manufacturing handover unclear; ",""))=0,"None — healthy",LEFT(IF($D12="No","Scope undefined; ","")&IF($E12="No","Brief unclear; ","")&IF($F12="No","Contract not signed; ","")&IF($G12="No","Deposit unpaid; ","")&IF($I12="No","Ownership not agreed; ","")&IF($J12="No","Deadline unrealistic; ","")&IF($K12="No","Slow client response; ","")&IF($L12="Yes","Brief keeps changing; ","")&IF($M12="Yes","Extra work requested; ","")&IF($N12="Yes","Exceeding expected hours; ","")&IF($O12="Yes","Expenses over budget; ","")&IF($P12="Yes","Margin too low; ","")&IF($Q12="Yes","Payment overdue; ","")&IF($R12="Yes","Scope creep; ","")&IF($S12="No","Compliance unclear; ","")&IF($T12="No","Manufacturing handover unclear; ",""),LEN(IF($D12="No","Scope undefined; ","")&IF($E12="No","Brief unclear; ","")&IF($F12="No","Contract not signed; ","")&IF($G12="No","Deposit unpaid; ","")&IF($I12="No","Ownership not agreed; ","")&IF($J12="No","Deadline unrealistic; ","")&IF($K12="No","Slow client response; ","")&IF($L12="Yes","Brief keeps changing; ","")&IF($M12="Yes","Extra work requested; ","")&IF($N12="Yes","Exceeding expected hours; ","")&IF($O12="Yes","Expenses over budget; ","")&IF($P12="Yes","Margin too low; ","")&IF($Q12="Yes","Payment overdue; ","")&IF($R12="Yes","Scope creep; ","")&IF($S12="No","Compliance unclear; ","")&IF($T12="No","Manufacturing handover unclear; ",""))-2))) | W12: =IF($A12="","",IFERROR(INDEX('Fragrance Projects'!$B$5:$B$64,MATCH($A12,'Fragrance Projects'!$A$5:$A$64,0)),"")) | X12: =IF($A12="","",IFERROR(INDEX('Project Financials'!$U$5:$U$64,MATCH($A12,'Project Financials'!$A$5:$A$64,0)),"")) | Y12: =IF($A12="","",IFERROR(INDEX('Project Financials'!$D$5:$D$64,MATCH($A12,'Project Financials'!$A$5:$A$64,0)),"")) | Z12: =IF($A12="","",IFERROR(INDEX('Project Financials'!$AC$5:$AC$64,MATCH($A12,'Project Financials'!$A$5:$A$64,0)),"")) | AA12: =IF($A12="","",IFERROR(INDEX(Payments!$N$5:$N$64,MATCH($A12,Payments!$B$5:$B$64,0)),""))
B13: =IF($A13="","",IFERROR(INDEX('Fragrance Projects'!$C$5:$C$64,MATCH($A13,'Fragrance Projects'!$A$5:$A$64,0)),"")) | C13: =IF($A13="","",IFERROR(INDEX('Fragrance Projects'!$D$5:$D$64,MATCH($A13,'Fragrance Projects'!$A$5:$A$64,0)),"")) | F13: =IF($A13="","",IFERROR(INDEX(Clients!$R$5:$R$44,MATCH($W13,Clients!$A$5:$A$44,0)),"")) | G13: =IF($A13="","",IF(IFERROR(INDEX(Payments!$G$5:$G$64,MATCH($A13,Payments!$B$5:$B$64,0)),0)>0,"Yes","No")) | H13: =IF($A13="","",IFERROR(INDEX('Fragrance Projects'!$L$5:$L$64,MATCH($A13,'Fragrance Projects'!$A$5:$A$64,0)),"")) | I13: =IF($A13="","",IF(AND(IFERROR(INDEX(Clients!$T$5:$T$44,MATCH($W13,Clients!$A$5:$A$44,0)),"")<>"",IFERROR(INDEX(Clients!$T$5:$T$44,MATCH($W13,Clients!$A$5:$A$44,0)),"")<>"Not Yet Agreed"),"Yes","No")) | O13: =IF($A13="","",IF(AND($Y13<>"",$Y13>0,$X13>0.4*$Y13),"Yes","No")) | P13: =IF($A13="","",IF(AND($Z13<>"",$Z13<0.15),"Yes","No")) | Q13: =IF($A13="","",IF($AA13="Overdue","Yes","No")) | U13: =IF($A13="","",_xlfn.IFS((IF($D13="No",1,0)+IF($E13="No",1,0)+IF($F13="No",1,0)+IF($G13="No",1,0)+IF($I13="No",1,0)+IF($J13="No",1,0)+IF($K13="No",1,0)+IF($L13="Yes",1,0)+IF($M13="Yes",1,0)+IF($N13="Yes",1,0)+IF($O13="Yes",1,0)+IF($P13="Yes",1,0)+IF($Q13="Yes",1,0)+IF($R13="Yes",1,0)+IF($S13="No",1,0)+IF($T13="No",1,0))<=2,"LOW",(IF($D13="No",1,0)+IF($E13="No",1,0)+IF($F13="No",1,0)+IF($G13="No",1,0)+IF($I13="No",1,0)+IF($J13="No",1,0)+IF($K13="No",1,0)+IF($L13="Yes",1,0)+IF($M13="Yes",1,0)+IF($N13="Yes",1,0)+IF($O13="Yes",1,0)+IF($P13="Yes",1,0)+IF($Q13="Yes",1,0)+IF($R13="Yes",1,0)+IF($S13="No",1,0)+IF($T13="No",1,0))<=5,"MEDIUM",TRUE(),"HIGH")) | V13: =IF($A13="","",IF(LEN(IF($D13="No","Scope undefined; ","")&IF($E13="No","Brief unclear; ","")&IF($F13="No","Contract not signed; ","")&IF($G13="No","Deposit unpaid; ","")&IF($I13="No","Ownership not agreed; ","")&IF($J13="No","Deadline unrealistic; ","")&IF($K13="No","Slow client response; ","")&IF($L13="Yes","Brief keeps changing; ","")&IF($M13="Yes","Extra work requested; ","")&IF($N13="Yes","Exceeding expected hours; ","")&IF($O13="Yes","Expenses over budget; ","")&IF($P13="Yes","Margin too low; ","")&IF($Q13="Yes","Payment overdue; ","")&IF($R13="Yes","Scope creep; ","")&IF($S13="No","Compliance unclear; ","")&IF($T13="No","Manufacturing handover unclear; ",""))=0,"None — healthy",LEFT(IF($D13="No","Scope undefined; ","")&IF($E13="No","Brief unclear; ","")&IF($F13="No","Contract not signed; ","")&IF($G13="No","Deposit unpaid; ","")&IF($I13="No","Ownership not agreed; ","")&IF($J13="No","Deadline unrealistic; ","")&IF($K13="No","Slow client response; ","")&IF($L13="Yes","Brief keeps changing; ","")&IF($M13="Yes","Extra work requested; ","")&IF($N13="Yes","Exceeding expected hours; ","")&IF($O13="Yes","Expenses over budget; ","")&IF($P13="Yes","Margin too low; ","")&IF($Q13="Yes","Payment overdue; ","")&IF($R13="Yes","Scope creep; ","")&IF($S13="No","Compliance unclear; ","")&IF($T13="No","Manufacturing handover unclear; ",""),LEN(IF($D13="No","Scope undefined; ","")&IF($E13="No","Brief unclear; ","")&IF($F13="No","Contract not signed; ","")&IF($G13="No","Deposit unpaid; ","")&IF($I13="No","Ownership not agreed; ","")&IF($J13="No","Deadline unrealistic; ","")&IF($K13="No","Slow client response; ","")&IF($L13="Yes","Brief keeps changing; ","")&IF($M13="Yes","Extra work requested; ","")&IF($N13="Yes","Exceeding expected hours; ","")&IF($O13="Yes","Expenses over budget; ","")&IF($P13="Yes","Margin too low; ","")&IF($Q13="Yes","Payment overdue; ","")&IF($R13="Yes","Scope creep; ","")&IF($S13="No","Compliance unclear; ","")&IF($T13="No","Manufacturing handover unclear; ",""))-2))) | W13: =IF($A13="","",IFERROR(INDEX('Fragrance Projects'!$B$5:$B$64,MATCH($A13,'Fragrance Projects'!$A$5:$A$64,0)),"")) | X13: =IF($A13="","",IFERROR(INDEX('Project Financials'!$U$5:$U$64,MATCH($A13,'Project Financials'!$A$5:$A$64,0)),"")) | Y13: =IF($A13="","",IFERROR(INDEX('Project Financials'!$D$5:$D$64,MATCH($A13,'Project Financials'!$A$5:$A$64,0)),"")) | Z13: =IF($A13="","",IFERROR(INDEX('Project Financials'!$AC$5:$AC$64,MATCH($A13,'Project Financials'!$A$5:$A$64,0)),"")) | AA13: =IF($A13="","",IFERROR(INDEX(Payments!$N$5:$N$64,MATCH($A13,Payments!$B$5:$B$64,0)),""))
